Workbook

Sheet RELATORIO
A1: CORPO DE BOMBEIROS MILITAR DO AMAZONAS | AQ1: DATA DE HOJE
A2: RELATÓRIO DE OCORRÊNCIAS 2026
A3: 1 | B3: Comandante do Incidente: | G3: CEL QOBM BORGES | W3: Período Operacional: | AD3: =TEXT(AQ3,"DD") -> 02 | AE3: =UPPER("/ "&TEXT(AQ3,"MMM")&" / 2026 - 8h00") -> / AGO / 2026 - 8H00 | AQ3: 46236
A4: 2 | B4: Chefe de Operações Capital: | G4: CEL QOBM MENEZES | W4: Próximo Período Operacional: | AD4: =TEXT(AQ7,"DD") -> 03 | AE4: =UPPER("/ "&TEXT(AQ7,"MMM")&" / 2026 - 8h00") -> / AGO / 2026 - 8H00
A5: 3 | B5: Chefe de Operações Interior: | G5: CEL QOBM MONTEIRO | W5: Reunião de Planejamento: | AD5: =TEXT($AQ$3,"DD") -> 02 | AE5: =UPPER("/ "&TEXT(AQ3,"MMM")&" / 2026 - 8h15") -> / AGO / 2026 - 8H15 | AQ5: =AQ3-1 -> 46235 | AW5: não mexer
A6: 4 | B6: Coordenador da Sala de Situação: | G6: TC QOBM FERREIRA | W6: Reunião de Briefing: | AD6: =TEXT($AQ$3,"DD") -> 02 | AE6: =UPPER("/ "&TEXT(AQ3,"MMM")&" / 2026 - 8h30") -> / AGO / 2026 - 8H30
A7: 5 | AQ7: =AQ3+1 -> 46237 | AW7: não mexer
A9: EFETIVO | G9: EFETIVO | P9: EFETIVO | Y9: RESUMO EFETIVO
A10: Nº | B10: MUNICÍPIO | C10: SERV. ORDINÁRIO | D10: SEG | E10: BRIGADISTA | G10: MUNICÍPIO | L10: SERV. ORDINÁRIO | M10: SEG | N10: BRIGADISTA | P10: BASES TEMPORÁRIAS | U10: SERV. ORDINÁRIO | V10: SEG | W10: BRIGADISTA | Y10: MISSÃO | AB10: CAPITAL | AC10: INTERIOR | AE10: TOTAL
A11: 1 | B11: =B63 -> Manaus | C11: 114 | D11: 10 | E11: 0 | G11: Manaquiri | L11: 4 | N11: 0 | P11: Boca do Acre | U11: 8 | W11: 0 | Y11: SV ORD | AB11: =SUM(C11) -> 114 | AC11: =SUM(C12:C23,L11:L23,U11:U16) -> 217 | AE11: =SUM(AB11:AD11) -> 331
B12: Apuí | C12: 12 | E12: 11 | G12: Manacapuru | L12: 6 | N12: 0 | P12: Borba | U12: 3 | W12: 0 | Y12: SEG | AB12: =SUM(D11) -> 10 | AC12: =SUM(D12:D23,M11:M23,V11:V16) -> 6 | AE12: =SUM(AB12:AD12) -> 16
B13: =B65 -> Atalaia do Norte | C13: 7 | E13: 0 | G13: Manicoré | L13: 13 | N13: 12 | P13: Canutama | U13: 5 | W13: 0 | Y13: BRIGADISTA | AB13: =SUM(E11) -> 0 | AC13: =SUM(E12:E23,N11:N23,W11:W16) -> 90 | AE13: =SUM(AB13:AD13) -> 90
B14: =B66 -> Autazes | C14: 14 | E14: 13 | G14: Maués | L14: 11 | M14: 2 | N14: 13 | P14: Careiro | U14: 5 | W14: 0 | Y14: TOTAL | AB14: =SUM(AB11:AB13) -> 124 | AC14: =SUM(AC11:AD13) -> 313 | AE14: =SUM(AE11:AF13) -> 437
B15: Barcelos | C15: 7 | E15: 12 | G15: Novo Airão | L15: 3 | N15: 2 | P15: Nhamundá | U15: 2 | W15: 0
B16: Coari | C16: 12 | E16: 0 | G16: Novo Aripuanã | L16: 12 | M16: 2 | N16: 7 | P16: Uricurituba | U16: 0 | W16: 0
B17: Envira | C17: 4 | E17: 0 | G17: Parintins | L17: 8 | N17: 0 | P17: =B135 -> TOTAL | U17: =SUM(U11:U16) -> 23 | V17: =SUM(V11:V16) -> 0 | W17: =SUM(W11:W16) -> 0
B18: Humaitá | C18: 21 | E18: 0 | G18: Presidente Figueiredo | L18: 6 | N18: 0
A19: 2 | B19: Iranduba | C19: 6 | D19: 2 | E19: 0 | G19: Rio Preto da Eva | L19: 5 | N19: 2
A20: 3 | B20: Itacoatiara | C20: 3 | E20: 0 | G20: Tabatinga | L20: 5 | N20: 1 | O20: [
B21: Itapiranga | C21: 7 | E21: 12
B22: Jutaí | C22: 5 | E22: 0 | G22: Tapauá | L22: 4 | N22: 0
B23: Lábrea | C23: 13 | E23: 0 | G23: Tefé | L23: 6 | N23: 5
G24: Total | L24: =SUM(C11:C23,L11:L23) -> 308 | M24: =SUM(D11:D23,M11:M23) -> 16 | N24: =SUM(E11:E23,N11:N23) -> 90
A26: RECURSOS | AD26: RESUMO RECURSOS | AJ26: RESUMO RECURSOS
A27: Nº | B27: MUNICÍPIO | C27: ABT | D27: AT | E27: ATP | F27: ATA | G27: ABF | H27: ATF | I27: ABS | J27: PIPA | K27: DOSA | L27: CRS | M27: AR | N27: UR | O27: GSE | P27: MT | Q27: TA | R27: EMBARCAÇÃO | S27: PICAPE FN | T27: PICAPE MUNI | U27: AUTOARP | V27: PICAPE ESFRON | W27: HELICÓPTERO | X27: AVIÃO | Y27: JET SKI | Z27: QUADRICICLO | AA27: AEM | AB27: TOTAL | AD27: RECURSOS | AG27: QTD | AJ27: RECURSOS | AM27: QTD
A28: 1 | B28: =B63 -> Manaus | C28: 5 | F28: 1 | G28: 1 | K28: 3 | L28: 1 | M28: 6 | N28: 6 | O28: 3 | R28: 1 | U28: 1 | Y28: 1 | Z28: 1 | AB28: =SUM(C28:AA28) -> 30 | AD28: =C27 -> ABT | AG28: =C59 -> 17 | AJ28: =P27 -> MT | AM28: =P59 -> 11
B29: Apuí | H29: 1 | M29: 2 | AB29: =SUM(C29:AA29) -> 3 | AD29: =D27 -> AT | AG29: =D59 -> 2 | AJ29: =Q27 -> TA | AM29: =Q59 -> 0
B30: =B65 -> Atalaia do Norte | H30: 1 | AB30: =SUM(C30:AA30) -> 1 | AD30: =AA27 -> AEM | AG30: =AA59 -> 0 | AJ30: =Z27 -> QUADRICICLO | AM30: =Z59 -> 1
B31: =B66 -> Autazes | H31: 1 | M31: 2 | AB31: =SUM(C31:AA31) -> 3 | AD31: =E27 -> ATP | AG31: =E59 -> 2 | AJ31: =R27 -> EMBARCAÇÃO | AM31: =R59 -> 14
B32: Barcelos | H32: 1 | M32: 1 | AB32: =SUM(C32:AA32) -> 2 | AD32: =F27 -> ATA | AG32: =F59 -> 3 | AJ32: =S27 -> PICAPE FN | AM32: =S59 -> 0
B33: Boca do Acre | H33: 1 | M33: 1 | AB33: =SUM(C33:AA33) -> 2 | AD33: =G27 -> ABF | AG33: =G59 -> 2 | AJ33: =T27 -> PICAPE MUNI | AM33: =T59 -> 0
B34: =B69 -> Borba | F34: 1 | AB34: =SUM(C34:AA34) -> 1 | AD34: =H27 -> ATF | AG34: =H59 -> 17 | AJ34: =U27 -> AUTOARP | AM34: =U59 -> 1
B35: Canutama | M35: 1 | AB35: =SUM(C35:AA35) -> 1 | AD35: =I27 -> ABS | AG35: =I59 -> 2 | AJ35: =V27 -> PICAPE ESFRON | AM35: =V59 -> 0
B36: Careiro | M36: 1 | AB36: =SUM(C36:AA36) -> 1 | AD36: =J27 -> PIPA | AG36: =J59 -> 0 | AJ36: =W27 -> HELICÓPTERO | AM36: =W59 -> 0
B37: Coari | H37: 1 | M37: 1 | AB37: =SUM(C37:AA37) -> 2 | AD37: =K27 -> DOSA | AG37: =K59 -> 5 | AJ37: =X27 -> AVIÃO | AM37: =X59 -> 0
B38: Envira | H38: 1 | AB38: =SUM(C38:AA38) -> 1 | AD38: =L27 -> CRS | AG38: =L59 -> 1 | AJ38: =Y27 -> JET SKI | AM38: =Y59 -> 5
A39: 2 | B39: =B74 -> Humaitá | G39: 1 | M39: 1 | N39: 1 | R39: 2 | AB39: =SUM(C39:AA39) -> 5 | AD39: =M27 -> AR | AG39: =M59 -> 39
A40: 3 | B40: =B75 -> Iranduba | C40: 1 | M40: 2 | N40: 1 | P40: 1 | AB40: =SUM(C40:AA40) -> 5 | AD40: =N27 -> UR | AG40: =N59 -> 17
A41: 4 | B41: =B76 -> Itacoatiara | C41: 1 | I41: 1 | M41: 1 | N41: 1 | P41: 2 | R41: 1 | AB41: =SUM(C41:AA41) -> 7 | AD41: =O27 -> GSE | AG41: =O59 -> 5
B42: Itapiranga | H42: 1 | M42: 1 | AB42: =SUM(C42:AA42) -> 2 | AD42: TOTAL RECURSOS | AM42: =SUM(AG28:AH41,AM28:AN41) -> 144
B43: =B78 -> Jutaí | H43: 1 | M43: 1 | AB43: =SUM(C43:AA43) -> 2
A44: 5 | B44: =B79 -> Lábrea | H44: 1 | M44: 2 | AB44: =SUM(C44:AA44) -> 3
B45: =B80 -> Manacapuru | C45: 2 | M45: 1 | N45: 1 | P45: 1 | R45: 1 | Y45: 1 | AB45: =SUM(C45:AA45) -> 7
B46: =B81 -> Manaquiri | H46: 1 | M46: 1 | AB46: =SUM(C46:AA46) -> 2
B47: Manicoré | H47: 1 | M47: 1 | O47: 1 | AB47: =SUM(C47:AA47) -> 3
B48: Maués | H48: 1 | M48: 1 | AB48: =SUM(C48:AA48) -> 2
B49: Nhamundá | AB49: =SUM(C49:AA49) -> 0
A50: 6 | B50: =B85 -> Novo Airão | C50: 1 | D50: 2 | M50: 1 | R50: 1 | Y50: 1 | AB50: =SUM(C50:AA50) -> 6
B51: =B86 -> Novo Aripuanã | H51: 1 | M51: 2 | AB51: =SUM(C51:AA51) -> 3
A52: 7 | B52: =B87 -> Parintins | C52: 2 | E52: 2 | F52: 1 | H52: 1 | M52: 3 | N52: 2 | O52: 1 | P52: 2 | R52: 3 | Y52: 1 | AB52: =SUM(C52:AA52) -> 18
A53: 8 | B53: =B88 -> Presidente Figueiredo | C53: 1 | M53: 1 | N53: 1 | R53: 1 | Y53: 1 | AB53: =SUM(C53:AA53) -> 5
A54: 9 | B54: =B89 -> Rio Preto da Eva | C54: 1 | H54: 1 | M54: 1 | N54: 2 | P54: 2 | R54: 2 | AB54: =SUM(C54:AA54) -> 9
A55: 10 | B55: =B90 -> Tabatinga | C55: 1 | K55: 1 | M55: 1 | N55: 1 | P55: 1 | R55: 1 | AB55: =SUM(C55:AA55) -> 6
B56: =B91 -> Tapauá | H56: 1 | M56: 1 | AB56: =SUM(C56:AA56) -> 2
B57: Tefé | C57: 2 | I57: 1 | K57: 1 | M57: 1 | N57: 1 | P57: 2 | R57: 1 | AB57: =SUM(C57:AA57) -> 9
A58: 11 | B58: Urucurituba | M58: 1 | AB58: =SUM(C58:AA58) -> 1
B59: TOTAL GERAL | C59: =SUM(C28:C58) -> 17 | D59: =SUM(D28:D58) -> 2 | E59: =SUM(E28:E58) -> 2 | F59: =SUM(F28:F58) -> 3 | G59: =SUM(G28:G58) -> 2 | H59: =SUM(H28:H58) -> 17 | I59: =SUM(I28:I58) -> 2 | J59: =SUM(J28:J58) -> 0 | ... AB59: =SUM(AB28:AB58) -> 144
A61: =CONCATENATE("INCÊNDIOS - OCORRÊNCIAS DIÁRIAS EM "&TEXT(AQ3,"DD")&"/"&TEXT(AQ3,"MM")&"/"&TEXT(AQ3,"AAA")) -> INCÊNDIOS - OCORRÊNCIAS DIÁRIAS EM 02/08/2026 | P61: =CONCATENATE("INCÊNDIOS - OCORRÊNCIAS DE 01/06/2026 À "&TEXT(AQ3,"DD")&"/"&TEXT(AQ3,"MM")&"/"&TEXT(AQ3,"AAA")) -> INCÊNDIOS - OCORRÊNCIAS DE 01/06/2026 À 02/08/2026 | AQ61: =AQ5 -> 46235
A62: Nº | B62: MUNICÍPIO | C62: INCÊNDIO URBANO | F62: INCÊNDIO FLORESTAL | I62: FOCOS COMBATIDOS | M62: TOTAL DE OCORRÊNCIAS | P62: Nº | Q62: MUNICÍPIO | U62: INCÊNDIO URBANO | X62: INCÊNDIO FLORESTAL | AA62: FOCOS COMBATIDOS | AD62: FOCOS DETECTADOS SATÉLITE | AF62: TOTAL DE ÁREA POR METROS² | AJ62: TOTAL DE OCORRÊNCIAS | AQ62: Nº | AR62: MUNICÍPIO | AV62: INCÊNDIO URBANO | AY62: INCÊNDIO FLORESTAL | BB62: FOCOS COMBATIDOS | BE62: FOCOS POR SATÉLITE | BG62: TOTAL DE ÁREA POR METROS² | BK62: TOTAL DE OCORRÊNCIAS
A63: 1 | B63: Manaus | C63: 6 | F63: 19 | I63: 45 | M63: =SUM(C63:H63) -> 25 | P63: 1 | Q63: =B63 -> Manaus | U63: =AV63+C63 -> 260 | X63: =F63+AY63 -> 158 | AA63: =I63+BB63 -> 318 | AD63: 5 | AF63: 35406 | AJ63: =SUM(U63:Z63) -> 418 | AQ63: 1 | AR63: Manaus | AV63: 254 | AY63: 139 | BB63: 273 | BE63: 5 | BG63: 24730 | BK63: 393
B64: Apuí | M64: =SUM(C64:H64) -> 0 | P64: 2 | Q64: Apuí | U64: =AV64+C64 -> 1 | X64: =F64+AY64 -> 9 | AA64: =I64+BB64 -> 25 | AD64: 18 | AF64: 900 | AJ64: =SUM(U64:Z64) -> 10 | AQ64: 2 | AR64: Apuí | AV64: 1 | AY64: 9 | BB64: 25 | BE64: 14 | BG64: 900 | BK64: 10
B65: Atalaia do Norte | M65: =SUM(C65:H65) -> 0 | P65: 3 | Q65: =B65 -> Atalaia do Norte | U65: =AV65+C65 -> 0 | X65: =F65+AY65 -> 1 | AA65: =I65+BB65 -> 4 | AD65: 3 | AF65: 650 | AJ65: =SUM(U65:Z65) -> 1 | AQ65: 3 | AR65: Atalaia do Norte | AV65: 0 | AY65: 1 | BB65: 4 | BE65: 3 | BG65: 650 | BK65: 1
A66: 2 | B66: Autazes | M66: =SUM(C66:H66) -> 0 | P66: 4 | Q66: =B66 -> Autazes | U66: =AV66+C66 -> 9 | X66: =F66+AY66 -> 11 | AA66: =I66+BB66 -> 33 | AD66: 21 | AF66: 8050 | AJ66: =SUM(U66:Z66) -> 20 | AQ66: 4 | AR66: Autazes | AV66: 9 | AY66: 11 | BB66: 33 | BE66: 22 | BG66: 7650 | BK66: 20
B67: Barcelos | M67: =SUM(C67:H67) -> 0 | P67: 5 | Q67: Barcelos | U67: =AV67+C67 -> 1 | X67: =F67+AY67 -> 0 | AA67: =I67+BB67 -> 0 | AD67: 10 | AF67: 450 | AJ67: =SUM(U67:Z67) -> 1 | AQ67: 5 | AR67: Barcelos | AV67: 1 | AY67: 0 | BB67: 0 | BE67: 10 | BG67: 450 | BK67: 1
B68: Boca de Acre | M68: =SUM(C68:H68) -> 0 | P68: 6 | Q68: Boca do Acre | U68: =AV68+C68 -> 1 | X68: =F68+AY68 -> 13 | AA68: =I68+BB68 -> 74 | AD68: 8 | AF68: 22250 | AJ68: =SUM(U68:Z68) -> 14 | AQ68: 6 | AR68: Boca do Acre | AV68: 1 | AY68: 13 | BB68: 74 | BE68: 8 | BG68: 22250 | BK68: 14
B69: Borba | M69: =SUM(C69:H69) -> 0 | P69: 7 | Q69: =B69 -> Borba | U69: =AV69+C69 -> 3 | X69: =F69+AY69 -> 7 | AA69: =I69+BB69 -> 47 | AD69: 4 | AF69: 42750 | AJ69: =SUM(U69:Z69) -> 10 | AQ69: 7 | AR69: Borba | AV69: 3 | AY69: 7 | BB69: 47 | BE69: 4 | BG69: 42750 | BK69: 10
B70: Canutama | M70: =SUM(C70:H70) -> 0 | P70: 8 | Q70: Canutama | U70: =AV70+C70 -> 1 | X70: =F70+AY70 -> 2 | AA70: =I70+BB70 -> 5 | AD70: 25 | AF70: 60 | AJ70: =SUM(U70:Z70) -> 3 | AQ70: 8 | AR70: Canutama | AV70: 1 | AY70: 2 | BB70: 5 | BE70: 24 | BG70: 60 | BK70: 3
B71: Careiro | F71: 2 | I71: 4 | M71: =SUM(C71:H71) -> 2 | P71: 9 | Q71: =B71 -> Careiro | U71: =AV71+C71 -> 2 | X71: =F71+AY71 -> 4 | AA71: =I71+BB71 -> 8 | AD71: 7 | AF71: 500 | AJ71: =SUM(U71:Z71) -> 6 | AQ71: 9 | AR71: Careiro | AV71: 2 | AY71: 2 | BB71: 4 | BE71: 3 | BG71: 50 | BK71: 4
B72: Coari | M72: =SUM(C72:H72) -> 0 | P72: 10 | Q72: Coari | U72: =AV72+C72 -> 3 | X72: =F72+AY72 -> 0 | AA72: =I72+BB72 -> 0 | AD72: 0 | AF72: 0 | AJ72: =SUM(U72:Z72) -> 3 | AQ72: 10 | AR72: Coari | AV72: 3 | AY72: 0 | BB72: 0 | BE72: 0 | BG72: 0 | BK72: 3
B73: Envira | P73: 11 | Q73: Envira | U73: =AV73+C73 -> 0 | X73: =F73+AY73 -> 0 | AA73: =I73+BB73 -> 0 | AD73: 0 | AF73: 0 | AJ73: =SUM(U73:Z73) -> 0 | AQ73: 11 | AR73: Envira | AV73: 0 | AY73: 0 | BB73: 0 | BE73: 0 | BG73: 0 | BK73: 0
B74: Humaitá | F74: 2 | I74: 3 | M74: =SUM(C74:H74) -> 2 | P74: 12 | Q74: =B74 -> Humaitá | U74: =AV74+C74 -> 6 | X74: =F74+AY74 -> 39 | AA74: =I74+BB74 -> 308 | AD74: 20 | AF74: 125090 | AJ74: =SUM(U74:Z74) -> 45 | AQ74: 12 | AR74: Humaitá | AV74: 6 | AY74: 37 | BB74: 305 | BE74: 18 | BG74: 109830 | BK74: 43
A75: 3 | B75: Iranduba | F75: 6 | I75: 41 | M75: =SUM(C75:H75) -> 6 | P75: 13 | Q75: =B75 -> Iranduba | U75: =AV75+C75 -> 4 | X75: =F75+AY75 -> 14 | AA75: =I75+BB75 -> 51 | AD75: 4 | AF75: 6980 | AJ75: =SUM(U75:Z75) -> 18 | AQ75: 13 | AR75: Iranduba | AV75: 4 | AY75: 8 | BB75: 10 | BE75: 3 | BG75: 2290 | BK75: 12
A76: 4 | B76: Itacoatiara | M76: =SUM(C76:H76) -> 0 | P76: 14 | Q76: =B76 -> Itacoatiara | U76: =AV76+C76 -> 6 | X76: =F76+AY76 -> 6 | AA76: =I76+BB76 -> 18 | AD76: 13 | AF76: 1600 | AJ76: =SUM(U76:Z76) -> 12 | AQ76: 14 | AR76: Itacoatiara | AV76: 6 | AY76: 6 | BB76: 18 | BE76: 13 | BG76: 1600 | BK76: 12
B77: Itapiranga | M77: =SUM(C77:H77) -> 0 | P77: 15 | Q77: =B77 -> Itapiranga | U77: =AV77+C77 -> 3 | X77: =F77+AY77 -> 8 | AA77: =I77+BB77 -> 147 | AD77: 4 | AF77: 24360 | AJ77: =SUM(U77:Z77) -> 11 | AQ77: 15 | AR77: Itapiranga | AV77: 3 | AY77: 8 | BB77: 147 | BE77: 4 | BG77: 24360 | BK77: 11
B78: Jutaí | M78: =SUM(C78:H78) -> 0 | P78: 16 | Q78: =B78 -> Jutaí | U78: =AV78+C78 -> 0 | X78: =F78+AY78 -> 0 | AA78: =I78+BB78 -> 0 | AD78: 1 | AF78: 0 | AJ78: =SUM(U78:Z78) -> 0 | AQ78: 16 | AR78: Jutaí | AV78: 0 | AY78: 0 | BB78: 0 | BE78: 1 | BG78: 0 | BK78: 0
A79: 5 | B79: Lábrea | M79: =SUM(C79:H79) -> 0 | P79: 17 | Q79: =B79 -> Lábrea | U79: =AV79+C79 -> 4 | X79: =F79+AY79 -> 17 | AA79: =I79+BB79 -> 81 | AD79: 25 | AF79: 80050 | AJ79: =SUM(U79:Z79) -> 21 | AQ79: 17 | AR79: Lábrea | AV79: 4 | AY79: 17 | BB79: 81 | BE79: 25 | BG79: 80050 | BK79: 21
B80: Manacapuru | F80: 2 | I80: 11 | M80: =SUM(C80:H80) -> 2 | P80: 18 | Q80: =B80 -> Manacapuru | U80: =AV80+C80 -> 6 | X80: =F80+AY80 -> 11 | AA80: =I80+BB80 -> 55 | AD80: 12 | AF80: 4200 | AJ80: =SUM(U80:Z80) -> 17 | AQ80: 18 | AR80: Manacapuru | AV80: 6 | AY80: 9 | BB80: 44 | BE80: 11 | BG80: 2750 | BK80: 15
B81: Manaquiri | M81: =SUM(C81:H81) -> 0 | P81: 19 | Q81: =B81 -> Manaquiri | U81: =AV81+C81 -> 1 | X81: =F81+AY81 -> 6 | AA81: =I81+BB81 -> 31 | AD81: 1 | AF81: 1650 | AJ81: =SUM(U81:Z81) -> 7 | AQ81: 19 | AR81: Manaquiri | AV81: 1 | AY81: 6 | BB81: 31 | BE81: 1 | BG81: 1650 | BK81: 7
B82: Manicoré | M82: =SUM(C82:H82) -> 0 | P82: 20 | Q82: =B82 -> Manicoré | U82: =AV82+C82 -> 1 | X82: =F82+AY82 -> 10 | AA82: =I82+BB82 -> 15 | AD82: 30 | AF82: 700 | AJ82: =SUM(U82:Z82) -> 11 | AQ82: 20 | AR82: Manicoré | AV82: 1 | AY82: 10 | BB82: 15 | BE82: 29 | BG82: 700 | BK82: 11
B83: Maués | M83: =SUM(C83:H83) -> 0 | P83: 21 | Q83: =B83 -> Maués | U83: =AV83+C83 -> 6 | X83: =F83+AY83 -> 6 | AA83: =I83+BB83 -> 30 | AD83: 3 | AF83: 400 | AJ83: =SUM(U83:Z83) -> 12 | AQ83: 21 | AR83: Maués | AV83: 6 | AY83: 6 | BB83: 30 | BE83: 3 | BG83: 400 | BK83: 12
B84: Nhamundá | M84: =SUM(C84:H84) -> 0 | P84: 22 | Q84: =B84 -> Nhamundá | U84: =AV84+C84 -> 0 | X84: =F84+AY84 -> 1 | AA84: =I84+BB84 -> 15 | AD84: 4 | AF84: 5000 | AJ84: =SUM(U84:Z84) -> 1 | AQ84: 22 | AR84: Nhamundá | AV84: 0 | AY84: 1 | BB84: 15 | BE84: 4 | BG84: 5000 | BK84: 1
A85: 6 | B85: Novo Airão | M85: =SUM(C85:H85) -> 0 | P85: 23 | Q85: =B85 -> Novo Airão | U85: =AV85+C85 -> 1 | X85: =F85+AY85 -> 3 | AA85: =I85+BB85 -> 2 | AD85: 3 | AF85: 50 | AJ85: =SUM(U85:Z85) -> 4 | AQ85: 23 | AR85: Novo Airão | AV85: 1 | AY85: 3 | BB85: 2 | BE85: 3 | BG85: 50 | BK85: 4
B86: Novo Aripuanã | M86: =SUM(C86:H86) -> 0 | P86: 24 | Q86: =B86 -> Novo Aripuanã | U86: =AV86+C86 -> 1 | X86: =F86+AY86 -> 5 | AA86: =I86+BB86 -> 18 | AD86: 20 | AF86: 450 | AJ86: =SUM(U86:Z86) -> 6 | AQ86: 24 | AR86: Novo Aripuanã | AV86: 1 | AY86: 5 | BB86: 18 | BE86: 17 | BG86: 450 | BK86: 6
A87: 7 | B87: Parintins | M87: =SUM(C87:H87) -> 0 | P87: 25 | Q87: =B87 -> Parintins | U87: =AV87+C87 -> 11 | X87: =F87+AY87 -> 1 | AA87: =I87+BB87 -> 1 | AD87: 1 | AF87: 0 | AJ87: =SUM(U87:Z87) -> 12 | AQ87: 25 | AR87: Parintins | AV87: 11 | AY87: 1 | BB87: 1 | BE87: 1 | BG87: 0 | BK87: 12
A88: 8 | B88: Presidente Figueiredo | M88: =SUM(C88:H88) -> 0 | P88: 26 | Q88: =B88 -> Presidente Figueiredo | U88: =AV88+C88 -> 4 | X88: =F88+AY88 -> 0 | AA88: =I88+BB88 -> 0 | AD88: 13 | AF88: 0 | AJ88: =SUM(U88:Z88) -> 4 | AQ88: 26 | AR88: Presidente Figueiredo | AV88: 4 | AY88: 0 | BB88: 0 | BE88: 13 | BG88: 0 | BK88: 4
A89: 9 | B89: Rio Preto da Eva | M89: =SUM(C89:H89) -> 0 | P89: 27 | Q89: =B89 -> Rio Preto da Eva | U89: =AV89+C89 -> 1 | X89: =F89+AY89 -> 2 | AA89: =I89+BB89 -> 25 | AD89: 5 | AF89: 40 | AJ89: =SUM(U89:Z89) -> 3 | AQ89: 27 | AR89: Rio Preto da Eva | AV89: 1 | AY89: 2 | BB89: 25 | BE89: 5 | BG89: 40 | BK89: 3
A90: 10 | B90: Tabatinga | M90: =SUM(C90:H90) -> 0 | P90: 28 | Q90: =B90 -> Tabatinga | U90: =AV90+C90 -> 2 | X90: =F90+AY90 -> 0 | AA90: =I90+BB90 -> 0 | AD90: 4 | AF90: 0 | AJ90: =SUM(U90:Z90) -> 2 | AQ90: 28 | AR90: Tabatinga | AV90: 2 | AY90: 0 | BB90: 0 | BE90: 4 | BG90: 0 | BK90: 2
B91: Tapauá | M91: =SUM(C91:H91) -> 0 | P91: 29 | Q91: =B91 -> Tapauá | U91: =AV91+C91 -> 1 | X91: =F91+AY91 -> 1 | AA91: =I91+BB91 -> 15 | AD91: 2 | AF91: 5200 | AJ91: =SUM(U91:Z91) -> 2 | AQ91: 29 | AR91: Tapauá | AV91: 1 | AY91: 1 | BB91: 15 | BE91: 2 | BG91: 5200 | BK91: 2
B92: Tefé | M92: =SUM(C92:H92) -> 0 | P92: 30 | Q92: =B92 -> Tefé | U92: =AV92+C92 -> 5 | X92: =F92+AY92 -> 2 | AA92: =I92+BB92 -> 4 | AD92: 6 | AF92: 150 | AJ92: =SUM(U92:Z92) -> 7 | AQ92: 30 | AR92: Tefe | AV92: 5 | AY92: 2 | BB92: 4 | BE92: 6 | BG92: 150 | BK92: 7
A93: 11 | B93: Uricurituba | M93: =SUM(C93:H93) -> 0 | P93: 31 | Q93: =B93 -> Uricurituba | U93: =AV93+C93 -> 0 | X93: =F93+AY93 -> 0 | AA93: =I93+BB93 -> 0 | AD93: 8 | AF93: 0 | AJ93: =SUM(U93:Z93) -> 0 | AQ93: 31 | AR93: Uricurituba | AV93: 0 | AY93: 0 | BB93: 0 | BE93: 8 | BG93: 0 | BK93: 0
B94: TOTAL | C94: =SUM(C63:E93) -> 6 | F94: =SUM(F63:H93) -> 31 | I94: =SUM(I63:K93) -> 104 | M94: =SUM(M63:M93) -> 37 | P94: TOTAL | U94: =SUM(U63:W93) -> 344 | X94: =SUM(X63:Z93) -> 337 | AA94: =SUM(AA63:AC93) -> 1330 | AD94: =SUM(AD63:AE93) -> 280 | AF94: =SUM(AF63:AH93) -> 366936 | AJ94: =SUM(AJ63:AJ93) -> 681 | AQ94: TOTAL | AV94: =SUM(AV63:AX93) -> 338 | AY94: =SUM(AY63:BA93) -> 306 | BB94: =SUM(BB63:BD93) -> 1226 | BE94: =SUM(AJ63+BK59BE59:BF93) -> #NAME? | BG94: =SUM(BG63:BI93) -> 334010 | BK94: =SUM(BK63:BK93) -> 644
A96: =CONCATENATE("INCÊNDIOS - RESUMO DE "&TEXT(AQ3,"DD")&"/"&TEXT(AQ3,"MM")&"/"&TEXT(AQ3,"AAA")) -> INCÊNDIOS - RESUMO DE 02/08/2026 | P96: =CONCATENATE("INCÊNDIOS - OCORRÊNCIAS DE 01/06/2026 ATÉ " &TEXT(AQ3,"DD")&"/"&TEXT(AQ3,"MM")&"/"&TEXT(AQ3,"AAA")) -> INCÊNDIOS - OCORRÊNCIAS DE 01/06/2026 ATÉ 02/08/2026 | AH96: CONCEITOS / OBSERVAÇÕES
A97: REGIÃO | C97: INCÊNDIO URBANO | F97: INCÊNDIO FLORESTAL | I97: FOCOS DOS INC. FLORESTAIS | M97: TOTAL DE OCORRÊNCIAS | P97: REGIÃO | U97: INCÊNDIO URBANO | X97: INCÊNDIO FLORESTAL | AA97: FOCOS DOS INC. FLORESTAIS | AE97: TOTAL DE OCORRÊNCIAS | AH97: FOCOS: São contabilizados das Ocorrências de Incêndios Florestais confirmados, in loco, ainda que não ocorra o combate mas com mensuração de área queimada. DESCONSIDERADAS as OCORRÊNCIAS DE TROTE, se in loco não houver confirmação de populares ou identificação da área queimada. INCÊNDIO FLORESTAL: deve ser igual ao número de focos ou menor que o número de focos.
A98: CAPITAL | C98: =C63 -> 6 | F98: =F63 -> 19 | I98: =I63 -> 45 | M98: =SUM(C98:H98) -> 25 | P98: CAPITAL | U98: =U63 -> 260 | X98: =X63 -> 158 | AA98: =AA63 -> 318 | AE98: =U98+X98 -> 418
A99: INTERIOR | C99: =SUM(C65:C93) -> 0 | F99: =SUM(F65:F93) -> 12 | I99: =SUM(I65:I93) -> 59 | M99: =SUM(C99:H99) -> 12 | P99: INTERIOR | U99: =SUM(U64:U93) -> 84 | X99: =SUM(X64:Z93) -> 179 | AA99: =SUM(AA64:AB93) -> 1012 | AE99: =U99+X99 -> 263
A100: TOTAL | C100: =SUM(C98:E99) -> 6 | F100: =SUM(F98:H99) -> 31 | I100: =SUM(I98:I99) -> 104 | M100: =SUM(M98:M99) -> 37 | P100: TOTAL | U100: =SUM(U98:W99) -> 344 | X100: =SUM(X98:X99) -> 337 | AA100: =SUM(AA98:AA99) -> 1330 | AE100: =SUM(AE98:AE99) -> 681
A102: =CONCATENATE("OUTRAS OCORRÊNCIAS DIÁRIAS EM "&TEXT(AQ3,"dd")&"/"&TEXT(AQ3,"mm")&"/"&TEXT(AQ3,"aaa")) -> OUTRAS OCORRÊNCIAS DIÁRIAS EM 02/08/2026 | U102: TOTAL GERAL DE OCORRÊNCIAS DIÁRIAS
A103: Nº | B103: MUNICÍPIO | C103: SALVAMENTO | G103: ACIDENTES | J103: APH | M103: AÇÃO DE PREVENÇÃO | Q103: SERVIÇOS | U103: REGIÃO / TIPO DE OCORRÊNCIA | Z103: SALVAMENTO | AC103: ACIDENTES | AE103: APH | AF103: AÇÃO DE PREVENÇÃO | AK103: SERVIÇOS
A104: 1 | B104: =B63 -> Manaus | C104: 7 | G104: 3 | J104: 8 | M104: 2 | Q104: 1
B105: Apuí | C105: 1
...

Sheet DADOS
A1: Carimbo de data/hora | B1: Endereço de e-mail | C1: INFORME SUA CIDADE DE ATUAÇÃO | D1: INFORME A DATA DA OCORRÊNCIA | E1: INFORME O HORÁRIO DA OCORRÊNCIA | F1: INFORME A NATUREZA DA OCORRÊNCIA | G1: INFORME A QUANTIDADE DE FOCOS DE INCÊNDIO NA OCORRÊNCIA | H1: INFORME AS COORDENADAS GEOGRÁFICAS DA OCORRÊNCIA | I1: INFORME O ENDEREÇO DA OCORRÊNCIA | J1: INFORME A ÁREA QUEIMADA (EM METROS QUADRADOS) | K1: INFORME A QUANTIDADE DE ÁGUA UTILIZADA (EM LITROS) | L1: ADMINISTRAÇÃO (QTD DE EFETIVO) | M1: SERVIÇO ORDINÁRIO (QTD DE EFETIVO) | N1: SEG (QTD DE EFETIVO) | O1: CÉU LIMPO (QTD DE EFETIVO) | P1: ACEIRO (QTD DE EFETIVO) | Q1: FORÇA NACIONAL (QTD DE EFETIVO) | R1: BRIGADISTA FLORESTAL (QTD DE EFETIVO) | S1: BRIGADISTA CIVIL (QTD DE EFETIVO) | T1: DEFESA CIVIL (QTD DE EFETIVO) | U1: TRIPULANTES DE AVIÃO (QTD DE EFETIVO) | V1: OUTROS (QTD DE EFETIVO) | W1: VIATURA ABT (QTD EMPREGADA) | X1: VIATURA AT (QTD EMPREGADA) | Y1: VIATURA ATP (QTD EMPREGADA) | Z1: VIATURA ATA (QTD EMPREGADA) | AA1: VIATURA ABF (QTD EMPREGADA) | AB1: VIATURA ABS (QTD EMPREGADA) | AC1: VIATURA PIPA (QTD EMPREGADA) | AD1: VIATURA DOSA (QTD EMPREGADA) | AE1: VIATURA CRS (QTD EMPREGADA) | AF1: VIATURA AR (QTD EMPREGADA) | AG1: VIATURA ATM (QTD EMPREGADA) | AH1: VIATURA UR (QTD EMPREGADA) | AI1: VIATURA MT (QTD EMPREGADA) | AJ1: VIATURA TA (QTD EMPREGADA) | AK1: VIATURA EMBARCAÇÃO (QTD EMPREGADA) | AL1: VIATURA PICAPE FN (QTD EMPREGADA) | AM1: VIATURA PICAPE MUN (QTD EMPREGADA) | AN1: VIATURA PICAPE SSP (QTD EMPREGADA) | AO1: VIATURA HELICÓPTERO (QTD EMPREGADA) | AP1: VIATURA AVIÃO (QTD EMPREGADA) | AQ1: VIATURA AEM (QTD EMPREGADA) | AR1: INFORME O NÚMERO DA OCORRÊNCIA (GRUPO CBI EM AÇÃO) | AS1: INFORME O NÚMERO DA OCORRÊNCIA (GRUPO OPERAÇÃO ACEIRO)
A2: 45528.682 | B2: salacbmam@gmail.com | C2: Manaus | D2: 45446 | F2: INCÊNDIO EM EDIFICAÇÕES
A3: 45528.685 | B3: salacbmam@gmail.com | C3: Manaus | D3: 45446 | F3: INCÊNDIO EM EDIFICAÇÕES
A4: 45528.686 | B4: salacbmam@gmail.com | C4: Manaus | D4: 45447 | F4: INCÊNDIO EM EDIFICAÇÕES
A5: 45528.687 | B5: salacbmam@gmail.com | C5: Manaus | D5: 45448 | F5: INCÊNDIO EM EDIFICAÇÕES
A6: 45484.752 | B6: salacbmam@gmail.com | C6: Humaitá | D6: 45449 | E6: 0.58333333 | F6: INCÊNDIO FLORESTAL | I6: Rua Projetada, zona rural | J6: 10000 | K6: 1000 | P6: 3
A7: 45484.759 | B7: salacbmam@gmail.com | C7: Humaitá | D7: 45449 | E7: 0.61111111 | F7: INCÊNDIO FLORESTAL | I7: Invasão atrás do conjunto Rio madeira s/n , Área Rural | J7: 10000 | K7: 1500 | P7: 3
A8: 45484.761 | B8: salacbmam@gmail.com | C8: Humaitá | D8: 45449 | E8: 0.64444444 | F8: INCÊNDIO FLORESTAL | I8: Ramal da comunidade do Uxi Bairro: Zona rural | J8: 20000 | K8: 2000 | P8: 3
A9: 45528.688 | B9: salacbmam@gmail.com | C9: Manaus | D9: 45449 | F9: INCÊNDIO EM EDIFICAÇÕES
A10: 45528.691 | B10: salacbmam@gmail.com | C10: Manaus | D10: 45450 | F10: INCÊNDIO FLORESTAL
A11: 45528.691 | B11: salacbmam@gmail.com | C11: Manaus | D11: 45450 | F11: INCÊNDIO EM EDIFICAÇÕES
A12: 45528.693 | B12: salacbmam@gmail.com | C12: Manaus | D12: 45451 | F12: INCÊNDIO FLORESTAL
A13: 45528.694 | B13: salacbmam@gmail.com | C13: Manaus | D13: 45452 | F13: INCÊNDIO EM EDIFICAÇÕES
A14: 45528.694 | B14: salacbmam@gmail.com | C14: Manaus | D14: 45452 | F14: INCÊNDIO EM EDIFICAÇÕES
A15: 45528.696 | B15: salacbmam@gmail.com | C15: Parintins | D15: 45452 | F15: INCÊNDIO EM EDIFICAÇÕES
A16: 45528.753 | B16: salacbmam@gmail.com | C16: Presidente Figueiredo | D16: 45453 | F16: INCÊNDIO FLORESTAL
A17: 45528.754 | B17: salacbmam@gmail.com | C17: Manaus | D17: 45453 | F17: INCÊNDIO EM EDIFICAÇÕES
A18: 45528.754 | B18: salacbmam@gmail.com | C18: Manaus | D18: 45453 | F18: INCÊNDIO EM EDIFICAÇÕES
A19: 45475.62 | B19: wagnneerrd@gmail.com | C19: Humaitá | D19: 45454 | E19: 0.8125 | F19: INCÊNDIO FLORESTAL | I19: Rua 2. Residencial Santa Clara. Bairro São Cristóvão | K19: 1000 | L19: 1 | M19: 3 | N19: 0 | O19: 0 | P19: 3 | Q19: 0 | R19: 0 | S19: 0 | T19: 0 | AA19: 1
A20: 45528.772 | B20: salacbmam@gmail.com | C20: Manaus | D20: 45454 | F20: INCÊNDIO EM EDIFICAÇÕES
A21: 45528.775 | B21: salacbmam@gmail.com | C21: Manaus | D21: 45454 | F21: INCÊNDIO FLORESTAL
A22: 45528.775 | B22: salacbmam@gmail.com | C22: Manaus | D22: 45454 | F22: INCÊNDIO FLORESTAL
A23: 45475.619 | B23: joaofelipe292@gmail.com | C23: Boca do Acre | D23: 45455 | E23: 0.58194444 | F23: INCÊNDIO FLORESTAL | H23: 8.77968242S 67.32831918W | I23: Rodovia Wilson Pinheiro, Bairro platô do Piquiá nº 11011-C | J23: 1000 | K23: 600 | P23: 04 | AF23: 1
A24: 45528.778 | B24: salacbmam@gmail.com | C24: Parintins | D24: 45455 | F24: INCÊNDIO EM EDIFICAÇÕES
A25: 45528.779 | B25: salacbmam@gmail.com | C25: Manacapuru | D25: 45455 | F25: INCÊNDIO FLORESTAL
A26: 45528.781 | B26: salacbmam@gmail.com | C26: Boca do Acre | D26: 45455 | F26: INCÊNDIO FLORESTAL
A27: 45528.781 | B27: salacbmam@gmail.com | C27: Boca do Acre | D27: 45455 | F27: INCÊNDIO FLORESTAL
A28: 45528.781 | B28: salacbmam@gmail.com | C28: Boca do Acre | D28: 45455 | F28: INCÊNDIO FLORESTAL
A29: 45528.781 | B29: salacbmam@gmail.com | C29: Boca do Acre | D29: 45455 | F29: INCÊNDIO FLORESTAL
A30: 45528.781 | B30: salacbmam@gmail.com | C30: Boca do Acre | D30: 45455 | F30: INCÊNDIO FLORESTAL
A31: 45528.781 | B31: salacbmam@gmail.com | C31: Boca do Acre | D31: 45455 | F31: INCÊNDIO FLORESTAL
A32: 45528.781 | B32: salacbmam@gmail.com | C32: Boca do Acre | D32: 45455 | F32: INCÊNDIO FLORESTAL
A33: 45528.784 | B33: salacbmam@gmail.com | C33: Manaus | D33: 45456 | F33: INCÊNDIO EM EDIFICAÇÕES
A34: 45528.784 | B34: salacbmam@gmail.com | C34: Manaus | D34: 45456 | F34: INCÊNDIO EM EDIFICAÇÕES
A35: 45528.784 | B35: salacbmam@gmail.com | C35: Manaus | D35: 45456 | F35: INCÊNDIO EM EDIFICAÇÕES
... A38: 45528.798 | B38: salacbmam@gmail.com | C38: Manaus | D38: 45458 | F38: INCÊNDIO EM EDIFICAÇÕES
A39: 45528.799 | C39: Itacoatiara | D39: 45459 | F39: INCÊNDIO EM EDIFICAÇÕES
A40: 45475.794 | B40: pgarciasbm@gmail.com | C40: Humaitá | D40: 45459 | E40: 0.62361111 | F40: INCÊNDIO FLORESTAL | G40: 3 | H40: -7.52536"S,-63.04117"W | I40: Rua Bom Conselho, conjunto Habitacional Uruapiara | J40: 300 | K40: 2500 | L40: 4 | M40: 2 | N40: 00 | O40: 00 | P40: 2 | Q40: 00 | R40: 00 | S40: 00 | T40: 00 | U40: 00 | V40: 00 | W40: 00 | X40: 00 | Y40: 00 | Z40: 00 | AA40: 00 | AB40: 1 | AC40: 00 | AD40: 00 | AE40: 00 | AF40: 00 | AG40: 00 | AH40: 00 | AI40: 00 | AJ40: 00 | AK40: 00 | AL40: 00 | AM40: 00 | AN40: 00 | AO40: 00 | AP40: 00 | AQ40: 00
A41: 45528.799 | C41: Humaitá | D41: 45459 | F41: INCÊNDIO FLORESTAL | G41: 1
A42: 45528.799 | C42: Humaitá | D42: 45459 | F42: INCÊNDIO FLORESTAL | G42: 1
A43: 45528.799 | C43: Humaitá | D43: 45459 | F43: INCÊNDIO FLORESTAL | G43: 9
A44: 45528.799 | C44: Iranduba | D44: 45459 | F44: INCÊNDIO FLORESTAL | G44: 2
A45: 45475.706 | B45: reneltonbatalha123@gmail.com | C45: Apuí | D45: 45460 | E45: 0.76736111 | F45: INCÊNDIO FLORESTAL | G45: 4 | I45: Bairro Cachoeirinha ao lado da UEA | J45: 700 | K45: 300 | L45: 0 | M45: 0 | N45: 0 | O45: 0 | P45: 04 | Q45: 0 | R45: 0 | S45: 0 | T45: 0 | U45: 0 | V45: 0 | W45: 0 | X45: 0 | Y45: 0 | Z45: 0 | AA45: 0 | AB45: 0 | AC45: 0 | AD45: 0 | AE45: 0 | AF45: 01 | AG45: 0 | AH45: 0 | AI45: 0 | AJ45: 0 | AK45: 0 | AL45: 0 | AM45: 0 | AN45: 0 | AO45: 0 | AP45: 0 | AQ45: 0
A46: 45475.799 | B46: pgarciasbm@gmail.com | C46: Humaitá | D46: 45460 | E46: 0.020138889 | F46: INCÊNDIO FLORESTAL | G46: 18 | H46: -7.52187"S,-63.03832 | I46: Br 230, 1 | J46: 2000 | K46: 2000 | L46: 00 | M46: 2 | N46: 00 | O46: 00 | P46: 2 | Q46: 00 | R46: 00 | S46: 00 | T46: 00 | U46: 00 | V46: 00 | W46: 00 | X46: 00 | Y46: 00 | Z46: 00 | AA46: 00 | AB46: 1 | AC46: 00 | AD46: 00 | AE46: 00 | AF46: 00 | AG46: 00 | AH46: 00 | AI46: 00 | AJ46: 00 | AK46: 00 | AL46: 00 | AM46: 00 | AN46: 00 | AO46: 00 | AP46: 00 | AQ46: 00
A47: 45528.784 | B47: salacbmam@gmail.com | C47: Manaus | D47: 45460 | F47: INCÊNDIO EM EDIFICAÇÕES
A48: 45528.784 | B48: salacbmam@gmail.com | C48: Manaus | D48: 45460 | F48: INCÊNDIO EM EDIFICAÇÕES
A49: 45528.784 | B49: salacbmam@gmail.com | C49: Manaus | D49: 45460 | F49: INCÊNDIO EM EDIFICAÇÕES
A50: 45528.784 | B50: salacbmam@gmail.com | C50: Manaus | D50: 45460 | F50: INCÊNDIO EM EDIFICAÇÕES
A51: 45528.784 | B51: salacbmam@gmail.com | C51: Manaus | D51: 45460 | F51: INCÊNDIO EM EDIFICAÇÕES
A52: 45528.784 | B52: salacbmam@gmail.com | C52: Manaus | D52: 45460 | F52: INCÊNDIO EM EDIFICAÇÕES
A53: 45528.784 | B53: salacbmam@gmail.com | C53: Boca do Acre | D53: 45460 | F53: INCÊNDIO FLORESTAL | G53: 37
A54: 45528.784 | B54: salacbmam@gmail.com | C54: Manaus | D54: 45460 | F54: INCÊNDIO FLORESTAL | G54: 1
A55: 45475.711 | B55: reneltonbatalha123@gmail.com | C55: Apuí | D55: 45461 | E55: 0.52430556 | F55: INCÊNDIO FLORESTAL | G55: 7 | I55: BR 230, KM3 | J55: 1200 | K55: 600 | L55: 0 | M55: 0 | N55: 0 | O55: 0 | P55: 03 | Q55: 0 | R55: 0 | S55: 0 | T55: 0 | U55: 0 | V55: 0 | W55: 0 | X55: 0 | Y55: 0 | Z55: 0 | AA55: 0 | AB55: 0 | AC55: 0 | AD55: 0 | AE55: 0 | AF55: 01 | AG55: 0 | AH55: 0 | AI55: 0 | AJ55: 0 | AK55: 0 | AL55: 0 | AM55: 0 | AN55: 0 | AO55: 0 | AP55: 0 | AQ55: 0
A56: 45528.784 | B56: salacbmam@gmail.com | C56: Manaus | D56: 45461 | F56: INCÊNDIO EM EDIFICAÇÕES
A57: 45528.784 | B57: salacbmam@gmail.com | C57: Manacapuru | D57: 45461 | F57: INCÊNDIO FLORESTAL | G57: 1
A58: 45528.784 | B58: salacbmam@gmail.com | C58: Tefé | D58: 45462 | F58: INCÊNDIO FLORESTAL | G58: 1
A59: 45475.715 | B59: reneltonbatalha123@gmail.com | C59: Apuí | D59: 45462 | E59: 0.78472222 | F59: INCÊNDIO FLORESTAL | G59: 9 | I59: Vicinal Coruja | J59: 3000 | K59: 200 | L59: 0 | M59: 0 | N59: 0 | O59: 0 | P59: 04 | Q59: 04 | R59: 0 | S59: 0 | T59: 0 | U59: 0 | V59: 0 | W59: 0 | X59: 0 | Y59: 0 | Z59: 0 | AA59: 0 | AB59: 0 | AC59: 0 | AD59: 0 | AE59: 0 | AF59: 01 | AG59: 0 | AH59: 0 | AI59: 0 | AJ59: 0 | AK59: 0 | AL59: 01 | AM59: 0 | AN59: 0 | AO59: 0 | AP59: 0 | AQ59: 0
A60: 45475.813 | B60: pgarciasbm@gmail.com | C60: Humaitá | D60: 45462 | E60: 0.90625 | F60: INCÊNDIO FLORESTAL | G60: 6 | H60: -7.50576"S,-63.03741"W | I60: Rua Dom José, Nova Esperança | J60: 400 | K60: 500 | L60: 00 | M60: 2 | N60: 00 | O60: 00 | P60: 2 | Q60: 00 | R60: 00 | S60: 00 | T60: 00 | U60: 00 | V60: 00 | W60: 00 | X60: 00 | Y60: 00 | Z60: 09 | AA60: 00 | AB60: 1 | AC60: 00 | AD60: 00 | AE60: 00 | AF60: 00 | AG60: 00 | AH60: 00 | AI60: 00 | AJ60: 00 | AK60: 00 | AL60: 00 | AM60: 00 | AN60: 00 | AO60: 00 | AP60: 00 | AQ60: 00
A61: 45528.784 | B61: salacbmam@gmail.com | C61: Manaus | D61: 45462 | F61: INCÊNDIO EM EDIFICAÇÕES
A62: 45528.784 | B62: salacbmam@gmail.com | C62: Manaus | D62: 45462 | F62: INCÊNDIO EM EDIFICAÇÕES
A63: 45475.625 | B63: wagnneerrd@gmail.com | C63: Humaitá | D63: 45463 | E63: 0.44305556 | F63: INCÊNDIO FLORESTAL | G63: 22 | I63: Alto Crato | J63: 20000 | K63: 20000 | L63: 3 | P63: 6 | Q63: 12 | AA63: 1
A64: 45475.628 | B64: wagnneerrd@gmail.com | C64: Humaitá | D64: 45463 | E64: 0.50069444 | F64: INCÊNDIO FLORESTAL | G64: 12 | I64: Rua Dom José. Bairro Nova Humaitá. | J64: 2000 | K64: 6000 | P64: 6 | Q64: 12 | AA64: 1
A65: 45483.676 | B65: salacbmam@gmail.com | C65: Novo Airão | D65: 45463 | E65: 0.8125 | F65: INCÊNDIO FLORESTAL | G65: 5 | I65: Rua Almerinda Malaquias, Caminho das Índias, 241 | J65: 400 | K65: 10000 | O65: 3 | R65: 3
A66: 45528.784 | B66: salacbmam@gmail.com | C66: Manaus | D66: 45463 | F66: INCÊNDIO EM EDIFICAÇÕES
A67: 45528.784 | B67: salacbmam@gmail.com | C67: Manaus | D67: 45463 | F67: INCÊNDIO EM EDIFICAÇÕES
A68: 45528.784 | B68: salacbmam@gmail.com | C68: Manaus | D68: 45463 | F68: INCÊNDIO EM EDIFICAÇÕES
A69: 45528.784 | B69: salacbmam@gmail.com | C69: Parintins | D69: 45463 | F69: INCÊNDIO FLORESTAL | G69: 1
A70: 45528.784 | B70: salacbmam@gmail.com | C70: Humaitá | D70: 45463 | F70: INCÊNDIO FLORESTAL | G70: 11
A71: 45528.784 | B71: salacbmam@gmail.com | C71: Manaus | D71: 45463 | F71: INCÊNDIO FLORESTAL | G71: 1
A72: 45475.6 | B72: haninhalopes02@gmail.com | C72: Novo Aripuanã | D72: 45464 | E72: 0.45833333 | F72: INCÊNDIO FLORESTAL | G72: 3 | I72: Rua Rogério Braga, s/n bairro Tucumã | K72: 300 | L72: 6 | M72: 2 | N72: 0 | O72: 0 | P72: 6 | Q72: 0 | R72: 0 | S72: 0 | T72: 0 | U72: 0 | V72: 0 | W72: 0 | X72: 0 | Y72: 0 | Z72: 0 | AA72: 0 | AB72: 0 | AC72: 0 | AD72: 0 | AE72: 0 | AF72: 1 | AG72: 0 | AH72: 0 | AI72: 0 | AJ72: 0 | AK72: 0 | AL72: 0 | AM72: 0 | AN72: 0 | AO72: 0 | AP72: 0 | AQ72: 0
A73: 45476.363 | B73: pdfimahumaita@gmail.com | C73: Humaitá | D73: 45464 | E73: 0.96805556 | F73: INCÊNDIO FLORESTAL | G73: 5 | H73: -7⁰31'5,27912"S-63⁰,02929"W5⁰N | I73: BR-230, KM-02 (BAIRRO: SÃO PEDRO) | J73: 800 | K73: 1000 | L73: 04 | M73: 06 | N73: 00 | O73: 00 | P73: 20 | Q73: 00 | R73: 00 | S73: 00 | T73: 00 | U73: 00 | V73: 00 | W73: 00 | X73: 00 | Y73: 00 | Z73: 00 | AA73: 01 | AB73: 00 | AC73: 00 | AD73: 00 | AE73: 00 | AF73: 00 | AG73: 00 | AH73: 00 | AI73: 00 | AJ73: 00 | AK73: 00 | AL73: 00 | AM73: 00 | AN73: 00 | AO73: 00 | AP73: 00 | AQ73: 00
A74: 45528.784 | B74: salacbmam@gmail.com | C74: Manaus | D74: 45464 | F74: INCÊNDIO EM EDIFICAÇÕES
A75: 45528.784 | B75: salacbmam@gmail.com | C75: Manaus | D75: 45464 | F75: INCÊNDIO FLORESTAL | G75: 1
A76: 45528.784 | B76: salacbmam@gmail.com | C76: Manaus | D76: 45464 | F76: INCÊNDIO FLORESTAL | G76: 1
A77: 45528.784 | B77: salacbmam@gmail.com | C77: Manaus | D77: 45464 | F77: INCÊNDIO FLORESTAL | G77: 1
A78: 45528.784 | B78: salacbmam@gmail.com | C78: Tefé | D78: 45464 | F78: INCÊNDIO FLORESTAL | G78: 1
A79: 45468.632 | B79: meirebm07@gmail.com | C79: Autazes | D79: 45465 | E79: 0.40972222 | F79: INCÊNDIO FLORESTAL | G79: 1 | H79: -3.585751, -59.133087 | I79: Rua Presidente Kennedy, n. 06, Bairro Multirão | J79: 0 | K79: 0 | L79: 2 | M79: 4 | N79: 0 | O79: 0 | P79: 8 | Q79: 0 | R79: 0 | S79: 0 | T79: 0 | U79: 0 | V79: 0 | W79: 0 | X79: 0 | Y79: 0 | Z79: 0 | AA79: 0 | AB79: 0 | AC79: 0 | AD79: 0 | AE79: 0 | AF79: 0 | AG79: 0 | AH79: 0 | AI79: 0 | AJ79: 0 | AK79: 0 | AL79: 0 | AM79: 1 | AN79: 0 | AO79: 0 | AP79: 0 | AQ79: 0
A80: 45475.673 | B80: srodriguesid7@gmail.com | C80: Lábrea | D80: 45465 | E80: 0.69097222 | F80: INCÊNDIO FLORESTAL | G80: 2 | H80: S-7° 17,578. W64° 46, 049 226° SE | I80: Rodovia 230, KM 4 | J80: 200 | K80: 100 | L80: 1 | M80: 3 | N80: 0 | O80: 0 | P80: 7 | Q80: 2 | R80: 0 | S80: 0 | T80: 0 | U80: 0 | V80: 0 | W80: 0 | X80: 0 | Y80: 0 | Z80: 0 | AA80: 0 | AB80: 0 | AC80: 0 | AD80: 0 | AE80: 0 | AF80: 1 | AG80: 0 | AH80: 0 | AI80: 0 | AJ80: 0 | AK80: 0 | AL80: FN-01 | AM80: 1 | AN80: 0 | AO80: 0 | AP80: 0 | AQ80: 0
A81: 45475.678 | B81: srodriguesid7@gmail.com | C81: Lábrea | D81: 45465 | E81: 0.76319444 | F81: INCÊNDIO FLORESTAL | G81: 1 | H81: S-7° 15,828, W64°, 46,645, 298° NW | I81: Ramal durapox, Bairro Novo, S/N | J81: 50 | K81: 200 | L81: 1 | M81: 3 | N81: 0 | O81: 0 | P81: 7 | Q81: 4 | R81: 0 | S81: 0 | T81: 0 | U81: 0 | V81: 0 | W81: 0 | X81: 0 | Y81: 0 | Z81: 0 | AA81: 0 | AB81: 0 | AC81: 0 | AD81: 0 | AE81: 0 | AF81: 1 | AG81: 0 | AH81: 0 | AI81: 0 | AJ81: 0 | AK81: 0 | AL81: FN-01 | AM81: 0 | AN81: 0 | AO81: 0 | AP81: 0 | AQ81: 0
A82: 45475.678 | B82: srodriguesid7@gmail.com | C82: Maués | D82: 45465 | F82: INCÊNDIO FLORESTAL | G82: 2
A83: 45475.678 | B83: srodriguesid7@gmail.com | C83: Lábrea | D83: 45465 | F83: INCÊNDIO FLORESTAL | G83: 1
A84: 45475.698 | B84: bmpaulolopes@gmail.com | C84: Manicoré | D84: 45465 | E84: 0.8125 | F84: INCÊNDIO FLORESTAL | G84: 1 | H84: -5.806857, -61.294384 | I84: Travessa Manaus, 350 - Bairro São Domingos | J84: 4 | K84: 40 | L84: 1 | M84: 0 | N84: 0 | O84: 0 | P84: 4 | Q84: 0 | R84: 0 | S84: 1 | T84: 0 | U84: 0 | V84: 0 | W84: 0 | X84: 0 | Y84: 0 | Z84: 0 | AA84: 0 | AB84: 0 | AC84: 0 | AD84: 0 | AE84: 0 | AF84: 1 | AG84: 0 | AH84: 0 | AI84: 0 | AJ84: 0 | AK84: 0 | AL84: 0 | AM84: 0 | AN84: 0 | AO84: 0 | AP84: 0 | AQ84: 0
A85: 45528.784 | B85: salacbmam@gmail.com | C85: Manaus | D85: 45465 | F85: INCÊNDIO EM EDIFICAÇÕES
A86: 45528.784 | B86: salacbmam@gmail.com | C86: Manaus | D86: 45465 | F86: INCÊNDIO FLORESTAL | G86: 1
A87: 45528.784 | B87: salacbmam@gmail.com | C87: Manaus | D87: 45465 | F87: INCÊNDIO FLORESTAL | G87: 1
A88: 45528.784 | B88: salacbmam@gmail.com | C88: Manaus | D88: 45465 | F88: INCÊNDIO FLORESTAL | G88: 1
A89: 45528.784 | B89: salacbmam@gmail.com | C89: Manaus | D89: 45465 | F89: INCÊNDIO FLORESTAL | G89: 2
A90: 45528.784 | B90: salacbmam@gmail.com | C90: Autazes | D90: 45465 | F90: INCÊNDIO EM EDIFICAÇÕES
A91: 45475.604 | B91: haninhalopes02@gmail.com | C91: Novo Aripuanã | D91: 45466 | E91: 0.64236111 | F91: INCÊNDIO FLORESTAL | G91: 2 | I91: Ramal do Baia, serraria do Paulo Alho | J91: 18 | K91: 600 | L91: 6 | M91: 2 | N91: 0 | O91: 0 | P91: 6 | Q91: 0 | R91: 0 | S91: 0 | T91: 0 | U91: 0 | V91: 6 | W91: 0 | X91: 0 | Y91: 0 | Z91: 0 | AA91: 0 | AB91: 0 | AC91: 0 | AD91: 0 | AE91: 0 | AF91: 1 | AG91: 0 | AH91: 0 | AI91: 0 | AJ91: 0 | AK91: 0 | AL91: 0 | AM91: 0 | AN91: 0 | AO91: 0 | AP91: 0 | AQ91: 0
A92: 45475.617 | B92: ribeiroalmedino@gmail.com | C92: Lábrea | D92: 45466 | E92: 0.775 | F92: INCÊNDIO FLORESTAL | G92: 12 | H92: -7.256723,-64.764671 | I92: Estrada do Barreiro Ramal Tarumã | J92: 12500 | K92: 500 | P92: 2 | Q92: 2 | R92: 0 | S92: 0 | T92: 0 | AF92: 1 | AL92: 01/ 1207
A93: 45475.692 | B93: fpaulo32525@gmail.com | C93: Manicoré | D93: 45466 | E93: 0.70833333 | F93: INCÊNDIO FLORESTAL | G93: 16 | I93: TERRENO DA TÂNIA DO CARTÓRIO ÁREA RURAL | J93: 2500 | K93: 550 | L93: 1 | M93: 0 | N93: 0 | O93: 0 | P93: 3 | Q93: 0 | R93: 0 | S93: 2 | T93: 0 | U93: 0 | V93: 0 | W93: 0 | X93: 0 | Y93: 0 | Z93: 0 | AA93: 0 | AB93: 0 | AC93: 0 | AD93: 0 | AE93: 0 | AF93: 1 | AG93: 0 | AH93: 0 | AI93: 0 | AJ93: 0 | AK93: 0 | AL93: 0 | AM93: 0 | AN93: 0 | AO93: 0 | AP93: 0 | AQ93: 0
A94: 45475.948 | B94: farm.edumaga@gmail.com | C94: Manaquiri | D94: 45466 | E94: 0.8125 | F94: INCÊNDIO FLORESTAL | G94: 1 | I94: Rua 03, próx a delegacia da polícia civil. | J94: 15 | K94: 20 | L94: 02 | M94: 03 | P94: 08 | S94: 09 | AF94: 01
A95: 45528.784 | B95: salacbmam@gmail.com | C95: Manaus | D95: 45466 | F95: INCÊNDIO EM EDIFICAÇÕES
A96: 45528.784 | B96: salacbmam@gmail.com | C96: Manaus | D96: 45466 | F96: INCÊNDIO EM EDIFICAÇÕES
A97: 45528.784 | B97: salacbmam@gmail.com | C97: Rio Preto da Eva | D97: 45466 | F97: INCÊNDIO FLORESTAL | G97: 4
A98: 45528.784 | B98: salacbmam@gmail.com | C98: Careiro Castanho | D98: 45466 | F98: INCÊNDIO FLORESTAL | G98: 2
A99: 45467.874 | B99: joaofelipe292@gmail.com | C99: Boca do Acre | D99: 45467 | E99: 0.82986111 | F99: INCÊNDIO FLORESTAL | G99: 3 | H99: 8,78029198S 67.33549262W | I99: proximo ao ABB | J99: 900 | K99: 200 | L99: 02 | M99: 02 | N99: 0 | O99: 0 | P99: 8 | Q99: 4 | R99: 0 | S99: 0 | T99: 0 | U99: 0 | V99: 0 | W99: 0 | X99: 0 | Y99: 0 | Z99: 0 | AA99: 0 | AB99: 0 | AC99: 0 | AD99: 0 | AE99: 0 | AF99: 1 | AG99: 0 | AH99: 0 | AI99: 0 | AJ99: 0 | AK99: 0 | AL99: 0 | AM99: 0 | AN99: 0 | AO99: 0 | AP99: 0 | AQ99: 0
A100: 45475.607 | B100: haninhalopes02@gmail.com | C100: Novo Aripuanã | D100: 45467 | E100: 0.49236111 | F100: INCÊNDIO FLORESTAL | G100: 4 | I100: Rua Rogério Braga s/n, nas dependências do Hospital Edith Mendes. | J100: 3000 | K100: 300 | L100: 6 | M100: 2 | N100: 0 | O100: 0 | P100: 6 | Q100: 0 | R100: 0 | S100: 0 | T100: 0 | U100: 0 | V100: 0 | W100: 0 | X100: 0 | Y100: 0 | Z100: 0 | AA100: 0 | AB100: 0 | AC100: 0 | AD100: 0 | AE100: 0 | AF100: 1 | AG100: 0 | AH100: 0 | AI100: 0 | AJ100: 0 | AK100: 0 | AL100: 0 | AM100: 0 | AN100: 0 | AO100: 0 | AP100: 0 | AQ100: 0
A101: 45475.661 | B101: carloslopes1116bm@gmail.com | C101: Lábrea | D101: 45467 | E101: 0.50347222 | F101: INCÊNDIO FLORESTAL | G101: 4 | I101: Estrada do barreiro, zona rural. | J101: 1000 | K101: 200 | L101: 00 | M101: 00 | N101: 00 | O101: 00 | P101: 03 | Q101: 02 | R101: 00 | S101: 00 | T101: 00 | U101: 00 | V101: 00 | W101: 00 | X101: 00 | Y101: 00 | Z101: 00 | AA101: 00 | AB101: 00 | AC101: 00 | AD101: 00 | AE101: 00 | AF101: 1 | AG101: 00 | AH101: 00 | AI101: 00 | AJ101: 00 | AK101: 00 | AL101: 01 | AM101: 00 | AN101: 00 | AO101: 00 | AP101: 00 | AQ101: 00
A102: 45475.704 | B102: bmpaulolopes@gmail.com | C102: Manicoré | D102: 45467 | E102: 0.58333333 | F102: INCÊNDIO FLORESTAL | G102: 4 | H102: -5°49'13,39389"S -61°17'10,943'' | I102: Estrada do Alonso, Bairro Manicorezinho | J102: 350 | K102: 750 | L102: 1 | M102: 0 | N102: 0 | O102: 0 | P102: 3 | Q102: 0 | R102: 0 | S102: 1 | T102: 0 | U102: 0 | V102: 0 | W102: 0 | X102: 0 | Y102: 0 | Z102: 0 | AA102: 0 | AB102: 0 | AC102: 0 | AD102: 0 | AE102: 0 | AF102: 1 | AG102: 0 | AH102: 0 | AI102: 0 | AJ102: 0 | AK102: 0 | AL102: 0 | AM102: 0 | AN102: 0 | AO102: 0 | AP102: 0 | AQ102: 0
...

Sheet DADOS antigos
A1: Carimbo de data/hora | B1: Endereço de e-mail | C1: INFORME SUA CIDADE DE ATUAÇÃO | D1: INFORME A DATA DA OCORRÊNCIA | E1: INFORME O HORÁRIO DA OCORRÊNCIA | F1: INFORME A NATUREZA DA OCORRÊNCIA | G1: INFORME A QUANTIDADE DE FOCOS DE INCÊNDIO NA OCORRÊNCIA | H1: INFORME AS COORDENADAS GEOGRÁFICAS DA OCORRÊNCIA | I1: INFORME O ENDEREÇO DA OCORRÊNCIA | J1: INFORME A ÁREA QUEIMADA (EM METROS QUADRADOS) | K1: INFORME A QUANTIDADE DE ÁGUA UTILIZADA (EM LITROS) | L1: ADMINISTRAÇÃO (QTD DE EFETIVO) | M1: SERVIÇO ORDINÁRIO (QTD DE EFETIVO) | N1: SEG (QTD DE EFETIVO) | O1: CÉU LIMPO (QTD DE EFETIVO) | P1: ACEIRO (QTD DE EFETIVO) | Q1: FORÇA NACIONAL (QTD DE EFETIVO) | R1: BRIGADISTA FLORESTAL (QTD DE EFETIVO) | S1: BRIGADISTA CIVIL (QTD DE EFETIVO) | T1: DEFESA CIVIL (QTD DE EFETIVO) | U1: TRIPULANTES DE AVIÃO (QTD DE EFETIVO) | V1: OUTROS (QTD DE EFETIVO) | W1: VIATURA ABT (QTD EMPREGADA) | X1: VIATURA AT (QTD EMPREGADA) | Y1: VIATURA ATP (QTD EMPREGADA) | Z1: VIATURA ATA (QTD EMPREGADA) | AA1: VIATURA ABF (QTD EMPREGADA) | AB1: VIATURA ABS (QTD EMPREGADA) | AC1: VIATURA PIPA (QTD EMPREGADA) | AD1: VIATURA DOSA (QTD EMPREGADA) | AE1: VIATURA CRS (QTD EMPREGADA) | AF1: VIATURA AR (QTD EMPREGADA) | AG1: VIATURA ATM (QTD EMPREGADA) | AH1: VIATURA UR (QTD EMPREGADA) | AI1: VIATURA MT (QTD EMPREGADA) | AJ1: VIATURA TA (QTD EMPREGADA) | AK1: VIATURA EMBARCAÇÃO (QTD EMPREGADA) | AL1: VIATURA PICAPE FN (QTD EMPREGADA) | AM1: VIATURA PICAPE MUN (QTD EMPREGADA) | AN1: VIATURA PICAPE SSP (QTD EMPREGADA) | AO1: VIATURA HELICÓPTERO (QTD EMPREGADA) | AP1: VIATURA AVIÃO (QTD EMPREGADA) | AQ1: VIATURA AEM (QTD EMPREGADA) | AR1: INFORME O NÚMERO DA OCORRÊNCIA (GRUPO CBI EM AÇÃO) | AS1: INFORME O NÚMERO DA OCORRÊNCIA (GRUPO OPERAÇÃO ACEIRO)
A2: 45484.752 | B2: salacbmam@gmail.com | C2: Humaitá | D2: 45449 | E2: 0.58333333 | F2: INCÊNDIO FLORESTAL | G2: 1 | I2: Rua Projetada, zona rural | J2: 10000 | K2: 1000 | P2: 3
A3: 45484.759 | B3: salacbmam@gmail.com | C3: Humaitá | D3: 45449 | E3: 0.61111111 | F3: INCÊNDIO FLORESTAL | G3: 1 | I3: Invasão atrás do conjunto Rio madeira s/n , Área Rural | J3: 10000 | K3: 1500 | P3: 3
A4: 45484.761 | B4: salacbmam@gmail.com | C4: Humaitá | D4: 45449 | E4: 0.64444444 | F4: INCÊNDIO FLORESTAL | G4: 1 | I4: Ramal da comunidade do Uxi Bairro: Zona rural | J4: 20000 | K4: 2000 | P4: 3
A5: 45484.772 | B5: salacbmam@gmail.com | C5: Parintins | D5: 45451 | E5: 0.86111111 | F5: INCÊNDIO EM EDIFICAÇÕES | I5: Rua Wilson Cursino , n° 3756 Bairro: Itaúna 2 | M5: 5
A6: 45475.62 | B6: wagnneerrd@gmail.com | C6: Humaitá | D6: 45454 | E6: 0.8125 | F6: INCÊNDIO FLORESTAL | G6: 6 | I6: Rua 2. Residencial Santa Clara. Bairro São Cristóvão | K6: 1000 | L6: 1 | M6: 3 | N6: 0 | O6: 0 | P6: 3 | Q6: 0 | R6: 0 | S6: 0 | T6: 0 | AA6: 1
A7: 45475.638 | B7: wagnneerrd@gmail.com | C7: Humaitá | D7: 45454 | E7: 0.81527778 | F7: INCÊNDIO FLORESTAL | G7: 8 | J7: 500 | K7: 1000 | P7: 6 | Q7: 12 | AA7: 1
A8: 45475.619 | B8: joaofelipe292@gmail.com | C8: Boca do Acre | D8: 45455 | E8: 0.58194444 | F8: INCÊNDIO FLORESTAL | G8: 2 | H8: 8.77968242S 67.32831918W | I8: Rodovia Wilson Pinheiro, Bairro platô do Piquiá nº 11011-C | J8: 1000 | K8: 600 | P8: 04 | AF8: 1
A9: 45475.751 | B9: pgarciasbm@gmail.com | C9: Humaitá | D9: 45455 | E9: 0.51805556 | F9: INCÊNDIO FLORESTAL | G9: 3 | H9: -7.52034"S,--63.03682 | I9: Rua Dom José, São Sebastião | J9: 50 | K9: 700 | L9: 4 | M9: 6 | N9: 00 | O9: 00 | P9: 6 | Q9: 00 | R9: 00 | S9: 00 | T9: 00 | U9: 00 | V9: 00 | W9: 00 | X9: 00 | Y9: 00 | Z9: 00 | AA9: 1 | AB9: 1 | AC9: 00 | AD9: 00 | AE9: 00 | AF9: 1 | AG9: 00 | AH9: 00 | AI9: 2 | AJ9: 00 | AK9: 1 | AL9: 3 | AM9: 00 | AN9: 00 | AO9: 00 | AP9: 00 | AQ9: 00
A10: 45475.758 | B10: pgarciasbm@gmail.com | C10: Humaitá | D10: 45455 | E10: 0.57291667 | F10: INCÊNDIO FLORESTAL | G10: 15 | H10: -7.52194"S,--63.03833"W | I10: Br 230, km 1 | J10: 1000 | K10: 4000 | L10: 4 | M10: 6 | N10: 00 | O10: 00 | P10: 6 | Q10: 6 | R10: 00 | S10: 00 | T10: 00 | U10: 00 | V10: 00 | W10: 00 | X10: 00 | Y10: 00 | Z10: 00 | AA10: 2 | AB10: 1 | AC10: 00 | AD10: 00 | AE10: 00 | AF10: 1 | AG10: 00 | AH10: 00 | AI10: 2 | AJ10: 00 | AK10: 1 | AL10: 03 | AM10: 00 | AN10: 00 | AO10: 00 | AP10: 09 | AQ10: 00
A11: 45475.763 | B11: pgarciasbm@gmail.com | C11: Humaitá | D11: 45455 | E11: 0.54583333 | F11: INCÊNDIO FLORESTAL | G11: 3 | H11: -7.52633"S,-63.03694 | I11: Rua Santa Civita, São Cristóvão | J11: 400 | K11: 1000 | L11: 4 | M11: 6 | N11: 00 | O11: 00 | P11: 6 | Q11: 6 | R11: 00 | S11: 00 | T11: 00 | U11: 0/ | V11: 00 | W11: 00 | X11: 00 | Y11: 00 | Z11: 00 | AA11: 2 | AB11: 1 | AC11: 00 | AD11: 00 | AE11: 00 | AF11: 1 | AG11: 00 | AH11: 00 | AI11: 2 | AJ11: 00 | AK11: 1 | AL11: 03 | AM11: 00 | AN11: 00 | AO11: 00 | AP11: 00 | AQ11: 00
A12: 45475.77 | B12: pgarciasbm@gmail.com | C12: Humaitá | D12: 45455 | E12: 0.60416667 | F12: INCÊNDIO FLORESTAL | G12: 10 | H12: -7.54234"S,--63.04496 | I12: Rua Castanheira, loteamento Santa Clara | J12: 1000 | K12: 4000 | L12: 4 | M12: 6 | N12: 00 | O12: 00 | P12: 6 | Q12: 6 | R12: 00 | S12: 00 | T12: 00 | U12: 00 | V12: 00 | W12: 00 | X12: 00 | Y12: 00 | Z12: 00 | AA12: 2 | AB12: 1 | AC12: 00 | AD12: 00 | AE12: 00 | AF12: 1 | AG12: 00 | AH12: 00 | AI12: 2 | AJ12: 00 | AK12: 1 | AL12: 03 | AM12: 00 | AN12: 00 | AO12: 00 | AP12: 00 | AQ12: 00
A13: 45475.629 | B13: joaofelipe292@gmail.com | C13: Boca do Acre | D13: 45456 | E13: 0.61805556 | F13: INCÊNDIO FLORESTAL | G13: 15 | H13: 8.7799141S 67.32562544W | I13: bairro concordia | J13: 250 | K13: 200 | P13: 4 | AF13: 1
A14: 45475.634 | B14: joaofelipe292@gmail.com | C14: Boca do Acre | D14: 45456 | E14: 0.61805556 | F14: INCÊNDIO FLORESTAL | G14: 15 | H14: 08°48'14.06" S 67°16'12.59" W 140 | I14: ramal do Ditão, proximo ao aterro sanitário | J14: 10000 | K14: 600 | P14: 04 | AF14: 1
A15: 45475.776 | B15: pgarciasbm@gmail.com | C15: Humaitá | D15: 45456 | E15: 0.93333333 | F15: INCÊNDIO FLORESTAL | G15: 2 | H15: -7.54172,"S,--63.06588"W | I15: Br 230, km 5 | J15: 50 | K15: 700 | L15: 4 | M15: 6 | N15: 00 | O15: 00 | P15: 6 | Q15: 00 | R15: 00 | S15: 00 | T15: 00 | U15: 00 | V15: 00 | W15: 00 | X15: 00 | Y15: 00 | Z15: 00 | AA15: 2 | AB15: 1 | AC15: 00 | AD15: 00 | AE15: 00 | AF15: 1 | AG15: 00 | AH15: 00 | AI15: 2 | AJ15: 00 | AK15: 1 | AL15: 00 | AM15: 00 | AN15: 00 | AO15: 00 | AP15: 00 | AQ15: 00
A16: 45475.783 | B16: pgarciasbm@gmail.com | C16: Humaitá | D16: 45458 | E16: 0.70833333 | F16: INCÊNDIO FLORESTAL | G16: 3 | H16: -7.49291"S,-63.02613"W | I16: Rua da Portobras, São Domingos Sávio | J16: 50 | K16: 2500 | L16: 4 | M16: 6 | N16: 00 | O16: 00 | P16: 6 | Q16: 00 | R16: 00 | S16: 00 | T16: 00 | U16: 00 | V16: 00 | W16: 00 | X16: 00 | Y16: 00 | Z16: 00 | AA16: 0 | AB16: 1 | AC16: 00 | AD16: 00 | AE16: 00 | AF16: 00 | AG16: 00 | AH16: 00 | AI16: 00 | AJ16: 00 | AK16: 00 | AL16: 00 | AM16: 00 | AN16: 00 | AO16: 00 | AP16: 00 | AQ16: 00
A17: 45475.788 | B17: pgarciasbm@gmail.com | C17: Humaitá | D17: 45458 | E17: 0.70833333 | F17: INCÊNDIO FLORESTAL | G17: 10 | H17: -7.50706"S,-63.04240"W | I17: Rua Campos Sales, Nova Esperança | J17: 1000 | K17: 2500 | L17: 4 | M17: 6 | N17: 00 | O17: 00 | P17: 6 | Q17: 00 | R17: 00 | S17: 00 | T17: 00 | U17: 00 | V17: 00 | W17: 00 | X17: 00 | Y17: 00 | Z17: 00 | AA17: 00 | AB17: 1 | AC17: 00 | AD17: 00 | AE17: 00 | AF17: 1 | AG17: 00 | AH17: 00 | AI17: 00 | AJ17: 00 | AK17: 00 | AL17: 00 | AM17: 00 | AN17: 00 | AO17: 00 | AP17: 00 | AQ17: 00
A18: 45476.406 | B18: pdfimahumaita@gmail.com | C18: Humaitá | D18: 45458 | E18: 0.70833333 | F18: INCÊNDIO FLORESTAL | G18: 3 | H18: -7⁰29'34,58423"S-63⁰1'33,87976"W19⁰N | I18: RUA: PORTOBRÁS, N⁰ 550 (BAIRRO: SÃO DOMINGOS SÁVIO) | J18: 600 | K18: 2000 | L18: 04 | M18: 06 | N18: 00 | O18: 00 | P18: 20 | Q18: 00 | R18: 00 | S18: 00 | T18: 00 | U18: 00 | V18: 00 | W18: 00 | X18: 00 | Y18: 00 | Z18: 00 | AA18: 00 | AB18: 01 | AC18: 00 | AD18: 00 | AE18: 00 | AF18: 00 | AG18: 00 | AH18: 00 | AI18: 00 | AJ18: 00 | AK18: 00 | AL18: 00 | AM18: 00 | AN18: 00 | AO18: 00 | AP18: 00 | AQ18: 00
A19: 45476.424 | B19: pdfimahumaita@gmail.com | C19: Humaitá | D19: 45458 | E19: 0.81875 | F19: INCÊNDIO FLORESTAL | G19: 3 | H19: -7⁰30'25,40381"S-63⁰2'32,20955"W248⁰W | I19: RUA: CAMPOS SALES, N⁰ 2384 (NOVA HUMAITÁ) | J19: 500 | K19: 400 | L19: 04 | M19: 06 | N19: 00 | O19: 00 | P19: 00 | Q19: 00 | R19: 00 | S19: 00 | T19: 00 | U19: 00 | V19: 00 | W19: 00 | X19: 00 | Y19: 00 | Z19: 00 | AA19: 00 | AB19: 00 | AC19: 00 | AD19: 00 | AE19: 00 | AF19: 01 | AG19: 00 | AH19: 00 | AI19: 00 | AJ19: 00 | AK19: 00 | AL19: 00 | AM19: 00 | AN19: 00 | AO19: 00 | AP19: 00 | AQ19: 00
A20: 45476.432 | B20: pdfimahumaita@gmail.com | C20: Humaitá | D20: 45458 | E20: 0.79861111 | F20: INCÊNDIO FLORESTAL | G20: 10 | H20: -7⁰30'25,38253"S-63⁰2'21408"W280⁰W | I20: RUA: CAMPOS SALES (BAIRRO: NOVA ESPERANÇA) | J20: 1000 | K20: 2000 | L20: 04 | M20: 06 | N20: 00 | O20: 00 | P20: 00 | Q20: 00 | R20: 00 | S20: 00 | T20: 00 | U20: 00 | V20: 00 | W20: 00 | X20: 00 | Y20: 00 | Z20: 00 | AA20: 00 | AB20: 01 | AC20: 00 | AD20: 00 | AE20: 00 | AF20: 00 | AG20: 00 | AH20: 00 | AI20: 00 | AJ20: 00 | AK20: 00 | AL20: 00 | AM20: 00 | AN20: 00 | AO20: 00 | AP20: 00 | AQ20: 00
A21: 45475.639 | B21: joaofelipe292@gmail.com | C21: Boca do Acre | D21: 45459 | E21: 0.66666667 | F21: INCÊNDIO FLORESTAL | G21: 26 | H21: 8.77711604S 67.33723269W | I21: loteamento jardim modelo, bairro São Cristóvão | J21: 70000 | K21: 3000 | P21: 04
A22: 45475.794 | B22: pgarciasbm@gmail.com | C22: Humaitá | D22: 45459 | E22: 0.62361111 | F22: INCÊNDIO FLORESTAL | G22: 3 | H22: -7.52536"S,-63.04117"W | I22: Rua Bom Conselho, conjunto Habitacional Uruapiara | J22: 300 | K22: 2500 | L22: 4 | M22: 2 | N22: 00 | O22: 00 | P22: 2 | Q22: 00 | R22: 00 | S22: 00 | T22: 00 | U22: 00 | V22: 00 | W22: 00 | X22: 00 | Y22: 00 | Z22: 00 | AA22: 00 | AB22: 1 | AC22: 00 | AD22: 00 | AE22: 00 | AF22: 00 | AG22: 00 | AH22: 00 | AI22: 00 | AJ22: 00 | AK22: 00 | AL22: 00 | AM22: 00 | AN22: 00 | AO22: 00 | AP22: 00 | AQ22: 00
A23: 45475.69 | B23: bmpaulolopes@gmail.com | C23: Manicoré | D23: 45460 | E23: 0.50486111 | F23: INCÊNDIO FLORESTAL | G23: 15 | I23: Campo do Cruzeiro - Estrada do Aeroporto - Bairro Laura Vicuna | J23: 2275 | K23: 600 | L23: 1 | M23: 0 | N23: 0 | O23: 0 | P23: 3 | Q23: 0 | R23: 0 | S23: 4 | T23: 0 | U23: 0 | V23: 0 | W23: 0 | X23: 0 | Y23: 0 | Z23: 0 | AA23: 0 | AB23: 0 | AC23: 0 | AD23: 0 | AE23: 0 | AF23: 1 | AG23: 0 | AH23: 0 | AI23: 0 | AJ23: 0 | AK23: 0 | AL23: 0 | AM23: 0 | AN23: 0 | AO23: 0 | AP23: 0 | AQ23: 0
A24: 45475.706 | B24: reneltonbatalha123@gmail.com | C24: Apuí | D24: 45460 | E24: 0.76736111 | F24: INCÊNDIO FLORESTAL | G24: 6 | I24: Bairro Cachoeirinha ao lado da UEA | J24: 700 | K24: 300 | L24: 0 | M24: 0 | N24: 0 | O24: 0 | P24: 04 | Q24: 0 | R24: 0 | S24: 0 | T24: 0 | U24: 0 | V24: 0 | W24: 0 | X24: 0 | Y24: 0 | Z24: 0 | AA24: 0 | AB24: 0 | AC24: 0 | AD24: 0 | AE24: 0 | AF24: 01 | AG24: 0 | AH24: 0 | AI24: 0 | AJ24: 0 | AK24: 0 | AL24: 0 | AM24: 0 | AN24: 0 | AO24: 0 | AP24: 0 | AQ24: 0
A25: 45475.799 | B25: pgarciasbm@gmail.com | C25: Humaitá | D25: 45460 | E25: 0.020138889 | F25: INCÊNDIO FLORESTAL | G25: 18 | H25: -7.52187"S,-63.03832 | I25: Br 230, 1 | J25: 2000 | K25: 2000 | L25: 00 | M25: 2 | N25: 00 | O25: 00 | P25: 2 | Q25: 00 | R25: 00 | S25: 00 | T25: 00 | U25: 00 | V25: 00 | W25: 00 | X25: 00 | Y25: 00 | Z25: 00 | AA25: 00 | AB25: 1 | AC25: 00 | AD25: 00 | AE25: 00 | AF25: 00 | AG25: 00 | AH25: 00 | AI25: 00 | AJ25: 00 | AK25: 00 | AL25: 00 | AM25: 00 | AN25: 00 | AO25: 00 | AP25: 00 | AQ25: 00
A26: 45475.711 | B26: reneltonbatalha123@gmail.com | C26: Apuí | D26: 45461 | E26: 0.52430556 | F26: INCÊNDIO FLORESTAL | G26: 7 | I26: BR 230, KM3 | J26: 1200 | K26: 600 | L26: 0 | M26: 0 | N26: 0 | O26: 0 | P26: 03 | Q26: 0 | R26: 0 | S26: 0 | T26: 0 | U26: 0 | V26: 0 | W26: 0 | X26: 0 | Y26: 0 | Z26: 0 | AA26: 0 | AB26: 0 | AC26: 0 | AD26: 0 | AE26: 0 | AF26: 01 | AG26: 0 | AH26: 0 | AI26: 0 | AJ26: 0 | AK26: 0 | AL26: 0 | AM26: 0 | AN26: 0 | AO26: 0 | AP26: 0 | AQ26: 0
A27: 45475.715 | B27: reneltonbatalha123@gmail.com | C27: Apuí | D27: 45462 | E27: 0.78472222 | F27: INCÊNDIO FLORESTAL | G27: 9 | I27: Vicinal Coruja | J27: 3000 | K27: 200 | L27: 0 | M27: 0 | N27: 0 | O27: 0 | P27: 04 | Q27: 04 | R27: 0 | S27: 0 | T27: 0 | U27: 0 | V27: 0 | W27: 0 | X27: 0 | Y27: 0 | Z27: 0 | AA27: 0 | AB27: 0 | AC27: 0 | AD27: 0 | AE27: 0 | AF27: 01 | AG27: 0 | AH27: 0 | AI27: 0 | AJ27: 0 | AK27: 0 | AL27: 01 | AM27: 0 | AN27: 0 | AO27: 0 | AP27: 0 | AQ27: 0
A28: 45475.813 | B28: pgarciasbm@gmail.com | C28: Humaitá | D28: 45462 | E28: 0.90625 | F28: INCÊNDIO FLORESTAL | G28: 6 | H28: -7.50576"S,-63.03741"W | I28: Rua Dom José, Nova Esperança | J28: 400 | K28: 500 | L28: 00 | M28: 2 | N28: 00 | O28: 00 | P28: 2 | Q28: 00 | R28: 00 | S28: 00 | T28: 00 | U28: 00 | V28: 00 | W28: 00 | X28: 00 | Y28: 00 | Z28: 09 | AA28: 00 | AB28: 1 | AC28: 00 | AD28: 00 | AE28: 00 | AF28: 00 | AG28: 00 | AH28: 00 | AI28: 00 | AJ28: 00 | AK28: 00 | AL28: 00 | AM28: 00 | AN28: 00 | AO28: 00 | AP28: 00 | AQ28: 00
A29: 45475.625 | B29: wagnneerrd@gmail.com | C29: Humaitá | D29: 45463 | E29: 0.44305556 | F29: INCÊNDIO FLORESTAL | G29: 22 | I29: Alto Crato | J29: 20000 | K29: 20000 | L29: 3 | P29: 6 | Q29: 12 | AA29: 1
A30: 45475.628 | B30: wagnneerrd@gmail.com | C30: Humaitá | D30: 45463 | E30: 0.50069444 | F30: INCÊNDIO FLORESTAL | G30: 12 | I30: Rua Dom José. Bairro Nova Humaitá. | J30: 2000 | K30: 6000 | P30: 6 | Q30: 12 | AA30: 1
A31: 45483.676 | B31: salacbmam@gmail.com | C31: Novo Airão | D31: 45463 | E31: 0.8125 | F31: INCÊNDIO FLORESTAL | G31: 5 | I31: Rua Almerinda Malaquias, Caminho das Índias, 241 | J31: 400 | K31: 10000 | O31: 3 | R31: 3
A32: 45468.656 | B32: avs.vanessaalves@gmail.com | C32: Autazes | D32: 45464 | E32: 0.64236111 | F32: INCÊNDIO FLORESTAL | G32: 4 | H32: -3°35'29,592"S -59°8'15,522"W | I32: Estrada da Fábrica de Gelo Bairro Mutirão | J32: 600 | K32: 2000 | L32: 00 | M32: 03 | N32: 00 | O32: 00 | P32: 08 | Q32: 00 | R32: 00 | S32: 01 | T32: 00 | U32: 00 | V32: 00 | W32: 00 | X32: 00 | Y32: 00 | Z32: 00 | AA32: 00 | AB32: 00 | AC32: 00 | AD32: 00 | AE32: 00 | AF32: 00 | AG32: 00 | AH32: 00 | AI32: 00 | AJ32: 00 | AK32: 00 | AL32: 00 | AM32: 01 | AN32: 00 | AO32: 00 | AP32: 00 | AQ32: 00
A33: 45475.6 | B33: haninhalopes02@gmail.com | C33: Novo Aripuanã | D33: 45464 | E33: 0.45833333 | F33: INCÊNDIO FLORESTAL | G33: 3 | I33: Rua Rogério Braga, s/n bairro Tucumã | K33: 300 | L33: 6 | M33: 2 | N33: 0 | O33: 0 | P33: 6 | Q33: 0 | R33: 0 | S33: 0 | T33: 0 | U33: 0 | V33: 0 | W33: 0 | X33: 0 | Y33: 0 | Z33: 0 | AA33: 0 | AB33: 0 | AC33: 0 | AD33: 0 | AE33: 0 | AF33: 1 | AG33: 0 | AH33: 0 | AI33: 0 | AJ33: 0 | AK33: 0 | AL33: 0 | AM33: 0 | AN33: 0 | AO33: 0 | AP33: 0 | AQ33: 0
A34: 45475.94 | B34: farm.edumaga@gmail.com | C34: Manaquiri | D34: 45464 | E34: 0.69444444 | F34: INCÊNDIO FLORESTAL | G34: 3 | H34: -3.2636, 60.2739 | J34: 100 | K34: 30 | L34: 02 | M34: 03 | P34: 08 | S34: 09 | AF34: 01
A35: 45475.943 | B35: farm.edumaga@gmail.com | C35: Manaquiri | D35: 45464 | E35: 0.76736111 | F35: INCÊNDIO FLORESTAL | G35: 1 | H35: -3.2615, -60.2711 | J35: 10 | K35: 0 | L35: 02 | M35: 03 | P35: 08 | S35: 09 | AF35: 01
A36: 45476.363 | B36: pdfimahumaita@gmail.com | C36: Humaitá | D36: 45464 | E36: 0.96805556 | F36: INCÊNDIO FLORESTAL | G36: 5 | H36: -7⁰31'5,27912"S-63⁰,02929"W5⁰N | I36: BR-230, KM-02 (BAIRRO: SÃO PEDRO) | J36: 800 | K36: 1000 | L36: 04 | M36: 06 | N36: 00 | O36: 00 | P36: 20 | Q36: 00 | R36: 00 | S36: 00 | T36: 00 | U36: 00 | V36: 00 | W36: 00 | X36: 00 | Y36: 00 | Z36: 00 | AA36: 01 | AB36: 00 | AC36: 00 | AD36: 00 | AE36: 00 | AF36: 00 | AG36: 00 | AH36: 00 | AI36: 00 | AJ36: 00 | AK36: 00 | AL36: 00 | AM36: 00 | AN36: 00 | AO36: 00 | AP36: 00 | AQ36: 00
A37: 45476.379 | B37: pdfimahumaita@gmail.com | C37: Humaitá | D37: 45464 | E37: 0.77430556 | F37: INCÊNDIO FLORESTAL | G37: 3 | H37: -7⁰34'13,69617"S-63⁰4'21,85893"W | I37: BR-319, KM-11 (ÁREA RURAL) | J37: 1700 | K37: 4000 | L37: 04 | M37: 06 | N37: 00 | O37: 00 | P37: 20 | Q37: 00 | R37: 00 | S37: 00 | T37: 00 | U37: 00 | V37: 00 | W37: 00 | X37: 00 | Y37: 00 | Z37: 00 | AA37: 01 | AB37: 00 | AC37: 00 | AD37: 00 | AE37: 00 | AF37: 00 | AG37: 00 | AH37: 00 | AI37: 00 | AJ37: 00 | AK37: 00 | AL37: 00 | AM37: 00 | AN37: 00 | AO37: 00 | AP37: 00 | AQ37: 00
A38: 45468.632 | B38: meirebm07@gmail.com | C38: Autazes | D38: 45465 | E38: 0.40972222 | F38: INCÊNDIO FLORESTAL | G38: 1 | H38: -3.585751, -59.133087 | I38: Rua Presidente Kennedy, n. 06, Bairro Multirão | J38: 0 | K38: 0 | L38: 2 | M38: 4 | N38: 0 | O38: 0 | P38: 8 | Q38: 0 | R38: 0 | S38: 0 | T38: 0 | U38: 0 | V38: 0 | W38: 0 | X38: 0 | Y38: 0 | Z38: 0 | AA38: 0 | AB38: 0 | AC38: 0 | AD38: 0 | AE38: 0 | AF38: 0 | AG38: 0 | AH38: 0 | AI38: 0 | AJ38: 0 | AK38: 0 | AL38: 0 | AM38: 1 | AN38: 0 | AO38: 0 | AP38: 0 | AQ38: 0
A39: 45468.637 | B39: meirebm07@gmail.com | C39: Autazes | D39: 45465 | E39: 0.63888889 | F39: INCÊNDIO FLORESTAL | G39: 1 | H39: -3.5755850, -59.1129800 | I39: Lago do Gomo, Sítio Aquários, próx UBS Salvina Pontes | J39: 2100 | K39: 40 | L39: 02 | M39: 04 | N39: 0 | O39: 00 | P39: 08 | Q39: 00 | R39: 04 | S39: 00 | T39: 00 | U39: 00 | V39: 00 | W39: 00 | X39: 00 | Y39: 00 | Z39: 00 | AA39: 00 | AB39: 00 | AC39: 00 | AD39: 00 | AE39: 00 | AF39: 00 | AG39: 00 | AH39: 00 | AI39: 00 | AJ39: 00 | AK39: 00 | AL39: 00 | AM39: 01 | AN39: 00 | AO39: 00 | AP39: 00 | AQ39: 00
A40: 45468.64 | B40: meirebm07@gmail.com | C40: Autazes | D40: 45465 | E40: 0.75 | F40: INCÊNDIO FLORESTAL | G40: 1 | H40: -3.613791, -59.134687 | I40: Estrada do Rosarinho, s/n, próx. Casa da Cultura | J40: 0 | K40: 0 | L40: 02 | M40: 04 | N40: 00 | O40: 00 | P40: 08 | Q40: 00 | R40: 00 | S40: 00 | T40: 00 | U40: 00 | V40: 00 | W40: 00 | X40: 00 | Y40: 00 | Z40: 00 | AA40: 00 | AB40: 00 | AC40: 00 | AD40: 00 | AE40: 00 | AF40: 00 | AG40: 00 | AH40: 00 | AI40: 00 | AJ40: 00 | AK40: 00 | AL40: 00 | AM40: 01 | AN40: 00 | AO40: 00 | AP40: 00 | AQ40: 00
A41: 45475.673 | B41: srodriguesid7@gmail.com | C41: Lábrea | D41: 45465 | E41: 0.69097222 | F41: INCÊNDIO FLORESTAL | G41: 2 | H41: S-7° 17,578. W64° 46, 049 226° SE | I41: Rodovia 230, KM 4 | J41: 200 | K41: 100 | L41: 1 | M41: 3 | N41: 0 | O41: 0 | P41: 7 | Q41: 2 | R41: 0 | S41: 0 | T41: 0 | U41: 0 | V41: 0 | W41: 0 | X41: 0 | Y41: 0 | Z41: 0 | AA41: 0 | AB41: 0 | AC41: 0 | AD41: 0 | AE41: 0 | AF41: 1 | AG41: 0 | AH41: 0 | AI41: 0 | AJ41: 0 | AK41: 0 | AL41: FN-01 | AM41: 1 | AN41: 0 | AO41: 0 | AP41: 0 | AQ41: 0
A42: 45475.678 | B42: srodriguesid7@gmail.com | C42: Lábrea | D42: 45465 | E42: 0.76319444 | F42: INCÊNDIO FLORESTAL | G42: 1 | H42: S-7° 15,828, W64°, 46,645, 298° NW | I42: Ramal durapox, Bairro Novo, S/N | J42: 50 | K42: 200 | L42: 1 | M42: 3 | N42: 0 | O42: 0 | P42: 7 | Q42: 4 | R42: 0 | S42: 0 | T42: 0 | U42: 0 | V42: 0 | W42: 0 | X42: 0 | Y42: 0 | Z42: 0 | AA42: 0 | AB42: 0 | AC42: 0 | AD42: 0 | AE42: 0 | AF42: 1 | AG42: 0 | AH42: 0 | AI42: 0 | AJ42: 0 | AK42: 0 | AL42: FN-01 | AM42: 0 | AN42: 0 | AO42: 0 | AP42: 0 | AQ42: 0
A43: 45475.678 | B43: srodriguesid7@gmail.com | C43: Maués | D43: 45465 | F43: INCÊNDIO FLORESTAL | G43: 2
A44: 45475.678 | B44: srodriguesid7@gmail.com | C44: Lábrea | D44: 45465 | F44: INCÊNDIO FLORESTAL | G44: 1
A45: 45475.698 | B45: bmpaulolopes@gmail.com | C45: Manicoré | D45: 45465 | E45: 0.8125 | F45: INCÊNDIO FLORESTAL | G45: 1 | H45: -5.806857, -61.294384 | I45: Travessa Manaus, 350 - Bairro São Domingos | J45: 4 | K45: 40 | L45: 1 | M45: 0 | N45: 0 | O45: 0 | P45: 4 | Q45: 0 | R45: 0 | S45: 1 | T45: 0 | U45: 0 | V45: 0 | W45: 0 | X45: 0 | Y45: 0 | Z45: 0 | AA45: 0 | AB45: 0 | AC45: 0 | AD45: 0 | AE45: 0 | AF45: 1 | AG45: 0 | AH45: 0 | AI45: 0 | AJ45: 0 | AK45: 0 | AL45: 0 | AM45: 0 | AN45: 0 | AO45: 0 | AP45: 0 | AQ45: 0
A46: 45475.966 | B46: isaxavier899@gmail.com | C46: Manaquiri | D46: 45465 | E46: 0.72291667 | F46: INCÊNDIO FLORESTAL | G46: 2 | I46: Local: Rua Francisco Jacob, nº 235 – Manaquiri-AM | J46: 20 | K46: 20 | L46: 02 | M46: 3 | P46: 8 | R46: 2 | AC46: 1 | AF46: 1
A47: 45475.604 | B47: haninhalopes02@gmail.com | C47: Novo Aripuanã | D47: 45466 | E47: 0.64236111 | F47: INCÊNDIO FLORESTAL | G47: 2 | I47: Ramal do Baia, serraria do Paulo Alho | J47: 18 | K47: 600 | L47: 6 | M47: 2 | N47: 0 | O47: 0 | P47: 6 | Q47: 0 | R47: 0 | S47: 0 | T47: 0 | U47: 0 | V47: 6 | W47: 0 | X47: 0 | Y47: 0 | Z47: 0 | AA47: 0 | AB47: 0 | AC47: 0 | AD47: 0 | AE47: 0 | AF47: 1 | AG47: 0 | AH47: 0 | AI47: 0 | AJ47: 0 | AK47: 0 | AL47: 0 | AM47: 0 | AN47: 0 | AO47: 0 | AP47: 0 | AQ47: 0
A48: 45475.617 | B48: ribeiroalmedino@gmail.com | C48: Lábrea | D48: 45466 | E48: 0.775 | F48: INCÊNDIO FLORESTAL | G48: 12 | H48: -7.256723,-64.764671 | I48: Estrada do Barreiro Ramal Tarumã | J48: 12500 | K48: 500 | P48: 2 | Q48: 2 | R48: 0 | S48: 0 | T48: 0 | AF48: 1 | AL48: 01/ 1207
A49: 45475.692 | B49: fpaulo32525@gmail.com | C49: Manicoré | D49: 45466 | E49: 0.70833333 | F49: INCÊNDIO FLORESTAL | G49: 16 | I49: TERRENO DA TÂNIA DO CARTÓRIO ÁREA RURAL | J49: 2500 | K49: 550 | L49: 1 | M49: 0 | N49: 0 | O49: 0 | P49: 3 | Q49: 0 | R49: 0 | S49: 2 | T49: 0 | U49: 0 | V49: 0 | W49: 0 | X49: 0 | Y49: 0 | Z49: 0 | AA49: 0 | AB49: 0 | AC49: 0 | AD49: 0 | AE49: 0 | AF49: 1 | AG49: 0 | AH49: 0 | AI49: 0 | AJ49: 0 | AK49: 0 | AL49: 0 | AM49: 0 | AN49: 0 | AO49: 0 | AP49: 0 | AQ49: 0
A50: 45475.948 | B50: farm.edumaga@gmail.com | C50: Manaquiri | D50: 45466 | E50: 0.8125 | F50: INCÊNDIO FLORESTAL | G50: 1 | I50: Rua 03, próx a delegacia da polícia civil. | J50: 15 | K50: 20 | L50: 02 | M50: 03 | P50: 08 | S50: 09 | AF50: 01
A51: 45467.68 | B51: reneltonbatalha123@gmail.com | C51: Apuí | D51: 45467 | E51: 0.50416667 | F51: INCÊNDIO FLORESTAL | G51: 17 | H51: -7°12'37,002'S-59°53'9,06W | I51: Rua do silêncio, bairro São Sebastião, município Apuí | J51: 4000 | K51: 1500 | L51: 01 | M51: 0 | N51: 0 | O51: 0 | P51: 04 | Q51: 0 | R51: 08 | S51: 01 | T51: 0 | U51: 0 | V51: 0 | W51: 0 | X51: 0 | Y51: 0 | Z51: 0 | AA51: 0 | AB51: 0 | AC51: 0 | AD51: 0 | AE51: 0 | AF51: 1 | AG51: 0 | AH51: 0 | AI51: 0 | AJ51: 0 | AK51: 0 | AL51: 0 | AM51: 01 | AN51: 0 | AO51: 0 | AP51: 0 | AQ51: 0
A52: 45467.789 | B52: mvmaiquior@gmail.com | C52: Manicoré | D52: 45467 | E52: 0.58333333 | F52: INCÊNDIO FLORESTAL | G52: 4 | H52: 5°49'13,38514"s 61°17'10,93575"W 5°4913,37639"S 61°17'10,94782"w 5°49'13,39389"s 61°17'10,943"W 5°49'13,4034"s 61°17'10,77522"w | I52: Estrada do Alonso (atrás da UEA) - Manicorézinho | J52: 750 | K52: 750 | N52: Nenhum | P52: 03 - militares | R52: 01 | AF52: 1
A53: 45467.874 | B53: joaofelipe292@gmail.com | C53: Boca do Acre | D53: 45467 | E53: 0.82986111 | F53: INCÊNDIO FLORESTAL | G53: 3 | H53: 8,78029198S 67.33549262W | I53: proximo ao ABB | J53: 900 | K53: 200 | L53: 02 | M53: 02 | N53: 0 | O53: 0 | P53: 8 | Q53: 4 | R53: 0 | S53: 0 | T53: 0 | U53: 0 | V53: 0 | W53: 0 | X53: 0 | Y53: 0 | Z53: 0 | AA53: 0 | AB53: 0 | AC53: 0 | AD53: 0 | AE53: 0 | AF53: 1 | AG53: 0 | AH53: 0 | AI53: 0 | AJ53: 0 | AK53: 0 | AL53: 0 | AM53: 0 | AN53: 0 | AO53: 0 | AP53: 0 | AQ53: 0
A54: 45475.607 | B54: haninhalopes02@gmail.com | C54: Novo Aripuanã | D54: 45467 | E54: 0.49236111 | F54: INCÊNDIO FLORESTAL | G54: 4 | I54: Rua Rogério Braga s/n, nas dependências do Hospital Edith Mendes. | J54: 3000 | K54: 300 | L54: 6 | M54: 2 | N54: 0 | O54: 0 | P54: 6 | Q54: 0 | R54: 0 | S54: 0 | T54: 0 | U54: 0 | V54: 0 | W54: 0 | X54: 0 | Y54: 0 | Z54: 0 | AA54: 0 | AB54: 0 | AC54: 0 | AD54: 0 | AE54: 0 | AF54: 1 | AG54: 0 | AH54: 0 | AI54: 0 | AJ54: 0 | AK54: 0 | AL54: 0 | AM54: 0 | AN54: 0 | AO54: 0 | AP54: 0 | AQ54: 0
A55: 45475.641 | B55: joaofelipe292@gmail.com | C55: Boca do Acre | D55: 45467 | E55: 0.82638889 | F55: INCÊNDIO FLORESTAL | G55: 3 | H55: 8,78029198S 67.33549262W | I55: Loteamento jardim modelo | J55: 900 | K55: 200 | P55: 04 | AF55: 1
A56: 45475.661 | B56: carloslopes1116bm@gmail.com | C56: Lábrea | D56: 45467 | E56: 0.50347222 | F56: INCÊNDIO FLORESTAL | G56: 4 | I56: Estrada do barreiro, zona rural. | J56: 1000 | K56: 200 | L56: 00 | M56: 00 | N56: 00 | O56: 00 | P56: 03 | Q56: 02 | R56: 00 | S56: 00 | T56: 00 | U56: 00 | V56: 00 | W56: 00 | X56: 00 | Y56: 00 | Z56: 00 | AA56: 00 | AB56: 00 | AC56: 00 | AD56: 00 | AE56: 00 | AF56: 1 | AG56: 00 | AH56: 00 | AI56: 00 | AJ56: 00 | AK56: 00 | AL56: 01 | AM56: 00 | AN56: 00 | AO56: 00 | AP56: 00 | AQ56: 00
A57: 45475.704 | B57: bmpaulolopes@gmail.com | C57: Manicoré | D57: 45467 | E57: 0.58333333 | F57: INCÊNDIO FLORESTAL | G57: 4 | H57: -5°49'13,39389"S -61°17'10,943'' | I57: Estrada do Alonso, Bairro Manicorezinho | J57: 350 | K57: 750 | L57: 1 | M57: 0 | N57: 0 | O57: 0 | P57: 3 | Q57: 0 | R57: 0 | S57: 1 | T57: 0 | U57: 0 | V57: 0 | W57: 0 | X57: 0 | Y57: 0 | Z57: 0 | AA57: 0 | AB57: 0 | AC57: 0 | AD57: 0 | AE57: 0 | AF57: 1 | AG57: 0 | AH57: 0 | AI57: 0 | AJ57: 0 | AK57: 0 | AL57: 0 | AM57: 0 | AN57: 0 | AO57: 0 | AP57: 0 | AQ57: 0
A58: 45475.719 | B58: reneltonbatalha123@gmail.com | C58: Apuí | D58: 45467 | E58: 0.47916667 | F58: INCÊNDIO FLORESTAL | G58: 22 | I58: Rua do silêncio, bairro São Sebastião | J58: 5000 | K58: 1500 | L58: 0 | M58: 0 | N58: 0 | O58: 0 | P58: 04 | Q58: 0 | R58: 09 | S58: 0 | T58: 0 | U58: 0 | V58: 0 | W58: 0 | X58: 0 | Y58: 0 | Z58: 0 | AA58: 0 | AB58: 0 | AC58: 0 | AD58: 0 | AE58: 0 | AF58: 01 | AG58: 0 | AH58: 0 | AI58: 0 | AJ58: 0 | AK58: 0 | AL58: 0 | AM58: 0 | AN58: 0 | AO58: 0 | AP58: 0 | AQ58: 0
A59: 45476.372 | B59: pdfimahumaita@gmail.com | C59: Humaitá | D59: 45467 | E59: 0.77777778 | F59: INCÊNDIO FLORESTAL | G59: 10 | H59: -732'34,971"S-63⁰3'49,153"W | I59: BR-230, KM-06 (ÁREA RURAL) | J59: 1500 | K59: 3000 | L59: 04 | M59: 06 | N59: 00 | O59: 00 | P59: 20 | Q59: 00 | R59: 00 | S59: 00 | T59: 00 | U59: 00 | V59: 00 | W59: 00 | X59: 00 | Y59: 00 | Z59: 00 | AA59: 01 | AB59: 00 | AC59: 00 | AD59: 00 | AE59: 00 | AF59: 00 | AG59: 00 | AH59: 00 | AI59: 00 | AJ59: 00 | AK59: 00 | AL59: 00 | AM59: 00 | AN59: 00 | AO59: 00 | AP59: 00 | AQ59: 00
A60: 45468.908 | B60: kah.bonnetcbmam@gmail.com | C60: Manaquiri | D60: 45468 | E60: 0.68888889 | F60: INCÊNDIO FLORESTAL | G60: 1 | H60: -3°25’53,362”S -60°27’11,36”W | I60: Rua Caetano Faria - Manaquiri/Am | J60: 10 | K60: 8 | L60: 3 | M60: 3 | P60: 8 | T60: 02 | AF60: 01
A61: 45468.911 | B61: kah.bonnetcbmam@gmail.com | C61: Manaquiri | D61: 45468 | E61: 0.69583333 | F61: INCÊNDIO FLORESTAL | G61: 1 | I61: -3°25’53.36” S-60°27’11.36”W | J61: 25 | K61: 10 | L61: 3 | M61: 3 | P61: 8 | AF61: 01
A62: 45468.914 | B62: kah.bonnetcbmam@gmail.com | C62: Manaquiri | D62: 45468 | E62: 0.72222222 | F62: INCÊNDIO FLORESTAL | G62: 1 | H62: -3°27’50,136S -60°27’44,418”W | I62: Zona Rural Manaquiri/Am | J62: 3 | K62: 5 | L62: 3 | M62: 3 | P62: 8 | T62: 02 | AF62: 01
A63: 45468.917 | B63: kah.bonnetcbmam@gmail.com | C63: Manaquiri | D63: 45468 | E63: 0.75 | F63: INCÊNDIO FLORESTAL | G63: 1 | H63: -3°26’26,543”S -60°27’37,254W | I63: Rua Osmar Freire Manaquiri/Am | J63: 4 | K63: 8 | L63: 3 | M63: 3 | P63: 8 | T63: 02 | AF63: 01
A64: 45468.943 | B64: joaofelipe292@gmail.com | C64: Boca do Acre | D64: 45468 | E64: 0.84166667 | F64: INCÊNDIO FLORESTAL | G64: 13 | H64: 8.77132581S 67.3278208W | I64: Rua BL DOZE | J64: 10000 | K64: 1200 | P64: 08 | Q64: 04 | AF64: 1
A65: 45475.609 | B65: haninhalopes02@gmail.com | C65: Novo Aripuanã | D65: 45468 | E65: 0.34722222 | F65: INCÊNDIO FLORESTAL | G65: 2 | I65: Lixão do município de novo Aripuanã | J65: 15 | K65: 200 | L65: 6 | M65: 2 | N65: 0 | O65: 0 | P65: 6 | Q65: 0 | R65: 0 | S65: 0 | T65: 0 | U65: 0 | V65: 0 | W65: 0 | X65: 0 | Y65: 0 | Z65: 0 | AA65: 0 | AB65: 0 | AC65: 0 | AD65: 0 | AE65: 0 | AF65: 1 | AG65: 0 | AH65: 0 | AI65: 0 | AJ65: 0 | AK65: 0 | AL65: 0 | AM65: 0 | AN65: 0 | AO65: 0 | AP65: 0 | AQ65: 0
A66: 45475.627 | B66: andrewodson@gmail.com | C66: Boca do Acre | D66: 45468 | E66: 0.84166667 | F66: INCÊNDIO FLORESTAL | G66: 13 | H66: 8.77132581S 67.3278208W | I66: RUA BL 12, TERRENO DA FÁBRICA DE AÇAÍ | J66: 10000 | K66: 1200 | P66: 08 | Q66: 04 | AF66: 1 | AL66: FN 01- 1026
A67: 45475.832 | B67: pgarciasbm@gmail.com | C67: Humaitá | D67: 45468 | E67: 0.68680556 | F67: INCÊNDIO FLORESTAL | G67: 10 | H67: -7°5,155,434"S-63°0,3874"W | I67: Rua Padre José Maria Penna, São Sebastião | J67: 10000 | K67: 4000 | L67: 4 | M67: 6 | N67: 00 | O67: 00 | P67: 6 | Q67: 00 | R67: 00 | S67: 00 | T67: 00 | U67: 00 | V67: 00 | W67: 00 | X67: 00 | Y67: 00 | Z67: 00 | AA67: 1 | AB67: 00 | AC67: 00 | AD67: 00 | AE67: 00 | AF67: 00 | AG67: 00 | AH67: 00 | AI67: 00 | AJ67: 00 | AK67: 00 | AL67: 00 | AM67: 00 | AN67: 00 | AO67: 00 | AP67: 00 | AQ67: 00
A68: 45475.839 | B68: pgarciasbm@gmail.com | C68: Humaitá | D68: 45468 | E68: 0.68680556 | F68: INCÊNDIO FLORESTAL | G68: 4 | H68: -7°518899"S,-63°°0,19089"W | I68: Avenida Gusmão, Nossa Senhora Do Carmo | J68: 80 | K68: 1500 | L68: 4 | M68: 6 | N68: 00 | O68: 00 | P68: 6 | Q68: 00 | R68: 00 | S68: 00 | T68: 00 | U68: 00 | V68: 00 | W68: 00 | X68: 00 | Y68: 00 | Z68: 00 | AA68: 1 | AB68: 00 | AC68: 00 | AD68: 00 | AE68: 00 | AF68: 00 | AG68: 00 | AH68: 00 | AI68: 00 | AJ68: 00 | AK68: 00 | AL68: 00 | AM68: 00 | AN68: 00 | AO68: 00 | AP68: 00 | AQ68: 00
A69: 45475.843 | B69: pgarciasbm@gmail.com | C69: Humaitá | D69: 45468 | E69: 0.75694444 | F69: INCÊNDIO FLORESTAL | G69: 4 | H69: -7°31,34,396"S,-63°1'27,301"W | I69: Rua Camilo, 355, Nossa Senhora do Carmo | J69: 60 | K69: 1500 | L69: 4 | M69: 6 | N69: 00 | O69: 00 | P69: 6 | Q69: 00 | R69: 00 | S69: 00 | T69: 00 | U69: 00 | V69: 00 | W69: 00 | X69: 00 | Y69: 00 | Z69: 00 | AA69: 01 | AB69: 00 | AC69: 00 | AD69: 00 | AE69: 00 | AF69: 00 | AG69: 00 | AH69: 00 | AI69: 00 | AJ69: 00 | AK69: 00 | AL69: 00 | AM69: 00 | AN69: 00 | AO69: 00 | AP69: 00 | AQ69: 00
A70: 45475.953 | B70: farm.edumaga@gmail.com | C70: Manaquiri | D70: 45468 | E70: 0.68888889 | F70: INCÊNDIO FLORESTAL | G70: 1 | H70: -3.2553, -60.2711 | J70: 10 | K70: 8 | L70: 02 | M70: 03 | S70: 09 | AF70: 01
A71: 45475.957 | B71: farm.edumaga@gmail.com | C71: Manaquiri | D71: 45468 | E71: 0.69791667 | F71: INCÊNDIO FLORESTAL | G71: 1 | H71: -3.2549, -60.271 | I71: Conjunto novo areal | J71: 25 | K71: 10 | L71: 02 | M71: 03 | R71: 02 | AF71: 01
A72: 45475.959 | B72: farm.edumaga@gmail.com | C72: Manaquiri | D72: 45468 | E72: 0.72222222 | F72: INCÊNDIO FLORESTAL | G72: 1 | H72: -3.2750, -60.2744 | I72: Zona rural de manaquiri | J72: 9 | K72: 9 | L72: 02 | M72: 03 | R72: 02 | AF72: 01
A73: 45475.961 | B73: farm.edumaga@gmail.com | C73: Manaquiri | D73: 45468 | E73: 0.75 | F73: INCÊNDIO FLORESTAL | G73: 1 | H73: -3.2626, -60.2737 | I73: Rua Osmar Freire | J73: 4 | K73: 5 | L73: 02 | M73: 03 | R73: 02 | AF73: 01
A74: 45469.801 | B74: reneltonbatalha123@gmail.com | C74: Apuí | D74: 45469 | E74: 0.70833333 | F74: INCÊNDIO FLORESTAL | G74: 6 | I74: Rua Zacarias, bairro cachoeirinha, próximo a faculdade UEA | J74: 1000 | K74: 600 | L74: 0 | M74: 0 | N74: 0 | O74: 0 | P74: 04 | Q74: 04 | R74: 0 | S74: 01 | T74: 0 | U74: 0 | V74: 0 | W74: 0 | X74: 0 | Y74: 0 | Z74: 0 | AA74: 0 | AB74: 0 | AC74: 0 | AD74: 0 | AE74: 0 | AF74: 01 | AG74: 0 | AH74: 0 | AI74: 0 | AJ74: 0 | AK74: 0 | AL74: 01 | AM74: 0 | AN74: 0 | AO74: 0 | AP74: 0 | AQ74: 0
A75: 45470.359 | B75: kah.bonnetcbmam@gmail.com | C75: Manaquiri | D75: 45469 | E75: 0.79166667 | F75: INCÊNDIO FLORESTAL | G75: 1 | H75: -3.4370609 S, -60.4561601 W | I75: Rua 3, s/n Manaquiri/Am | J75: 1 | K75: 0 | L75: 02 | M75: 03 | P75: 08 | AF75: 01
A76: 45470.448 | B76: gg.feio@gmail.com | C76: Manicoré | D76: 45469 | E76: 0.75 | F76: INCÊNDIO FLORESTAL | G76: 8 | H76: 60° NE, 67° NE, 70° NE, 95° NE, 221° NE, 223° NE, 140°NE, 141°NE ( demais dados naos foram carregados por falta de sinal de internet) | I76: Estrada do Banho do Antiniga | J76: 750 | K76: 450 | L76: 01 | M76: NA | N76: NA | O76: NA | P76: 03 | Q76: 0 | R76: 03 | S76: 01 | T76: 0 | U76: 0 | V76: NA | W76: 0 | X76: 0 | Y76: 0 | Z76: 0 | AA76: 0 | AB76: 0 | AC76: 0 | AD76: 0 | AE76: 0 | AF76: 01
A77: 45475.632 | B77: wagnneerrd@gmail.com | C77: Humaitá | D77: 45469 | E77: 0.62152778 | F77: INCÊNDIO FLORESTAL | G77: 16 | I77: Rua Portobras. Bairro São Domingos Sávio | J77: 2000 | K77: 4000 | P77: 6 | Q77: 12 | AA77: 1
A78: 45475.707 | B78: bmpaulolopes@gmail.com | C78: Manicoré | D78: 45469 | E78: 0.75347222 | F78: INCÊNDIO FLORESTAL | G78: 8 | H78: -5°52'26"S -61°14'51"W | I78: Estrada do Rio Atininga | J78: 750 | K78: 450 | L78: 1 | M78: 0 | N78: 0 | O78: 0 | P78: 3 | Q78: 0 | R78: 0 | S78: 1 | T78: 0 | U78: 0 | V78: 0 | W78: 0 | X78: 0 | Y78: 0 | Z78: 0 | AA78: 0 | AB78: 0 | AC78: 0 | AD78: 0 | AE78: 0 | AF78: 1 | AG78: 0 | AH78: 0 | AI78: 0 | AJ78: 0 | AK78: 0 | AL78: 0 | AM78: 0 | AN78: 0 | AO78: 0 | AP78: 0 | AQ78: 0
A79: 45475.723 | B79: reneltonbatalha123@gmail.com | C79: Apuí | D79: 45469 | E79: 0.70833333 | F79: INCÊNDIO FLORESTAL | G79: 6 | I79: Rua Zacarias BAIRRO Cachoeirinha | J79: 1000 | K79: 600 | L79: 0 | M79: 0 | N79: 0 | O79: 0 | P79: 04 | Q79: 04 | R79: 0 | S79: 0 | T79: 0 | U79: 0 | V79: 0 | W79: 0 | X79: 0 | Y79: 0 | Z79: 0 | AA79: 0 | AB79: 0 | AC79: 0 | AD79: 0 | AE79: 0 | AF79: 01 | AG79: 0 | AH79: 0 | AI79: 0 | AJ79: 0 | AK79: 0 | AL79: 01 | AM79: 0 | AN79: 0 | AO79: 0 | AP79: 0 | AQ79: 0
A80: 45475.965 | B80: farm.edumaga@gmail.com | C80: Manaquiri | D80: 45469 | F80: INCÊNDIO FLORESTAL | G80: 1
A81: 45475.965 | B81: farm.edumaga@gmail.com | C81: Manaquiri | D81: 45469 | E81: 0.79166667 | F81: INCÊNDIO FLORESTAL | G81: 1 | I81: Rua 03, s/n Manaquiri | J81: 6 | K81: 10 | L81: 02 | M81: 03 | P81: 08 | R81: 02 | AF81: 01
A82: 45470.659 | B82: andressastosilva@gmail.com | C82: Careiro Castanho | D82: 45470 | E82: 0.62222222 | F82: INCÊNDIO FLORESTAL | G82: 4 | H82: -3.811389 -60.352500 | I82: Rua Josino Matos Filho, Sebastião Borges, CAREIRO-AM | J82: 13 | K82: 0 | L82: 00 | M82: 00 | N82: 00 | O82: 00 | P82: 03 | Q82: 00 | R82: 02 | S82: 00 | T82: 00 | U82: 00 | V82: 00 | W82: 00 | X82: 00 | Y82: 00 | Z82: 00 | AA82: 00 | AB82: 00 | AC82: 00 | AD82: 00 | AE82: 00 | AF82: 01 | AG82: 00 | AH82: 00 | AI82: 00 | AJ82: 00 | AK82: 00 | AL82: 00 | AM82: 00 | AN82: 00 | AO82: 00 | AP82: 00 | AQ82: 00
A83: 45470.773 | B83: andrewodson@gmail.com | C83: Boca do Acre | D83: 45470 | E83: 0.63194444 | F83: INCÊNDIO FLORESTAL | G83: 6 | H83: -8° 48'19"S - 67°15'40" W | I83: Bairro do cruzeirinho 1 km após o lixao | J83: 10000 | K83: 1200 | L83: 0 | M83: 0 | N83: 0 | O83: 0 | P83: 8 | Q83: 04 | R83: 0 | S83: 0 | T83: 0 | U83: 0 | V83: 0 | AF83: 1 | AL83: FN01-1026
A84: 45470.783 | B84: conse.desegurancaalimentar@gmail.com | C84: Manaquiri | D84: 45470 | E84: 0.44097222 | F84: INCÊNDIO FLORESTAL | G84: 1 | H84: -3º27'21,624"S-60º27'40,486"W | I84: Rua 08, AM-354, KM 3, Manaquiri-AM. | J84: 30 | K84: 150 | L84: 0 | M84: 0 | N84: 0 | O84: 0 | P84: 8 | Q84: 0 | R84: 9 | S84: 0 | T84: 4 | U84: 0 | W84: 0 | X84: 0 | Y84: 0 | Z84: 0 | AA84: 0 | AB84: 0 | AC84: 0 | AD84: 0 | AE84: 0 | AF84: 1 | AG84: 0 | AH84: 0 | AI84: 0 | AJ84: 0 | AK84: 0 | AL84: 0 | AM84: 0 | AN84: 0 | AO84: 0 | AP84: 0 | AQ84: 0
A85: 45470.791 | B85: conse.desegurancaalimentar@gmail.com | C85: Manaquiri | D85: 45470 | E85: 0.46319444 | F85: INCÊNDIO FLORESTAL | G85: 14 | H85: -3º27'53,918"S-60º27'38,864"W | I85: Ramal do KM 4, próximo a AM-354, Manaquiri-AM, | J85: 200 | K85: 200 | L85: 0 | M85: 0 | N85: 0 | O85: 0 | P85: 8 | Q85: 0 | R85: 9 | S85: 0 | T85: 4 | U85: 0 | V85: 0 | W85: 0 | X85: 0 | Y85: 0 | Z85: 0 | AA85: 0 | AB85: 0 | AC85: 0 | AD85: 0 | AE85: 0 | AF85: 1 | AG85: 0 | AH85: 0 | AI85: 0 | AJ85: 0 | AK85: 0 | AL85: 0 | AM85: 0 | AN85: 0 | AO85: 0 | AP85: 0 | AQ85: 0
A86: 45470.877 | B86: andrewodson@gmail.com | C86: Boca do Acre | D86: 45470 | E86: 0.8125 | F86: INCÊNDIO FLORESTAL | G86: 3 | H86: 8°44'55.1"S 67°23'40.8"W | I86: Rua Jaçanã, 2 S/N, praia do gado | J86: 800 | K86: 300 | P86: 08 | Q86: 04 | AF86: 1 | AL86: FN 01- 1026
A87: 45476.386 | B87: pdfimahumaita@gmail.com | C87: Humaitá | D87: 45470 | E87: 0.68333333 | F87: INCÊNDIO FLORESTAL | G87: 5 | H87: -7,5259416-63,0264368"W | I87: CHÁCARA DO FORTÃO (BAIRRO: SÃO CRISTÓVÃO, ÁREA RURAL) | J87: 600 | K87: 1000 | L87: 04 | M87: 06 | N87: 00 | O87: 00 | P87: 20 | Q87: 00 | R87: 00 | S87: 00 | T87: 00 | U87: 00 | V87: 00 | W87: 00 | X87: 00 | Y87: 00 | Z87: 00 | AA87: 01 | AB87: 01 | AC87: 00 | AD87: 00 | AE87: 00 | AF87: 00 | AG87: 00 | AH87: 00 | AI87: 00 | AJ87: 00 | AK87: 00 | AL87: 00 | AM87: 00 | AN87: 00 | AO87: 00 | AP87: 00 | AQ87: 00
A88: 45528.392 | C88: Manaus | D88: 45471 | F88: INCÊNDIO EM EDIFICAÇÕES
A89: 45528.392 | C89: Manaus | D89: 45473 | F89: INCÊNDIO FLORESTAL | G89: 1
A90: 45528.392 | C90: Itacoatiara | D90: 45473 | F90: INCÊNDIO EM EDIFICAÇÕES
A91: 45528.392 | C91: Manaus | D91: 45473 | F91: INCÊNDIO EM EDIFICAÇÕES
A92: 45528.392 | C92: Manaus | D92: 45473 | F92: INCÊNDIO EM EDIFICAÇÕES
A93: 45528.392 | C93: Manaus | D93: 45473 | F93: INCÊNDIO EM EDIFICAÇÕES
A94: 45528.392 | C94: Manaus | D94: 45473 | F94: INCÊNDIO EM EDIFICAÇÕES
A95: 45528.392 | C95: Manaus | D95: 45473 | F95: INCÊNDIO EM EDIFICAÇÕES
A96: 45528.392 | C96: Manaus | D96: 45471 | F96: INCÊNDIO EM EDIFICAÇÕES
A97: 45528.392 | C97: Manaus | D97: 45472 | F97: INCÊNDIO EM EDIFICAÇÕES
A98: 45528.392 | C98: Manaus | D98: 45472 | F98: INCÊNDIO FLORESTAL | G98: 1
A99: 45528.392 | C99: Tabatinga | D99: 45472 | F99: INCÊNDIO FLORESTAL | G99: 8
A100: 45528.392 | C100: Manaus | D100: 45472 | F100: INCÊNDIO FLORESTAL | G100: 1
...

Sheet Página4
A1: Macrogrupo | B1: Naturezas | C1: Ano | D1: Mês | E1: Data Atendimento | F1: Data Ocorrência | G1: Data Envio Despacho | H1: Data Empenho Equipe | I1: Narrativa | J1: Atividades | K1: Usuario Finalizador
A2: Incêndio em edificação | B2: Incêndio em residência | C2: 2023 | D2: Jan | E2: 44927 | G2: 44927 | H2: 44927 | I2: 1º BI, POSTO ZUMBI, VIATURA ABT-30, SOB O COMANDO DO SARGENTO BM SILVA, CONTROLARAM INCÊNDIO EM INSTÂNCIA DE ALVENARIA SOLICITANTE: FABIANA FERREIRA, CONTATO: 99625-8128. PROPRIETÁRIO: ARNALDO FRANÇA DE MATOS JÚNIOR. RG 279465- 8, CPF 023 744 832 74 BAIRRO: MAUAZINHO, RUA S. FRANCISCO, N 50. INCENDIO EM 2 KITNETES MEDINDO +- 3X5. PREJUÍZO MATERIAL: 01 GELADEIRA, 01 TV , 01 CAMA ,01COLCHÃ, FORRO PVC, REBOCO DA PAREDE, ESPELHO. NO COMBATE E RESCALDO FORAM USADOS 2MIL LITROS DE ÁGUA. NA RUA: SÃO FRANCISCO N56 MAUAZINHO, PRÓXIMO AO CAMPO DO VERMELHÃO SOLICITANTE: FABIANA FERREIRA CONTATO: 99625-8128 | K2: Waldira Marinho Lima Oliveira
A3: Incêndio em edificação | B3: Incêndio em residência | C3: 2023 | D3: Jan | E3: 44927 | G3: 44927 | H3: 44927 | I3: COMANDANTE DE SOCORRO, VIATURA AR-55'1º BI, POSTO CIS GRANDE CISCULAR, VIATURA ABT-25, SOB O COMANDO DO SARGENTO BM ARIULDO, CONTROLARAM INCÊNDIO EM RESIDENCIA DE ALVENARIA, HOUVE QUEIMA DE: 1 CAMA DE SOLTEIRO, FORRO PVC 15M², UM GUARDA ROUPA 4 PORTAS MDF, E DIVERSOS PEÇAS DE ROUPAS, QUEIMA PARCIAL DE DOIS QUARTOS DA CASA, PROPRIETÁRIA SENHORA ALCINDA FERREIRA DA SILVA, NO COMBATE E RESCALDO FORAM USADOS 2,000 LITROS DE ÁGUA. PRINCÍPIO DE INC¿NDIO EM RESIDÊNCIA DE ALVENARIA, NA RUA PADRE CÍCERO N196 CIDADE DE DEUS, PRÓXIMO AO SALMO 91 SOLICITANTE: KELVE CONTATO: 993860957 | K3: Waldira Marinho Lima Oliveira
A4: Incêndio em edificação | B4: Incêndio em residência | C4: 2023 | D4: Jan | E4: 44927 | G4: 44927 | I4: PRINCÍPIO DE INCÊNDIO EM CASA DE ALVENARIA NA RUA IRMÃ ELIZABETH BAYMA 337 NOVA CIDADE SOLICITANTE: WESLEY CONTATO: 99438 -8687 | K4: Waldira Marinho Lima Oliveira
A5: Outras ocorrências | B5: Atendimento pré-hospitalar transporte de paciente | C5: 2023 | D5: Jan | E5: 44927 | G5: 44927 | H5: 44927 | I5: ATENDIMENTO PRÉ HOSPITALAR TRANSPORTE DE PACIENTE PARA O HOSPITAL E PRONTO SOCORRO DR. JOÃO LÚCIO PEREIRA MACHADO AV. COSME E FERREIRA - COROADO PACIENTE: NEILON COSME ALVVES CONTATO: 993639798 GREM POSTO ZUMBI, VIATURA UR-19, PLANO DE OPERAÇÕES Nº 101-CBC/2022 OPERAÇÃO REVEILLON SHOPÍNG FELIPE DAOU, SEGUNDO TURNO REALIZARAM ATENDIMENTO PRÉ HOSPÍTALAR: TIPO DA OCORRÊNCIA:COLISÃO MOTO X MOTO, LOCAL DA OCORRÊNCIA: EM FRENTE AO SHOPPING PHILLIP DAOU, UR-19 GU SV, 1°TEN LEONARDO CORRÊA, 1°TEN MARCOS ALEXANDRE, 3°SGT HELINALDO, SITUAÇÃO DA , CORRÊNCIA. UR 19 ACIONADA PELA PM NA PREVENÇÃO DO RÉVEILLON NO ESTACIONAMENTO DO SHOPPING PHILLIP DAOU PARA ATENDIMENTO DE VÍTIMA DE COLISÃO MOTO X MOTO. AÇÃO DOS BOMBEIROS: À CHEGADA NO LOCAL DA OCORRÊNCIA, VÍTIMA DEAMBULANDO, COM SINAIS DE EMBRIAGUEZ, CONSCIENTE, ORIENTADO, COM TRAUMA CORTO CONTUDO EM FACE, NA REGIÃO DE SUPERCÍLIO DIREITO, NASAL E MAXILAS. REALIZADA IMOBILIZAÇÃO PADRÃO, XABCDE, ACESSO VENOSO PERIFERICO E TRANSPORTE AO HPS JOÃO LÚCIO. AVALIAÇÃO PRIMARIA, XABCDE. IMOBILIZAÇÃO PADRÃO EM PRANCHA LONGA. AVALIAÇÃO SECUNDÁRIA, SSVV, PA: 160X90, SPO2: 98% EM AR AMBIENTE, FC: 115, FR: 19, ENCAMINHAMENTO, ENCAMINHADO AO HPS JOÃO LÚCIO, SETOR DE POLITRAUMA. RECEBIDO PELO MÉDICO JULIANA OZORES CRM AM 5261. DADOS DA VÍTIMA: NOME: NEILON COSME ALVES, 35 ANOS, RG:4471171, ENDEREÇO: RUA MONTE VERDE N95, BAIRRO GILBERTO MESTRINHO, TELEFONE: 99363-9798 | K5: Waldira Marinho Lima Oliveira
A6: Outras ocorrências | B6: Atendimento pré-hospitalar transporte de paciente | C6: 2023 | D6: Jan | E6: 44927 | G6: 44927 | H6: 44927 | I6: ATENDIMENTO PRÉ HOSPITALAR TRANSPORTE DE PACIENTE PARA O HP DR. JOÃO LÚCIO PEREIRA MACHADO - AVENIDA COSME E FERREIRA COROADO PACIENTE: MARCIO DOS SANTOS SOUZA 36 ANOS GREM POSTO ZUMBI, VIATURA UR-19, PLANO DE OPERAÇÕES Nº 101-CBC/2022 OPERAÇÃO REVEILLON SHOPÍNG FELIPE DAOU, SEGUNDO TURNO REALIZARAM ATENDIMENTO PRÉ HOSPÍTALAR: TIPO DA OCORRÊNCIA: QUEDA DA PRÓPRIA ALTURA COM TCE, LOCAL DA OCORRÊNCIA: ESTACIONAMENTO DO SHOPPING PHILLIP DAOU, UR-19 GU SV, 1°TEN LEONARDO CORRÊA, 1°TEN MARCOS ALEXANDRE, _3°SGT HELINALDO, SITUAÇÃO DA OCORRÊNCIA. UR 19 ACIONADA PELA EQUIPE DE APH DA PREVENÇÃO PARA ATENDIMENTO DE VÍTIMA DE QUEDA DA PRÓPRIA ALTURA COM PERDA DE CONSCIÊNCIA. AÇÃO DOS BOMBEIROS: À CHEGADA NO LOCAL DA OCORRÊNCIA, VÍTIMA IMOBILIZADA EM PRANCHA LONGA, COM TRAUMA CORTO CONTUSO EM REGIÃO PARIETAL ESQUERDA E FRONTAL COM SANGRAMENTO ATIVO. VÍTIMA APRESENTANDO CONVULSÕES DURANTE O TRANSPORTE. REFERE RETROVIROSE. REALIZADA AVALIAÇÃO PRIMÁRIA E SECUNDÁRIA, ACESSO VENOSO PERIFERICO E TRANSPORTE AO HPS JOÃO LÚCIO.AVALIAÇÃO PRIMARIA XABCDE. IMOBILIZAÇÃO PADRÃO EM PRANCHA LONGA, OXIGENOTERAPIA COM MÁSCARA COM RESERVATÓRIO 10L/MIN, ACESSO VENOSO PERIFERICO. AVALIAÇÃO SECUNDÁRIA, SSVV, PA: 120X80, SPO2: 98% EM MÁSCARA COM RESERVATÓRIO 10L/MIN,FC: 120, FR: 22,ENCAMINHADO AO HPS JOÃO LÚCIO, SETOR DE POLITRAUMA. RECEBIDO PELA MÉDICA RANNA AM 5170, DADOS DA VÍTIMA: NOME: MARCIO DOS SANTOS SOUZ, 36 ANOS, RG: 2321829-9, ENDEREÇO: RUA CRAVINHO N 450, BAIRRO: JORGE TEIXEIRA 4. ETAPA, TELEFONE: NÃO INFORMADO. | K6: Waldira Marinho Lima Oliveira
A7: Outras ocorrências | B7: Prevenção - outros | C7: 2023 | D7: Jan | E7: 44927 | G7: 44927 | H7: 44927 | I7: SEG DOS POSTOS CBMAM. CB DIRLEY SOUZA 1026 06:00 18:00 12:00 POSTO PONTA NEGRA 233/CIA CG/2024 REFORÇO DE GUARNIÇÃO CB CLEUTON 1037 06:00 18:00 12:00 POSTO PONTA NEGRA 233/CIA CG/2024 REFORÇO DE GUARNIÇÃO CB TOURINHO 1095 06:00 18:00 12:00 POSTO PONTA NEGRA 233/CIA CG/2024 REFORÇO DE GUARNIÇÃO CB WANDER 1255 06:00 18:00 12:00 POSTO PONTA NEGRA 233/CIA CG/2024 REFORÇO DE GUARNIÇÃO SGT RICARDO GOMES 1627 06:00 18:00 12:00 POSTO PONTA NEGRA 075/DG-PGGM/2024 REFORÇO DE GUARNIÇÃO SGT FIGUEIRA 1673 06:00 18:00 12:00 POSTO PONTA NEGRA 075/DG-PGGM/2024 REFORÇO DE GUARNIÇÃO ST ESMERALDO 631 06:00 18:00 12:00 POSTO PONTA NEGRA 964/BBE/2024 REFORÇO DE GUARNIÇÃO CB HENRIQUE LEMOS 1064 06:00 18:00 12:00 POSTO PONTA NEGRA 964/BBE/2024 REFORÇO DE GUARNIÇÃO CB BRUNA 1182 06:00 18:00 12:00 POSTO PONTA NEGRA 964/BBE/2024 REFORÇO DE GUARNIÇÃO CB VICTOR 1036 07:30 19:30 12:00 POSTO RODOVIARIA 965/BBE/2022 REFORÇO DE GUARNIÇÃO ST COSTA E SILVA 378 07:30 19:30 12:00 SCI-AEROPORTO 001/SCI/2024 REFORÇO DE GUARNIÇÃO CB NOGUEIRA 1091 07:30 19:30 12:00 SCI-AEROPORTO 001/SCI/2024 REFORÇO DE GUARNIÇÃO CB RAFAELE 1191 07:30 19:30 12:00 SCI-AEROPORTO 001/SCI/2024 REFORÇO DE GUARNIÇÃO SGT A. SOUSA 1591 08:00 20:00 12:00 POSTO ZUMBI 859/GREM/2024 REFORÇO DE GUARNIÇÃO SGT JEFERSON ARAUJO 1533 13:00 23:00 10:00 TEATRO AMAZ. 108/CBC/2022 POSSE GOVERNADOR SGT ADEILSON 1844 13:00 23:00 10:00 TEATRO AMAZ. 108/CBC/2022 POSSE GOVERNADOR CB PASSOS 1033 14:00 23:00 09:00 TEATRO AMAZ. 126/COBOM/2024 POSSE E JANTAR DO GOVERNADOR CB PIMENTA 1167 13:00 20:00 07:00 TEATRO AMAZ. 967/BBE POSSE E JANTAR DO GOVERNADOR SGT RAINNIER NORONHA 695 14:00 22:00 08:00 TEATRO AMAZ. 407/BIFMA PCI SGT S. ROCHA 771 14:00 22:00 08:00 TEATRO AMAZ. 407/BIFMA PCI TEN MOTA 532 14:00 22:00 08:00 TEATRO AMAZ. 183/DAT POSSE E JANTAR DO GOVERNADOR ST POLARI 528 14:00 22:00 08:00 TEATRO AMAZ. 183/DAT POSSE E JANTAR DO GOVERNADOR ST LUCIO 539 14:00 22:00 08:00 TEATRO AMAZ. 183/DAT POSSE E JANTAR DO GOVERNADOR SGT GOES 594 14:00 22:00 08:00 TEATRO AMAZ. 183/DAT POSSE E JANTAR DO GOVERNADOR SGT F. PAULO 735 14:00 22:00 08:00 TEATRO AMAZ. 183/DAT POSSE E JANTAR DO GOVERNADOR SGT GUTEMBERGUE 741 14:00 22:00 08:00 TEATRO AMAZ. 183/DAT POSSE E JANTAR DO GOVERNADOR CB GETLEN 1025 14:00 22:00 08:00 TEATRO AMAZ. 183/DAT POSSE E JANTAR DO GOVERNADOR TEN ALAIDE NEVES 1328 15:00 22:00 07:00 TEATRO AMAZ. 153/DS POSSE E JANTAR DO GOVERNADOR TEN LOUREIRO 1335 15:00 22:00 07:00 TEATRO AMAZ. 153/DS POSSE E JANTAR DO GOVERNADOR TEN MARINALDO 1407 15:00 22:00 07:00 TEATRO AMAZ. 153/DS POSSE E JANTAR DO GOVERNADOR TEN MARCELO MORAES 1476 15:00 22:00 07:00 TEATRO AMAZ. 153/DS POSSE E JANTAR DO GOVERNADOR TEN ROGERIO XIMENES 1355 15:00 22:00 07:00 TEATRO AMAZ. 153/DS POSSE E JANTAR DO GOVERNADOR TEN ÉRICA 1522 15:00 22:00 07:00 TEATRO AMAZ. 153/DS POSSE E JANTAR DO GOVERNADOR TEN PATENA 1401 15:00 22:00 07:00 TEATRO AMAZ. 153/DS POSSE E JANTAR DO GOVERNADOR TEN DO VALE 1409 15:00 22:00 07:00 TEATRO AMAZ. 153/DS POSSE E JANTAR DO GOVERNADOR TEN LISSA 1370 15:00 22:00 07:00 TEATRO AMAZ. 153/DS POSSE E JANTAR DO GOVERNADOR TEN INDAYAH 1438 15:00 22:00 07:00 TEATRO AMAZ. 153/DS POSSE E JANTAR DO GOVERNADOR TEN LUANNY GOMES 1481 15:00 22:00 07:00 TEATRO AMAZ. 153/DS POSSE E JANTAR DO GOVERNADOR TEN SILVIA CRISTINA 1362 15:00 22:00 07:00 TEATRO AMAZ. 153/DS POSSE E JANTAR DO GOVERNADOR | J7: TEN THALYADE 1430 15:00 22:00 07:00 TEATRO AMAZ. 153/DS POSSE E JANTAR DO GOVERNADOR TEN CARLOS ANTONIO 1436 15:00 22:00 07:00 TEATRO AMAZ. 153/DS POSSE E JANTAR DO GOVERNADOR TEN PEDRO SANTOS 1431 15:00 22:00 07:00 TEATRO AMAZ. 153/DS POSSE E JANTAR DO GOVERNADOR TEN SERGIO CARVALHO 1826 15:00 22:00 07:00 TEATRO AMAZ. 153/DS POSSE E JANTAR DO GOVERNADOR SGT LIDIANE 1638 15:00 22:00 07:00 TEATRO AMAZ. 153/DS POSSE E JANTAR DO GOVERNADOR SGT JOVELINA 1671 15:00 22:00 07:00 TEATRO AMAZ. 153/DS POSSE E JANTAR DO GOVERNADOR CB NEIRES 1798 15:00 22:00 07:00 TEATRO AMAZ. 153/DS POSSE E JANTAR DO GOVERNADOR CB BRUNO QUEZADA 1802 15:00 22:00 07:00 TEATRO AMAZ. 153/DS POSSE E JANTAR DO GOVERNADOR CB LADISLAU 1778 15:00 22:00 07:00 TEATRO AMAZ. 153/DS POSSE E JANTAR DO GOVERNADOR TEN EVELYN 1426 15:00 22:00 07:00 TEATRO AMAZ. 153/DS POSSE E JANTAR DO GOVERNADOR TEN JOQUEBEDE 1394 15:00 22:00 07:00 TEATRO AMAZ. 153/DS POSSE E JANTAR DO GOVERNADOR SGT F. MOTA 1333 15:00 22:00 07:00 TEATRO AMAZ. 153/DS POSSE E JANTAR DO GOVERNADOR SGT SÁVIA 1700 15:00 22:00 07:00 TEATRO AMAZ. 153/DS POSSE E JANTAR DO GOVERNADOR SGT CAMILA DIAS 1595 15:00 22:00 07:00 TEATRO AMAZ. 153/DS POSSE E JANTAR DO GOVERNADOR SGT SIMPLICIO 1691 15:00 22:00 07:00 TEATRO AMAZ. 153/DS POSSE E JANTAR DO GOVERNADOR ST ARTUR 635 14:00 22:00 08:00 TEATRO AMAZ. 238/CIACG POSSE E JANTAR DO GOVERNADOR CB DORIAN 1109 14:00 22:00 08:00 TEATRO AMAZ. 962/BBE POSSE E JANTAR DO GOVERNADOR CB ELIELSON 1159 18:00 06:00 12:00 QCG 235/CIA CG/2022 SENTINELA ARMADA SERVIÇO DO DIA 01.01.2024 / 1º TURNO CMT DE SOCORRO: 2º TEN BM VALÉRIO CONTROLADOR COBOM: 1º TEN BM RICARDO ------------------------------------------------------------------------------------------------------------------------------------------------------------- CB RONALDO 1153 19:30 07:30 12:00 PB-RODOVIÁRIA 965/BBE/2022 REFORÇO DE GUARNIÇÃO ST VIEIRA PAIVA 375 19:30 07:30 12:00 SCI 002/SCI/2024 REFORÇO DE GUARNIÇÃO TEN MATOS 570 19:30 07:30 12:00 SCI 002/SCI/2024 REFORÇO DE GUARNIÇÃO CB MOREIRA JÚNIOR 1256 19:30 07:30 12:00 SCI 002/SCI/2024 REFORÇO DE GUARNIÇÃO CB LÉCIO 1093 20:00 08:00 12:00 DAT 181/DAT/2022 PERMANENCIA SGT ROBERTO PIMENTEL 1568 20:00 08:00 12:00 PONTA NEGRA 860/GREM/2022 REFORÇO DE GUARNIÇÃO SERVIÇO DO DIA 01.01.2024 / 2º TURNO CMT DE SOCORRO: 2º TEN BM VALÉRIO CONTROLADOR COBOM: 1º TEN BM R. LIRA | K7: Rozivaldo de Souza Lira
A8: Outras ocorrências | B8: Encontro de cadáver | C8: 2023 | D8: Jan | E8: 44927 | G8: 44927 | H8: 44927 | I8: Solicitante informa que acabaram de encontrar um cadáver esquartejado no local, pede-se apoio de vtr. | J8: A GUARNIÇÃO DA VIATURA 7307 DA 3º CICOM, AO COMANDO DO SARGENTO BRAGA, INFORMOU QUE FOI ENCONTRADO EM VIA PUBLICA UM CADARVER DO SEXO MASCULINO ESQUARTEJADO, SEGUNDO OS POLICIAIS, PRIMEIRAMENTE FOI ENCONTRADO SOMENTE O TRONCO DA VÍTIMA, MAIS ADIANTE TEM UM BUEIRO E OS POLICIAIS AVISTARAM UMA GRANDE MOVIMENTAÇÃO DE MOSCAS, AO AVERIGUAR, FORAM ENCONTRADOS AS DUAS PERNAS, OS DOIS BRAÇOS E A CABEÇA. FOI SOLICITADO APOIO DE UMA EQUIPE DO BOMBEIRO.NINGUEM CONHECE A VITIMA. VITIMA - SEXO MASCULINO APROXIMADAMENTE 25 ANOS VIATURAS DO ESTADO EMPENHADAS NESTA OCORRENCIA: 3º CICOM 47.0 VTR 7307 SGT BRAGA 14400 SGT JEMERSON 19167 SGT RUI DA SILVA 17933 HOMICIDO VTR 311 DELEGADO - RAFAEL AMANGUE INVESTIGADORES - ADRIANA ANDREI JERONIMO BOMBEIRO APT 31 COMANDANTE - CABO ROBSON CABO PIMENTEL CABO ALAN OLIVEIRA VTR 2008 PERICIA DA CRIMINALISTICA ALACIDE MOREIRA RICARDO CAMPOS IML 667 FAROL FRANCISCO ALVES AUXILIAR NECROPCIA RIBAMAR | K8: LUIZ RICARDO DE OLIVEIRA ALBUQUERQUE
A9: Outras ocorrências | B9: Prevenção em festas / eventos diversos | C9: 2023 | D9: Jan | E9: 44927 | G9: 44927 | H9: 44927 | I9: POSTO CENTRAL, VIATURA, ABT-31, UR-23, ABP-01, SOB O COMANDO DO CAPITÃO EDU COSTA, DESLOCARAM PARA CUMPRIR O.S 108/CBC/2022; EVENTO: POSSE DO GOVERNADOR; LOCAL: TEATRO AMAZONAS; HORÁRIO: 15:00 PRONTO. PLANO DE OPERAÇÕES Nº 108/CBC/2022; EVENTO: POSSE DO GOVERNADOR; LOCAL: TEATRO AMAZONAS; VIATURAS: ABT-29, ABT-31, UR-23, ABP-01 À COMANDO DO CAP BM EDU. HORÁRIO: 15:00 PRONTO. TÉRMINO DE PREVENÇÃO NO TEATRO AMAZONAS, AS VIATURAS DESLOCAM PARA O SEGUNDO PONTO DE PREVENÇÃO, NO CENTRO DE CONVENÇÕES VASCO VASQUES. TÉRMINO DE PREVENÇÃO, AS VIATURAS RETREM AOS SEUS POSTOS DE ORIGEM. SERVIÇO DO DIA 01.01.2024 / 2º TURNO CMT DE SOCORRO: 2º TEN BM VALÉRIO CONTROLADOR COBOM: 1º TEN BM R. LIRA | K9: Rozivaldo de Souza Lira
A10: Outras ocorrências | B10: Afogamento | C10: 2023 | D10: Jan | E10: 44927 | G10: 44927 | H10: 44927 | I10: AFOGAMENTO NA PRAIA DA PONTA NEGRA. EQUIPE DE SALVA VIDAS, GREM, UR-23, POSTO PONTA NEGRA, VITIMA APROXIMADAMENTE 30ANOS. SEM IDENTIFICAÇÃO E SEM DOCUMENTO. UM RAPAZ DISSE QUE CONHECIA ELE. MAS NAO SOUBE INFORMAR, ATUAÇÃO DOS BOMBEIROS, RETIRADA DO MEIO LÍQUIDO, PROCEDIMENTO DE REANIMAÇÃO CARDIO PULMONAR SEM EXITO, O CORPO FOI ENTREGUE A POLICIA CIVIL DELEGADO RAFAEL ALEMAND E INVESTIGADOR LUKEDISON, DHS VTR 311, IML VTR 667, RIBAMAR CARVALHO E FRANCISCO ALVES. | K10: LUIZ RICARDO DE OLIVEIRA ALBUQUERQUE
A11: Outras ocorrências | B11: Corte de algema / anel / outros | C11: 2023 | D11: Jan | E11: 44927 | G11: 44927 | H11: 44927 | I11: Ocorrencia de retirada de objeto circular de ferro do dedo anelar direito da mao de Ana Karen de Souza Santiago, 21 anos, RG 3227679-6. Tel. 99536-4404. Residente a rua Sant Petemberg N.07 bairro Nova cidade. A mesma estava acompanhada de seu esposo o senhor Morients Pereira Vieira, 22 anos, tel. 99349-7668. BBE, POSTO CENTRAL, VIATUAR ABT-29, RERALIZARAM RETIRADA DE OBJETO CIRCULAR DE FERRO DO DEDO ANELAR DIREITO DA MÃO DE: ANA KAREN DE SOUZA SANTIAGO, 21 ANOS, RG 3227679-6. TEL. 99536-4404. RESIDENTE A RUA SANT PETEMBERG N.07 BAIRRO NOVA CIDADE. A MESMA ESTAVA ACOMPANHADA DE SEU ESPOSO O SENHOR MORIENTS PEREIRA VIEIRA, 22 ANOS, TEL. 99349-7668. S.A. | K11: LUIZ RICARDO DE OLIVEIRA ALBUQUERQUE
A12: Outras ocorrências | B12: Encontro de cadáver | C12: 2023 | D12: Jan | E12: 44927 | G12: 44927 | I12: BBE, POSTO RODOVIÁRIA, VIATURA ABT-29, DESLOCOU PARA ENCONTRO DE CADÁVER EM APOIO A POLICIA MILITAR, EM ANDAMENTO... BBE; PB RODOVIÁRIA; VTR ABT-29 À COMANDO DO SGT BM VITAL. DESLOCA AO LOCAL SOLICITADO, ATENDE ROCORRÊNCIA DE RESGATE DE CADÁVER. LOCALIZAÇÃO E REMOÇÃO DE CADÁVER. SOLICITAÇÃO POR PARTE DA GUARNIÇÃO DA PMAM DO CIPCAES. LOCAL, ÁREA DE MATA FECHADA. AÇÃO DA GUARNIÇÃO CBMAM: RETIRADA DE UM CORPO EM ESTADO AVANÇADO DE DECONPOSIÇÃO, EM UMA COVA DE APROXIMADAMENTE 1m À 1.10m DE PROFUNDIDADE, UTILIZAÇÃO DE MATERIAL DE SAPA. NO LOCAL ACOMPANHANDO TODO SERVIÇO, O DELEGADO RAFAEL ALLEMAND, DA DELEGACIA DE HOMICIDIOS, INVESTIGADORES: LUKEDSON E ANDREI, NA VTR 311. EQUIPE DO IML VTR 741. FRANCISCO (MOTORISTA) SENHORES FRANCISCO E RIBAMAR AUXILIAR. PERÍCIA VTR 2005 PERITO: ALTAIDE E MOTORISTA RICARDO CAMPOS. EQUIPE PMAM: ROCAM VTR 9225 A COMANDO DO SGT PM W. BEZERRA, FAROL SD ROMULO, SD E. BRASIL AUXILIAR. EQUIPE DA CIPCAES VTR 9226, FAROL CB RICARDO MELO CH. SGT EMERSON E AUX. CB JAMISON, CADELA FIONA. CORPO ENTREGUE AOS CUIDADOS DO IML. A VTR ABT-29 RETRAIU AO PB DE ORIGEM. SERVIÇO DO DIA 01.01.2024 / 2º TURNO CMT DE SOCORRO: 2º TEN BM VALÉRIO CONTROLADOR COBOM: 1º TEN BM R. LIRA | J12: VTR 9226/CANIL AVERIGUAÇÃO DE ENCONTRO DE CADÁVER | K12: Rozivaldo de Souza Lira
A13: Outras ocorrências | B13: Desaparecimento de pessoa | C13: 2023 | D13: Jan | E13: 44927 | G13: 44927 | H13: 44927 | I13: BBE, PELOTÃO PONTA NEGRA, Walcinara da Silva barrocas tel.993992892 Filho: kaik Ruan da Silva de Souza 5 anos Ende: rua bacuri 38 Tarumã LOCAL DO DESAPARECIMENTO: Praia da ponta Negra BBE, PELOTÃO PONTA NEGRA, ENCONTRARAM A CRIANÇA: WALCINARA DA SILVA BARROCAS, 5 ANOS, FILHO: KAIK RUAN DA SILVA DE SOUZA, TEL.993992892, ENDEREÇO: RUA BACURI, Nº 38, BAIRRO TARUMÃ, A CRIANÇA ESTAVA CHORANDO ANDANDO SOZINHA NA PRAIA DA PONTA NEGRA, APÓS ALGUMA TEMPO A MÃE APÁRECEU ENTÃO A EQUIPE ENTREGOU A CRIANÇA NO POSTO DOS BOMBEIROS. | K13: LUIZ RICARDO DE OLIVEIRA ALBUQUERQUE
A14: Outras ocorrências | B14: Atendimento ao banhista | C14: 2023 | D14: Jan | E14: 44927 | G14: 44927 | H14: 44927 | I14: PACIENTE: Betsabata Aguilera del Valle. 46 anos CELULAR: 92 98631 6012 ENDEREÇO: Lírio do vale - beco das flores ATENDIMENTO PELA GU DE APH, FOI AVALIADA PELO TEN BM REATEGUI APRESENTOU MAL SÚBITO, TAQUICARDIA. ENCAMINHADA AO SPA JOVENTINA DIAS PELA UR 19 | K14: LUIZ RICARDO DE OLIVEIRA ALBUQUERQUE
A15: Outras ocorrências | B15: Atendimento pré-hospitalar transporte de paciente | C15: 2023 | D15: Jan | E15: 44927 | G15: 44927 | H15: 44927 | I15: PACIENTE: Betsabata Aguilera del Valle. 46 anos CELULAR: 92 98631 6012 ENDEREÇO: Lírio do vale - beco das flores ATENDIMENTO PELA GU DE APH, FOI AVALIADA PELO TEN BM REATEGUI APRESENTOU MAL SÚBITO, TAQUICARDIA. ENCAMINHADA AO SPA JOVENTINA DIAS PELA UR 19 | K15: LUIZ RICARDO DE OLIVEIRA ALBUQUERQUE
A16: Outras ocorrências | B16: Corte de algema / anel / outros | C16: 2023 | D16: Jan | E16: 44927 | G16: 44927 | I16: CORTE DE ANEL EM UNIDADE HOSPITALAR HPS JOÃO LUCIO PACIENTE: CLAUDIO RERIVELTON LIRA - 29 a ANEL TIPO ALIANÇA EM MÃO ESQUERDA CLÍNICA POLITRAUMA HPS JOÃO LÚCIO ENFº ADONILSON DA ENFª POLITRAUMA - 3249 9407 1º BI; PB ZUMBI; VTR ABT-30 À COMANDO DO SGT BM GENTIL. DESLOCA ATÉ AO HPS JOÃO LÚCIO, ATENDER OCORRÊNCIA DE CORTE DE ANEL, SETOR DE POLITRALMA. SOLICITANTE: ENFERMEIRO ADONILSON 3249-9407. PACIENTE: CLÁUDIO RERIVELTON LIRA. 29 ANOS. ANEL TIPO ALIANÇA, DEDO ANELAR ESQUERDO. SERVIÇO DO DIA 01.01.2024 / 2º TURNO CMT DE SOCORRO: 2º TEN BM VALÉRIO CONTROLADOR COBOM: 1º TEN BM R. LIRA | K16: Rozivaldo de Souza Lira
A17: Outras ocorrências | B17: Captura / resgate de animais | C17: 2023 | D17: Jan | E17: 44927 | G17: 44927 | I17: RUA PADRE RAMIM, N 8, ZUMBI 2 PROX A ESCOLA MUNICIPAL ANITA GARIBALDI 99398-3070 - HELENA COSTA CACHORRO PRESO ENTRE DUAS PAREDES. 1º BI; PB ZUMBI; VTR ABT-30 À COMANDO DO SGT BM GENTIL. DESLOCA ATÉ AO HPS JOÃO LÚCIO, ATENDER OCORRÊNCIA DE RESDGATE DE ANIMAL TIPO CACHORRO, O MESMO ESTÁ PRESO ENTRE DUAS PAREDES, CACHORRO TIPO VIRA-LATA. SOLICITANTE: PROPRIETÁRIA DA 1ª CASA: SRA. HELENA ZACARIAS DA COSTA. 64 ANOS. CPF: 416.188.232-72 TEL: 99999-7739. PROPRIETÁRIA DA 2ª CASA: SRA. OTARCILA ALMEIDA DE FREITAS. 80 ANOS. CPF: 052.644.642-00 CEL: 99466-9991. AÇÃO DO BOMBEIRO: NÃO FOI POSSÍVEL A REMOÇÃO DO ANIMAL MEDIANTE CAMBÃO, A SRA OTARCILA AUTORIZOU A GUARNIÇÃO QUEBRAR O MURO DA DISPENSA DE SUA CASA, FOI QUEBRADO CERCA DE 50cm LARGURA E 50cm DE ALTURA, DO MURO DA MESMA. O ANIMAL FOI RESGATADO COM VIDA E ENTREGUE À PROPRIETÁRIA DO MESMO. LOCAL EM SEGURANÇA, A VTR ABT-30 RETRAI AO PB DE ORIGEM. SERVIÇO DO DIA 01.01.2024 / 2º TURNO CMT DE SOCORRO: 2º TEN BM VALÉRIO CONTROLADOR COBOM: 1º TEN BM R. LIRA | K17: Rozivaldo de Souza Lira
A18: Outras ocorrências | B18: Corte de algema / anel / outros | C18: 2023 | D18: Jan | E18: 44927 | G18: 44927 | I18: CORTE DE ANEL NO CIS GRANDE CIRCULAR. 1º BI; PB CIS GC; A GUARNIÇÃO DA VTR ABT-25 REALIZOU CORTE DE ANEL NO DEDO ANELAR ESQUERDO. MATERIAL: ROMMANEL. SOLICITANTE: MAYARA DE SOUZA SILVA. 24 ANOS. FONE: 99411-4819 RG: 3154583-1 ENDEREÇO: RUA JACARANDÁ. BAIRRO: JORGE TEIXEIRA SERVIÇO DO DIA 01.01.2024 / 2º TURNO CMT DE SOCORRO: 2º TEN BM VALÉRIO CONTROLADOR COBOM: 1º TEN BM R. LIRA | K18: Rozivaldo de Souza Lira
A19: Outras ocorrências | B19: Prevenção - outros | C19: 2023 | D19: Jan | E19: 44928 | G19: 44928 | H19: 44929 | I19: SEG NOS POSTOS DO CBMAM SGT TIAGO RAMIRES 1829 08:00 20:00 12:00 QCG 159/CSM/2022 GARAGISTA SGT SILVA 776 07:30 19:30 12:00 CIS G. CIRCULAR 002/1°BI/2024 REFORÇO DE GU CB RODRIGO VIEIRA 1152 07:00 17:00 10:00 QGC 001/CBC/2024 CORTE DE ÁRVORE ST ARILSON 572 07:30 19:30 12:00 SCI-EG 003/SCI-EG/2024 REFORÇO DE EQUIPAGEM ST HELDER 738 07:30 19:30 12:00 SCI-EG 003/SCI-EG/2024 REFORÇO DE EQUIPAGEM CB DIEGO FALCÃO 1266 07:30 19:30 12:00 SCI-EG 003/SCI-EG/2024 REFORÇO DE EQUIPAGEM SGT LAURA 766 08:00 20:00 12:00 PB RODOVIÁRIA 960/BBE/2022 REFORÇO DE GU ST PABLO 692 08:00 20:00 12:00 BIFMA 001/BIFMA/2024 REFORÇO DE GU TEN EDITH 1441 23:00 04:00 05:00 SHOPPING PHLIPPE DAOU 151/DS/2022 OPERÇÃO REVEILLON SGT LUCIANE MOTA 1544 23:00 04:00 05:00 SHOPPING PHLIPPE DAOU 151/DS/2022 OPERÇÃO REVEILLON SGT SARA DIANE 1561 23:00 04:00 05:00 SHOPPING PHLIPPE DAOU 151/DS/2022 OPERÇÃO REVEILLON SGT SARA 1563 23:00 04:00 05:00 SHOPPING PHLIPPE DAOU 151/DS/2022 OPERÇÃO REVEILLON SGT JUCILEIDA 1705 23:00 04:00 05:00 SHOPPING PHLIPPE DAOU 151/DS/2022 OPERÇÃO REVEILLON SGT IBERNON 1607 23:00 04:00 05:00 SHOPPING PHLIPPE DAOU 151/DS/2022 OPERÇÃO REVEILLON SGT SILVANDO 1679 23:00 04:00 05:00 SHOPPING PHLIPPE DAOU 151/DS/2022 OPERÇÃO REVEILLON SGT IRLENE 1594 23:00 04:00 05:00 SHOPPING PHLIPPE DAOU 151/DS/2022 OPERÇÃO REVEILLON SGT EVANGELISTA 699 14:00 19:00 05:00 TEATRO AMAZONAS 409/BIFMA/2022 SOLENIDADE DE POSSE DO TJAM CB MARCUS 1017 14:00 19:00 05:00 TEATRO AMAZONAS 409/BIFMA/2022 SOLENIDADE DE POSSE DO TJAM CB LUCIANA 1774 13:00 18:00 05:00 QCG 001/AJAI/2024 ATENDER PRAZOS JUDICIAIS SGT HELOISA PAIVA 1717 15:00 23:00 08:00 TEATRO AMAZONAS 125/COBOM/2022 SOLENIDADE DE POSSE DO TJAM ST AURÉLIO 618 14:00 23:00 09:00 TEATRO AMAZONAS 004/1°BI/2024 SOLENIDADE DE POSSE DO TJAM SGT ARILDO 760 14:00 23:00 09:00 TEATRO AMAZONAS 004/1°BI/2024 SOLENIDADE DE POSSE DO TJAM CB PETILLO 1130 14:00 23:00 09:00 TEATRO AMAZONAS 004/1°BI/2024 VOLANTE ATP- 07 CB BARBOSA 1097 15:00 23:00 08:00 TEATRO AMAZONAS 956/BBE/2022 SOLENIDADE DE POSSE DO TJAM CB SARMENTO 1105 15:00 23:00 08:00 TEATRO AMAZONAS 956/BBE/2022 SOLENIDADE DE POSSE DO TJAM CB MARCUS FREIRE 1189 15:00 23:00 08:00 TEATRO AMAZONAS 239/CIACCG/2022 SOLENIDADE DE POSSE DO TJAM SGT JEFERSON SOUZA 1533 18:00 06:00 12:00 QCG 235/CIACG/23 ATALAIA CB S. RODRIGUES 1003 20:00 08:00 12:00 PB RODOVIÁRIA 960/BBE/22 REFORÇO DE GU SGT SILLAS JUNIOR 715 20:00 08:00 12:00 QCG 159/CSM/22 GARAGISTA CB GETLYN 1025 20:00 08:00 12:00 DAT 181/DAT/22 PERMANÊNCIA CB RAFAEL LIMA 1040 19:30 07:30 12:00 CIS G. CIRCULAR 003/1°BI/23 REFORÇO DE GU CB ASSUNÇÃO 1147 19:30 07:30 12:00 SCI - EG 04/SCI-EG/23 REFORÇO DE GU CB GERÔNIMO 1202 19:30 07:30 12:00 SCI - EG 04/SCI-EG/23 REFORÇO DE GU CB GENIVALDO 1193 19:30 07:30 12:00 SCI - EG 04/SCI-EG/23 REFORÇO DE GU SERVIÇO DO DIA 02.01.2024 / 1º TURNO CMT DE SOCORRO: 2º TEN BM EDUARDO ARAÚJO CONTROLADOR COBOM: 1º TEN BM R. LIRA | K19: LUIZ RICARDO DE OLIVEIRA ALBUQUERQUE
A20: Incêndio em edificação | B20: Incêndio em apartamento | C20: 2023 | D20: Jan | E20: 44928 | G20: 44928 | I20: PRINCIPIO DE INCENDIO EM APARTAMENTO. BBE; PB CENTRAL; VTR ABT-31 À COMANDO DO CB BM ROBISON. DESLOCA AO LOCAL SOLICITADO, ATNDER OCORRÊNCIA DE PRINCÍPIO DE INCÊNDIO EM APARTAMENTO. TRATA-SE DE UM CURTO ELÉTRICO NA GELADEIRA, QUE PROVOCOU UM FOCO DE INCÊNDIO CONTIDO PELOS PRÓPRIOS MORADORES, QUE À POSERAM NA ÁREA EXTERNA DA CASA. SOLICITANTE: RONELIO CARDOSO DE LIMA. 40 ANOS. TEL: 92 99172-7579 RG: 1519219-9 SSP/AM CPF: 524.562.632-91 NARRATIVA: PRINCÍPIO DE INCÊNDIO NA COZINHA INICIADO NA PARTE DE TRÁS DA GELADEIRA. O SOLICITANTE FEZ A RETIRADA DA GELADEIRA PARA ÁREA EXTERNA E EXTINGUIU AS CHAMAS POR RESFRIAMENTO. LOCAL EM SEGURANÇA, A VTR ABT-31 RETRAI AO PB DE ORIGEM. SERVIÇO DO DIA 02.01.2024 / 1º TURNO CMT DE SOCORRO: 2º TEN BM EDUARDO ARAÚJO CONTROLADOR COBOM: 1º TEN BM R. LIRA | K20: Rozivaldo de Souza Lira
A21: Outras ocorrências | B21: Corte de árvore | C21: 2023 | D21: Jan | E21: 44928 | G21: 44928 | I21: CORTE DE ÁRVORE DE MÉDIO PORTE TIPO PITOMBEIRA, RUA SANTA ISABEL, 446 - COMPENSA. CBC; VTR AR-42 COMPOSTA PELOS MILITARES, CB BM J. NUNES, CB BM IRINILDO E CB BM RODRIGO VIEIRA. DESOCA PARA CUMPRIR MISSÃO DE CORTE DE ÁRVORE TIPO PITIMBEIRA. SOLICITANTE: ITAMAR. TEL: 99134-6750. CORTE DA ÁRVORE PARCIAL, NÃO FINALIZADA POR TER CHOVIDO MUITO NA ÁREA, FICANDO APENAS O TRONCO, A VTR AR-42 RETRA AO PB DE ORIGEM. SERVIÇO DO DIA 02.01.2024 / 1º TURNO CMT DE SOCORRO: 2º TEN BM EDUARDO ARAÚJO CONTROLADOR COBOM: 1º TEN BM R. LIRA | K21: Rozivaldo de Souza Lira
A22: Outras ocorrências | B22: Vistoria em árvore - situação de risco | C22: 2023 | D22: Jan | E22: 44928 | G22: 44928 | I22: SENHORA VERICA / LOGISTICA, SOLICITOU APOIO PARA UMA ARVORE QUE ESTA EM RISCO DE TOMBAMENTO TOTAL, PARTE DA ARVORE CAIU ENTRE OS PREDIOS DO HEMOAM E ANTIGO HOSPICIO EDUARDO RIBEIRO. BBE; PB RODOVIÁRIA; VTR ABT-29 À COMANDO DA SGT BM LAURA. DESLOCA ATÉ O HEMOAM, ATENDER OCORRÊNCIA DE VISTORIA/CORTE DE ÁRVORE. TRATA-SE DE DOIS GALHOS DE GRANDE PORTE QUE CAÍRAM E ESTÃO OBSTRUINDO A PASSAGEM DE VEÍCULOS. AÇÃO DA GUARNIÇÃO: RETIRADO OS GALHOS DO MEIO DA VIA, SEM ALTERAÇÃO. A VTR ABT-29 RETRAI AO PB DE ORIGEM. SERVIÇO DO DIA 02.01.2024 / 1º TURNO CMT DE SOCORRO: 2º TEN BM EDUARDO ARAÚJO CONTROLADOR COBOM: 1º TEN BM R. LIRA | K22: Rozivaldo de Souza Lira
A23: Outras ocorrências | B23: Prevenção em festas / eventos diversos | C23: 2023 | D23: Jan | E23: 44928 | G23: 44928 | I23: ORDEM DE SERVIÇO 294/CBC/2022 EVENTO: POSSE DA NOVA DIRETORIA DO TRIBUNAL DE JUSTIÇA DO AMAZONAS. MISSÃO: REALIZAR PREVENÇÃO EM EVENTOS, ATENDIMENTO DE URG¿NCIA E EMERGÊNCIAS, DATA; 02/01/2024 HORA: 13:30 ÀS 20:00 LOCAL: TEATRO AMAZONAS / PALÁCIO RIO NEGRO RECURSOS EMPREGADOS: 01 SUPERIOR DE DIA, 01 UR, 02 BM DO BBE, 02 BM DO 1° BI. COMANDANTE DE SOCORRO, VIATURA AR-55, GREM; PB JAGUAR; VTR UR-19 DESLOCA AO TEATRO AMAZONAS, CUMPRIR PLANO DE OPERAÇÃO Nº 294-CBC/2022. EVENTO: POSSE DA NOVA DIRETORIA DO TRIBUNAL DE JUSTIÇA DO AMAZONAS, TJAM. MISSÃO: REALIZAR PREVENÇÃO EM EVENTO, ATENDIMENTO DE URGÊNCIA/EMERGÊNCIA. LOGO APÓS CUMPRIR SEGUNDO PONTO DE PREVENÇÃO, NO PALÁCIO RIO NEGRO, JANTAR DAS AUTORIDADES. EM SEGUIDA DESLOCARAM PARA O CENTRO DE CONVENÇÕES ONDE PERMANECERAM ATÉ O TÉRMINO DO EVENTO. | K23: LUIZ RICARDO DE OLIVEIRA ALBUQUERQUE
A24: Outras ocorrências | B24: Corte de algema / anel / outros | C24: 2023 | D24: Jan | E24: 44928 | G24: 44928 | I24: CORTE DE ANEL REGISTRADO NO BBE. BBE; PB RODOVIÁRIA; A GUARNIÇÃO DA VTR ABT-29 ATENDEU UMA OCORRÊNCIA DE CORTE DE ANEL. DEDO ANELAR ESQUERDO. NOME: JÚLIA EVELIN DE OLIVEIRA GOMES. 13 ANOS. RG: 3782635-2 MÃE: JOSIANE SILVA DE OLIVEIRA. ENDEREÇO. RUA INDEPENDÊNCIA N° 34 BAIRRO REDENÇÃO. SERVIÇO DO DIA 02.01.2024 / 1º TURNO CMT DE SOCORRO: 2º TEN BM EDUARDO ARAÚJO CONTROLADOR COBOM: 1º TEN BM R. LIRA | K24: Rozivaldo de Souza Lira
A25: Outras ocorrências | B25: Incêndio em veículo | C25: 2023 | D25: Jan | E25: 44929 | G25: 44929 | H25: 44929 | I25: FOGO EM VEÍCULO - CORSA ANTIGO RUA GUARACIABA, 141 - COLONIA TERRA NOVA PRÓXIMO AO MERCADINHO BEATRIZ BRUNA - 98405 5001 BIFMA, PARQUE SUMAUMA, VIATURA ABT-32, SOB O COMANDO DO ST BM PABLO DESLOCARAM PARA INCENCIO EM VEÍCULO MODELO CELTA DE COR PRATA, PLACA JWY-0112, PROPRIETÁRIO: MARCELINO DA SILVA, 49 ANOS, RG 47397071287, CONTATO 99441-2338, A EQUIPE INFORMOU QUE O FOGO DEU INÍCIO PELA BATERIA, A VIZINHANÇA CONSEGUIU CONTROLAR AS CHAMAS, A EQUIPE REALIZOU O ISOLAMENTO DA BATERIA DO VEÍCULO, HOUVE DANOS PARCIAL NO COMPARTIMENTO DO MOTOR SOMENTE. | K25: LUIZ RICARDO DE OLIVEIRA ALBUQUERQUE
A26: Outras ocorrências | B26: Prevenção - outros | C26: 2023 | D26: Jan | E26: 44929 | G26: 44929 | H26: 44929 | I26: SEG NOS POSTOS DO CBMAM NA DATA DE 03 DE JAN DE 2024 1 CB SARNEY 1223 08:30 20:00 11:30 1° B.I 005/1º BI/2024 CONDUTOR AR - 55 2 CB DIVAL 1008 08:00 20:00 12:00 PB CENTRAL 001/BBE/2024 REFORÇO DE GUARNIÇÃO 3 ST COMAPA 609 08:00 17:00 09:00 QCG 002/CBC CORTE DE ÁRVORE NA BASE BIBV 4 CB CARLOS LOPES 1116 08:00 17:00 09:00 QCG 002/CBC CORTE DE ÁRVORE NA BASE BIBV 5 CB RODRIGO VIEIRA 1152 08:00 17:00 09:00 QCG 002/CBC CORTE DE ÁRVORE NA BASE BIBV 6 SGT NOBRE 1620 07:30 19:30 12:00 SCI 005/SCI/2024 REFORÇO DE APH 7 SGT ELBISON 725 07:30 19:30 12:00 SCI 006/SCI/2024 REFORÇO DE EQUIPAGEM 8 CB CLEBER 1190 07:30 19:30 12:00 SCI 006/SCI/2024 REFORÇO DE EQUIPAGEM 9 CB PAULO RICARDO 1232 07:30 19:30 12:00 SCI 006/SCI/2024 REFORÇO DE EQUIPAGEM 10 CB ANTÔNIO 1240 07:30 19:30 12:00 SCI 006/SCI/2024 REFORÇO DE EQUIPAGEM 11 CB MARCUS 1017 08:00 14:00 06:00 BIFMA 002/BIFMA/2024 APOIO LOGÍSTICO 12 CB LUCIANA 1774 13:00 18:00 05:00 QCG 002/AJAI/2024 PRAZOS PROCESSUAIS 13 TEN WASHINGTON BORGES 1388 08:00 13:00 05:00 PB PONTA NEGRA 003/GRE,/2024 INVENTÁRIO PATRIMONIAL 14 SGT KLEWTON MANOEL 1858 08:00 13:00 05:00 PB PONTA NEGRA 003/GRE,/2024 INVENTÁRIO PATRIMONIAL COMANDO DE SOCORRO: TEN BM DENILSON COORDENADOR: TEN BM GUERREIRO -------------------------------------------------------------------------------------------------------------------------------------------------------------------- CB MORAIS 1139 20:00 08:00 12:00 PB FLUVIAL 001/BBE/2024 PERMANÊNCIA CB MARCUS FREIRE 1189 18:00 06:00 12:00 QCG 235/CIACG/2022 SENTINELA ARMADA CB PABLO JEAN 1155 20:00 08:00 12:00 DAT 182/DAT/2022 PERMANÊNCIA ST ARILSON 572 19:30 07:30 12:00 SCI-EG 007/SCI-EG/2024 REFORÇO DE EQUIPAGEM ST VIVALDO 619 19:30 07:30 12:00 SCI-EG 007/SCI-EG/2024 REFORÇO DE EQUIPAGEM ST HELDER 738 19:30 07:30 12:00 SCI-EG 007/SCI-EG/2024 REFORÇO DE EQUIPAGEM CB LICATA 1103 19:30 07:30 12:00 SCI-EG 007/SCI-EG/2024 REFORÇO DE EQUIPAGEM SGT SARA DIANE 1561 19:30 07:30 12:00 SCI-EG 005/SCI-EG/2024 REFORÇO APH CB LUCIANO 1206 20:00 08:00 12:00 QCG 008/1°BI/2024 CONDUTOR VTR AR-55 SERVIÇO DO DIA 03.01.2024 / 2º TURNO CMT DE SOCORRO: 2º TEN BM DENILSON CONTROLADOR COBOM: 1º TEN BM R. LIRA | K26: Rozivaldo de Souza Lira
A27: Outras ocorrências | B27: Prevenção - outros | C27: 2023 | D27: Jan | E27: 44929 | G27: 44929 | I27: GREM, POSTO ZUMBI, UR-19. AO COMANDO DO TEN BM SANDRO CAMARGO, CUMPRIRAM A ORDEM DE SERVIÇO Nº 001/GREM/CBC/2024. EVENTO: TFM NO QCG, DETERMINAÇÃO: CMT DO GREM, MISSÃO: PREVENÇÃO E ATENDIMENTO EM URGÊNCIA/EMERGÊNCIA. OCORRÊNCIA DE PREVENÇÃO FINALIZADA S/A. COMANDO DE SOCORRO: TEN BM DENILSON COORDENADOR: TEN BM GUERREIRO | K27: Ezequias Guerreiro Marques
A28: Outras ocorrências | B28: Prevenção em manifestação popular | C28: 2023 | D28: Jan | E28: 44929 | G28: 44929 | I28: ORDEM DE SERVIÇO N° 002/GREM/2024. PREVENÇÃO E ATENDIMENTO DE URGÊNCIA/EMERGÊNCIA EM FRENTE AO COMANDO MILITAR DA AMAZÔNIA. IDEM DA OC; 2022112412334829548 | K28: Ezequias Guerreiro Marques
A29: Outras ocorrências | B29: Corte de árvore | C29: 2023 | D29: Jan | E29: 44929 | G29: 44929 | H29: 44929 | I29: CBC, AR-42. AO COMANDO DO ST BM COMAPA, DESLOCARAM-SE AO LOCAL (BIBV, 1º BIS) PARA REALIZAR CORTE DE ÁRVORE, RESPONSÁVEL: TENENTE ALENCAR, DETERMINAÇÃO: COMANDANTE DO CBC. FOI REALIZADO O CORTE TOTAL DE UMA ÁRVORE DA ESPÉCIE ANGELINZEIRO. OCORRÊNCIA REALIZADA SEM ALTERAÇÃO. COMANDO DE SOCORRO: TEN BM DENILSON. COORDENADOR: TEN BM GUERREIRO | K29: Ezequias Guerreiro Marques
A30: Outras ocorrências | B30: Transporte de pessoal ou equipamento | C30: 2023 | D30: Jan | E30: 44929 | G30: 44929 | I30: CSM. AR-47. O EFETIVO: SGT BM SILAS, CB MAQUINÉ E FC JOSIMAR, DESLOCARAM-SE AO POSTO DE IRANDUBA PARA A MANUTENÇÃO DA VIATURA UR-17. PORÉM, SEM ÊXITO. VIATURA DEU CHEGADA A MANAUS APÓS O RETORNO ÀS 11H30MIN. FINALIZADA S/A. COMANDO DE SOCORRO: TEN BM DENILSON COORDENADOR: TEN BM GUERREIRO | K30: Ezequias Guerreiro Marques
A31: Outras ocorrências | B31: Incêndio em transformador de poste de rede elétrica | C31: 2023 | D31: Jan | E31: 44929 | G31: 44929 | I31: 1º BI, GRANDE CIRCULAR, ABT-25. AO COMANDO DO CB BM TIAGO SILVA, DESLOCARAM-SE AO LOCAL (BOLA DO JORGE TEIXEIRA) PARA ATENDER OCORRÊNCIA DE INCÊNDIO EM REDE ELÉTRICA. CHEGANDO AO LOCAL FOI CONSTATADO QUE A AMAZONAS ENERGIA JÁ ESTAVA NO LOCAL. AÇÃO DOS BOMBEIROS: A GUARNIÇÃO DO CORPO DE BOMBEIROS REALIZOU A EXTINÇÃO DAS CHAMAS DA REDE ELÉTRICA UTILIZANDO APROXIMADAMENTE 50 L DE ÁGUA (JATO DE ÁGUA/ PACOTES). SOLICITANTE. GLAUBER ANDRADE DE SOUZA, CPF: 74820206249, FONE 981559973. OCORRÊNCIA FINALIZADA SEM ALTERAÇÃO. COMANDO DE SOCORRO: TEN BM DENILSON COORDENADOR: TEN BM GUERREIRO | K31: Ezequias Guerreiro Marques
A32: Outras ocorrências | B32: Corte de árvore | C32: 2023 | D32: Jan | E32: 44929 | G32: 44929 | I32: BIFMA, POSTO SUMAÚMA, ABT-32. AO COMANDO DO SGT BM S. ROCHA, DESLOCARAM-SE AO LOCAL PARA ATENDER OCORRÊNCIA DE ÁRVORE SOBRE RESIDÊNCIA. CHEGANDO AO LOCAL FOI CONSTATADO QUE UMA ÁRVORE DA ESPÉCIE BENJAMINZEIRO ESTAVA SOBRE A RESIDÊNCIA DA SOLICITANTE. AÇÃO DOS BOMBEIROS: RETIRADA E CORTE TOTAL DA ÁRVORE QUE ESTAVA SOBRE A RESIDÊNCIA. SOLICITANTE: ROSA DA CUNHA, FONE: 99203-5488. APÓS DEIXAR LOCAL EM SEGURANÇA, VIATURA RETORNOU AO POSTO DE ORIGEM SEM ALTERAÇÃO. COMANDO DE SOCORRO: TEN BM DENILSON COORDENADOR: TEN BM GUERREIRO | K32: Ezequias Guerreiro Marques
A33: Outras ocorrências | B33: Controle de Insetos | C33: 2023 | D33: Jan | E33: 44929 | G33: 44929 | I33: CASA DE CABA LOCALIZADA NA CUMIEIRA PARTE EXTERNA (40 CM DE DIÂMETRO, APROXIMADAMENTE) RUA 47, CASA 1042 - JAPIIM 1 EM FRENTE A CASA DA CARNE / ATACADÃO / ANTIGA EMPRESA RALC / ESCOLA DE EDUCAÇÃO INFANTIL ESPAÇO DO SABER EDUARDO BALDEVEZO SILVA 99143-5656 CIENTE DO GÁS 'BBE, POSTO CENTRAL, ABT-31. AO COMANDO DO CB BM DIVAL, DESLOCARAM-SE AO LOCAL PARA REALIZAR VISTORIA EM INSETO. CHEGANDO AO LOCAL O SOLICITANTE NÃO SE ENCONTRAVA NO LOCAL, E A INQUILINA ESTAVA DE SAÍDA E NÃO PODERIA AGUARDAR O CONTROLE. A GUARNIÇÃO ORIENTOU PARA POSTERIORMENTE RETORNAR A LIGAÇÃO AO COBOM E REALIZAR OUTRO AGENDAMENTO. VIATURA RETORNOU AO POSTO DE ORIGEM S/A. | K33: Ezequias Guerreiro Marques
A34: Outras ocorrências | B34: Apoio ao samu | C34: 2023 | D34: Jan | E34: 44929 | G34: 44929 | I34: BBE, POSTO CENTRAL, ABT-31. AO COMANDO DO CB BM DIVAL, DESLOCARAM-SE AO LOCAL PARA AJUDAR O SAMU EM TRANSPORTE DE PESSOA OBESA, DA RESIDÊNCIA DO PACIENTE ATÉ A VIATURA DO SAMU. O PACIENTE ENCONTRAVA-SE RETIDO EM SUA CASA, POIS NÃO CONSEGUIA ANDAR PELO SEU PESO E DOR NA REGIÃO ABDOMINAL. PACIENTE: IVAN SOEIRO SALGADO, IDADE: 53 ANOS, CPF: 348.181.702-91, PA 130 X 80, FC 94, GLICEMIA 157, SATURAÇÃO 99%. FOI FEITO A RETIRADA NA PRANCHA (MACA CESTO) E DESCIDO POR AUXÍLIO DE CORDAS, FREIO TIPO 8 E MOSQUETÃO PARA SEGURANÇA NA REMOÇÃO EM UM DECLIVE. APÓS A ENTREGA DO PACIENTE AO SAMU (VIATURA NÃ INFORMADA). VIATURA RETORNOU AO POSTO DE ORIGEM S/A. COMANDO DE SOCORRO: TEN BM DENILSON COORDENADOR: TEN BM GUERREIRO | K34: Ezequias Guerreiro Marques
A35: Outras ocorrências | B35: Salvamento ou captura de animal doméstico | C35: 2023 | D35: Jan | E35: 44929 | G35: 44929 | I35: SRA. GISELE, FONE: 99192-1138. PEDE APOIO PARA RESGATE DEO SEU CACHORRO PRESO NO PORTAO DA SUA CASA, ENTRE O PORTAO E O MURRO. RUA DAS JARANAS, N. 81, COROADO 3, CONJUNTO ACARIQUARA. PROXIMO A MATERNIDADE ANA BRAGA. SOLICITANTE RETORNOU A LIGAÇÃO E INFORMOU QUE NÃO SERÁ MAIS NECESSÁRIO APOIO POIS FOI RETIRADO O ANIMAL. | K35: Ezequias Guerreiro Marques
A36: Outras ocorrências | B36: Corte de algema / anel / outros | C36: 2023 | D36: Jan | E36: 44929 | G36: 44929 | I36: BBE, POSTO CENTRAL, ABT-31. AO COMANDO DO CB BM DIVAL, REALIZARAM CORTE DE ANEL (OURO) DO DEDO ANELAR ESQUERDO DA PACIENTE: JEANE CRISTINA OLIVEIRA ALVES, TEL: 99944-9795, CPF: 876.774.072-34, NASCIMENTO: 25/07/88, IDADE: 34 ANOS, ENDEREÇO: AV CONSTANTINO NERY ¿ Nº 2229 - BAIRRO: CHAPADA. OCORRÊNCIA FINALIZADA SEM ALTERAÇÃO. COMANDO DE SOCORRO: TEN BM DENILSON COORDENADOR: TEN BM GUERREIRO | K36: Ezequias Guerreiro Marques
A37: Incêndio em edificação | B37: Incêndio em residência | C37: 2023 | D37: Jan | E37: 44929 | G37: 44929 | I37: INCÊNDIO EM RESIDÊNCIA - TV. ADALBERTO VELE - BETÂNIA. SOLICITANTE: JÚLIO CESAR 99273 - 9104. BBE; PB CENTRAL; VTR ABT-31 À COMANDO DO ST BM VELASCO. DESLOCA AO LOCAL SOLICITADO, ATENDER OCORRÊNCIA DE INCÊNDIO EM RESIDÊNCIA. AO CHEGAR NO LOCAL, O INCÊNDIO JÁ HAVIA SIDO CONTROLADO POR MORADORES E VIZINHOS. NARRATIVA: RESIDÊNCIA DE ALVENARIA DE 2 PISOS, ONDE O INCÊNDIO COMEÇOU NA SALA DE ESTAR CONJUGADA COM A COZINHA. FOI REALIZADA UMA VERIFICAÇÃO PELA GUARNIÇÃO EM TODOS OS CÔMODOS, NOS DOIS ANDARES. DANOS: MATERIAL QUAIMADO: 01 JOGO DESOFÁ DE 2 E 3 LUGARES, 01 TV SMART 46 ", 01 FREEZER 01 PORTA, 01 GELADEIRA 2 PORTAS, 01 FOGÃO 4 BOCAS, 01 ARMÁRIO DE COZINHA EMBUTIDO, 01 FORNO MICROONDAS, 100m DE FORRÓ PVC. PROPRIETÁRIA: ELZA MARA ELIZÂNGELA DA SILVA LOPES. RG: 10192018-2 IDADE: 49 ANOS. CONTATO: 98805-7004 NO LOCAL VTR PM 25-7309 2º SGT PM MANFRED CPA SUL. LOCAL EM SEGURANÇA, A VTR ABT-31 RETRAI AI PB DE ORIGEM. SERVIÇO DO DIA 03.01.2024 / 2º TURNO CMT DE SOCORRO: 2º TEN BM DENILSON CONTROLADOR COBOM: 1º TEN BM R. LIRA | K37: Rozivaldo de Souza Lira
A38: Outras ocorrências | B38: Apoio ao samu | C38: 2023 | D38: Jan | E38: 44929 | G38: 44929 | I38: Rua Dario de Melo - 93 - Tancredo Neves Ao lado da torre da Vivo E ao lado da Casa n°95. Ela mora na parte de trás, casa de alvenaria no reboco. Na parte da frente tem uma casa de madeira, tem um jambeiro na frente também. Paciente Cadeirante, Diabética e hipertensa, Sozinha, Passando Mal. | K38: Rozivaldo de Souza Lira
A39: Outras ocorrências | B39: Atendimento pré-hospitalar | C39: 2023 | D39: Jan | E39: 44929 | G39: 44929 | I39: UR 19. QRU: Colisão moto X moto. QTR: 23h Acionamento: Agente da GM da PN. QTH: Avenida Coronel Teixeira s/n. Ponto de referência: em frente à árvore de Natal. QRA:Caio Vitor Galvão dos Santos, 25 END: Rua das malvaci 19. Jorge Teixeira. Manaus /AM. FONE: 92 98611 9513 RG: não lembra e estava com documentos. SITUAÇÃO: Pelo local uma vítima, da qual estava sentada, após saído do local da colisão. Transitava na moto com capacete quando veio a colidir com uma outra moto de um colega. Na análise primária, vítima apresenta-se consciente, orientado contactante o pupilas isocoricas e nega algias. Apresenta descreta escoriação em membro superior direito. Sinais vitais estáveis. Negou o transporte para o hospital. Reportado ao Hórus dos fatos e, UR-19, deslocou-se para o PB Jaguar. GREM; PB JAGUAR; VTR UR-19 À COMANDO DO TEN BM SANDRO CAMARGO. DESLOCAOU PARA ATENDER OCORRÊNCIA DE ACIDENTE DE TRÂNSITO. COLISÃO ENTRE DUAS MOTOCICLETAS. NARRATIVA: NO LOCAL UMA VÍTIMA, DA QUAL ESTAVA SENTADA, APÓS SAÍDO DO LOCAL DA COLISÃO. TRANSITAVA NA MOTO COM CAPACETE QUANDO VEIO A COLIDIR COM OUTRA MOTO DE UM COLEGA. NA ANÁLISE PRIMÁRIA, VÍTIMA APRESENTA-SE CONSCIENTE, ORIENTADO CONTACTANTE, AS PUPILAS ISOCORICAS E NEGA ALGIAS. APRESENTA DESCRETA ESCORIAÇÃO EM MEMBRO SUPERIOR DIREITO. SINAIS VITAIS ESTÁVEIS. NEGOU O TRANSPORTE PARA O HOSPITAL. NOME: CAIO VITOR GALVÃO DOS SANTOS. 25 ANOS. ENDEREÇO: RUA DAS MALVACI Nº 19 BAIRRO: JORGE TEIXEIRA. FONE: 92 98611-9513 O MESMO ESTAVA SEM OS DOCUMENTOS. LOCAL EM SEGURANÇA, A VTR UR-19 RETRAI AO PB DE ORIGEM. SERVIÇO DO DIA 03.01.2024 / 2º TURNO CMT DE SOCORRO: 2º TEN BM DENILSON CONTROLADOR COBOM: 1º TEN BM R. LIRA | K39: Rozivaldo de Souza Lira
A40: Outras ocorrências | B40: Prevenção - outros | C40: 2023 | D40: Jan | E40: 44930 | G40: 44930 | H40: 44930 | I40: SEG DO DIA 04/01/2024 CB W. MARINHO 1238 07:30 19:30 12:00 1ºBI 006/1ºBI/2024 PERMANÊNCIA SGT WENDEL 706 07:30 19:30 12:00 SCI- EG 008//SCI-EG/2024 REFORÇO DE GU CB CARLOS ALBERTO 1078 07:30 19:30 12:00 SCI- EG 008//SCI-EG/2024 REFORÇO DE GU CB RAFAELE 1191 07:30 19:30 12:00 SCI- EG 008//SCI-EG/2024 REFORÇO DE GU CB CARDOSO 1129 07:00 19:00 12:00 COBOM 001/COBOM/2024 ATENDIMENTO 193 CB IRINILDO 1158 07:00 17:00 10:00 CENTRAL 006/CBC/2024 REFORÇO DE GU SGT PRISCILA CHAGAS 1525 13:00 18:00 05:00 CBMAM 003/AJAI/2024 PROCESSOS JUDICIAIS PGE E TJAM CB N. SOUZA 1195 07:30 19:30 12:00 PB RODOVIÁRIA 965/BBE/2022 REFORÇO DE GU SGT NELSON 1834 13:00 18:00 05:00 QCG 001/BM-3/EMG/2022 APOIO ADMINISTRATIVO SERVIÇO DO DIA 04.01.2024 / 1º TURNO CMT DE SOCORRO: 2º TEN BM VALÉRIO CONTROLADOR COBOM: 1º TEN BM R. LIRA SGT JEFFERSON ARAÚJO 1533 18:00 06:00 12:00 CIA CG 235/CIACG/2024 SENTINELA DA GUARDA SGT LUTHI 1631 19:00 07:00 12:00 COBOM/CIOPS 002/COBOM/2024 REFORÇO DE GU SGT ONOFRE 1233 20:00 08:00 12:00 BBE 965/BBE/2024 VOLANTE DA ABT-29 CB MARCOS PAULO 1121 19:30 07:30 12:00 SCI-EG 009/SCI/2024 REFORÇO DE GU CB ELIZEU COSTA 1164 19:30 07:30 12:00 SCI-EG 009/SCI/2024 REFORÇO DE GU CB MOREIRA JUNIOR 1256 19:30 07:30 12:00 SCI-EG 009/SCI/2024 REFORÇO DE GU SGT L. RUAS 588 19:30 07:30 12:00 DISTRITO 007/1º BI/2024 PERMANENCIA SGT SIDNEY 703 20:00 08:00 12:00 DAT 182/DAT/2024 PERMANENCIA CB JOILDO 1267 20:00 08:00 12:00 FLUVIAL 002/BBE/2022 REFORÇO DE GU COMANDANTE DE SOCORRO: TEN BM VALÉRIO COORDENADOR: TEN BM GUERREIRO | K40: Ezequias Guerreiro Marques
A41: Outras ocorrências | B41: Atendimento pré-hospitalar transporte inter-hospitalar | C41: 2023 | D41: Jan | E41: 44930 | G41: 44930 | I41: ATENDIMENTO PRÉ - HOSPITALAR TRANSPORTE DE PACIENTE - SCI AV. SANTOS DUMONT. CBC; SCI; VTR ALFA-03 À COMANDO DA SGT BM DIANA DINIZ. DESLOCA DA ÁREA DO AEROPORTO INTERNACIONAL BRIGADEIRO EDUARDO GOMES PARA ATENDER OCRRÊNCIA DE TRANSPORTE DE PACIENTE ATÉ A UPA CAMPOS SALES. PACIENTE: VINICIUS SÁ RODRIGUES. IDADE: 22 ANOS. CPF: 067.734.693-09 TEL: 85 99998-3661 NARRATIVA: PACIENTE APRESENTOU CRISE CONVULSIVA TÔNICA CLÔNICA GENERALIZADA PRESENCIADA PELOS POPULARES NO SAGUÃO DO AEROPORTO. ENCONTRA-SE EM PÓS ICTAL, SUDOREICO, HIPOCORADO, LETÁRGICOS, TAQUICÁRDICO, HIPOTENSÃO PA:104X64 FC:130 SAT:94% T: 36.2C. AÇÃO DO BOMBEIRO: REALIZADO REMOÇÃO DO PACIENTE PARA UPA DE CAMPOS SALES ACOMPANHADO PELO FUNCIONÁRIO DA EMPRESA LATAM, NOME: JUAN MATHEUS NASCIMENTO SILVA. MÉDICO DR. ALTAIR ALENCAR JR. CRM 10346 SERVIÇO DO DIA 04.01.2024 / 1º TURNO CMT DE SOCORRO: 2º TEN BM VALÉRIO CONTROLADOR COBOM: 1º TEN BM R. LIRA | K41: Rozivaldo de Souza Lira
A42: Outras ocorrências | B42: Acidente de trânsito com vítima fatal | C42: 2023 | D42: Jan | E42: 44930 | G42: 44930 | I42: BUSCA, RESGATE DE PESSOA. O SAMU SOLICITOU QUE UM VEICULO CAIU EM UM BARRANCO COM VÍTIMA INCONSCIENTE NA AVENIDA SOLIMÕES BAIRRO MAUAZINHO 1º BI; PB ZUMBI; VTR ABT-30 À COMANDO DO CB BM JORGE COELHO. DESLOCA AO LOCAL SOLICITADO, ATENDER OCORRÊNCIA DE ACIDÊNTE DE TRÂNSITO COM VÍTIMA FATAL. VEÍCULO: FORD ECO SPORT. PLACA: NOOG175 COR: PRATA.VÍTIMA: JOÃO DE SOUZA. 55 ANOS. RG: 195186-1 LOCAL: AVENIDA SOLIMÕES. DADOS DO SAMU: MÉDICA: LARISSA CÂMARA CRM 7365. (ATESTOU O ÓBTO) ENFERMEIRA: FRANCISCA ANNE, CONDUTOR: CLÁUDIO SALLES. NO LOCAL, PERÍCIA: JOSÉ QUEIROZ E ADILSON PINTO. IML: VTR-741 CONDUTOR: GILSON GOMES, TÉCNICO: FELIPE MENESES. AÇÃO DO BOMBEIRO: RETIRADA DO CORPO DO INTERIOR DO VEÍCULO E REGATADO ATRAVÉS DO SISTEMA 4X1, EM SEGUIDA ENTREGUE AO IML. LOCAL EM SEGURANÇA, A VTR ABT-30 RETRAI AO PB DE ORIGEM. SERVIÇO DO DIA 04.01.2024 / 1º TURNO CMT DE SOCORRO: 2º TEN BM VALÉRIO CONTROLADOR COBOM: 1º TEN BM R. LIRA | K42: Rozivaldo de Souza Lira
A43: Outras ocorrências | B43: Vistoria em árvore - situação de risco | C43: 2023 | D43: Jan | E43: 44930 | G43: 44930 | I43: VISTORIA EM ÁRVORE- AUTORIZAÇÃO Nº730/2021-DMAU/SEMMAS SOLICITANTE: ALCEMIRA LOPES RUA ENVIRAS, 174 CONJ. AJURICABA-COROADO CBC; VTR AR-42 COMPOSTA PELOS MILITARES, CB BM RODRIGO VIEIRA, CB BM CARLOS LOPES, CB BM IRINILDO. DESLOCA PARA CUMPRIR A AUTORIZAÇÃO Nº 730/2021 - DMAU/SEMMAS. PROTOCOLO SIGED: 2021.15848.15875.9.014439 / SOLICITANTE: ALCEMIRA LOPES DA SILVA. ENDEREÇO: RUA ENVIRAS Nº 174 CONJUNTO ACARIQUARA - COROADO. ÁRVORE NÃO CORTADA, NECESSITA APENAS PODA, O CH DE GUARNIÇÃO ORIENTOU A PROPRIETÁRIA. A VTR AR-42 RETRAIU AO PB DE ORIGEM. SERVIÇO DO DIA 04.01.2024 / 1º TURNO CMT DE SOCORRO: 2º TEN BM VALÉRIO CONTROLADOR COBOM: 1º TEN BM R. LIRA | K43: Rozivaldo de Souza Lira
A44: Outras ocorrências | B44: Vistoria em árvore - situação de risco | C44: 2023 | D44: Jan | E44: 44930 | G44: 44930 | I44: SOLICITANTE INFORMA QUE HÁ NO SEU QUINTAL 3 ÁRVORES DE PORTE GRANDE EM SITUAÇÃO DE RÍSCO, QUE DEVIDO AS CHUVAS ENCONTRAM-SE COM AS RAÍZES EXPOSTAS, 1 MANGUEIRA E 2 ABACATEIROS RUA ITAPURA, Nº17, BAIRRO NOVO ALEIXO III, SUBINDO O CHAPÉU GOIANO, POR TRÁS DO CONDOMÍNIO PARQUE AMAZÔNIA SOLICITANTE: HELOÍSA LEAL. TEL-98825-3024 CBC; VTR AR-55 À COMANDO DO TEN BM VALÉRIO. DESLOCA AO LOCAL SOLICITADO, ATENDER OCORRÊNCIA DE VISTORIA EM 3 ÁRVORES, 1 MANGUEIRA E 2 ABACATEIROS. VISTORIA REALIZADA, AS ÁRVORES ESTÃO SADIAS, NÃO NECESSITAM DE CORTE, A SOLICITANTE FOI ORIENTADA SOBRE A SITUAÇÃO. A VTR AR-55 RETRAI AO PB DE ORIGEM. SERVIÇO DO DIA 04.01.2024 / 1º TURNO CMT DE SOCORRO: 2º TEN BM VALÉRIO CONTROLADOR COBOM: 1º TEN BM R. LIRA | K44: Rozivaldo de Souza Lira
A45: Outras ocorrências | B45: Corte de algema / anel / outros | C45: 2023 | D45: Jan | E45: 44930 | G45: 44930 | I45: CORTE DE ANEL POSTO ZUMBI NA RUA DRA. HELOISA ZUMBI DOS PALMARES 1º BI; PB ZUMBI; A GUARNIÇÃO DA VTR ABT-30, REALIZOU CORTE DE ANEL DE AÇO, DEDO INDICADOR DIREITO. PACIENTE : DAVI CESAR MENEZES. 15 ANOS. RESPONSÁVEL, PAI : JEFERSON CESAR MENEZES. RG: 1862788-9 ENDEREÇO: RUA IPOEIRAS Nº 20 NOVO ALEIXO. FONE 984071641 SERVIÇO DO DIA 04.01.2024 / 1º TURNO CMT DE SOCORRO: 2º TEN BM VALÉRIO CONTROLADOR COBOM: 1º TEN BM R. LIRA | K45: Rozivaldo de Souza Lira
A46: Outras ocorrências | B46: Controle de Insetos | C46: 2023 | D46: Jan | E46: 44930 | G46: 44930 | I46: CASA DE CABA NO REFEITÓRIO DA ESCOLA MUNICIPAL PROF IVOMAR DE LIMA VIEIRA AV. ALARICO FURTADO 9941684 CIDADE DE DEUS , PRÓX A RESERVA ADOLFO DUCK SOLICITANTE:MARCIANO MATIAS 99207-5335 1º BI; PB CIS GC; VTR ABT-25 À COMANDO DO SGT BM ARILDO. DESLOCA AO LOCAL SOLICITADO, ATENDER OCORRÊNCIA DE CONTROLE DE INSETOS, CONTROLE REALIZADO COM SUCESSO, A VTR ABT-25 RETRAI AO PB DE ORIGEM. SERVIÇO DO DIA 04.01.2024 / 1º TURNO CMT DE SOCORRO: 2º TEN BM VALÉRIO CONTROLADOR COBOM: 1º TEN BM R. LIRA | K46: Rozivaldo de Souza Lira
A47: Outras ocorrências | B47: Busca, resgate de pessoa em ambiente de selva | C47: 2023 | D47: Jan | E47: 44930 | G47: 44930 | H47: 44930 | I47: BUSCA , RESGATE DE PESSOA EM AMBIENTE DE SELVA - COMPARECEU A ESTE DIP O NACIONAL PAULO PARA DECLARAR QUE SEU FILHO SAIU POR VOLTA DAS 18:50 HS EM UMA MOTO DE PLACAS NOR 3104. O DECLARANTE INFORMA QUE VIZINHOS INFORMARAM QUE PAULO JUNIO TERIA SIDO ''LEVADO'' POR TRAFICATES DO BAIRRO DA UNIÃO PARA UMA REGIÃO DE MATA E ATÉ O MOMENTO NÃO RETORNOU. ENDEREÇO: RUA ZULMA DE AZEVEDO Nº271; BAIRRO: PAQUE 10 DE NOVEMBRO; COMPLEMENTO: BAIRRO DA UNIÃO SOLICITANTE: : PAULO DE LIMA E SILVA JUNIOR CONTATO: 99347-4069. EM ANDAMENTO... SERVIÇO DO DIA 04.01.2024 / 1º TURNO CMT DE SOCORRO: 2º TEN BM VALÉRIO CONTROLADOR COBOM: 1º TEN BM R. LIRA .................................................................................... SERVIÇO DO DIA 05 DE JANEIRO DE 2024. 1º TURNO. BOLETIM Nº 00000055/2024 - 1º DISTRITO INTEGRADO DE POLÍCIA - MANAUS-AM. BUSCA E RESGATE DE PESSOA EM AMBIENTE DE SELVA - COMPARECEU A ESTE DIP O NACIONAL PAULO PARA DECLARAR QUE SEU FILHO SAIU POR VOLTA DAS 18:50 HS EM UMA MOTO DE PLACA NOR-3104. O DECLARANTE INFORMA QUE VIZINHOS INFORMARAM QUE PAULO JUNIOR TERIA SIDO ''LEVADO'' POR TRAFICANTES DO BAIRRO DA UNIÃO PARA UMA REGIÃO DE MATA E ATÉ O MOMENTO NÃO RETORNOU. ENDEREÇO: RUA ZULMA DE AZEVEDO Nº 271; BAIRRO: PARQUE 10 DE NOVEMBRO; COMPLEMENTO: BAIRRO DA UNIÃO. SOLICITANTE: PAULO DE LIMA E SILVA JUNIOR. CONTATO: 99347-4069. DEPARECIMENTO DESDE O DIA 31.12.2022. EQUIPE DE BUSCA DO BIFMA DESLOCARÁ NO DIA 05/01/2022. A EQUIPE COMANDADA PELO TENENTE GOMES, SGT EVANGELISTA, SGT S. ROCHA, CB DANILO, CB A. SILVEIRA, CB FELIPE DESLOCARAM AS 07:30 PARA O LOCAL DAS BUSCAS.INFORMARAM QUE PERCORRERAM UM PERCURSO DE APROXIMADAMENTE 3,5 KM ATÉ LOCALIZAR UMA ÁREA COM MARCAS DE AÇÃO HUMANA. VERIFICARAM O LOCAL E CONSTATARAM A PRESENÇA DE UM CORPO ENTERRADO E QUE INCLUSIVE FOI RECONHECIDO PELO PAI DA VÍTIMA QUE ESTAVA NO LOCAL. PAULO JUNIO PEREIRA SILVA,19 ANOS(VÍTIMA). PAULO DE LIMA SILVA JUNIOR, 36 ANOS (PAI). ANA PAULA FAIA DA SILVA, 32 ANOS ( MADRASTA), END.RUA DAS PALMEIRA 271 BAIRRO UNIÃO. NO LOCAL ANDRÉ SANTANA - PERITO PERÍCIA PC VTR 2005. NUNES ¿ INVESTIGADOR, FABIANA ¿ INVESTIGADORA HOMICÍDIOS ¿ PC. VTR 667 - IML FRANCISCO ALVEZ E RIBAMAR. APENAS ESSAS INFORNMAÇÕES FORAM REPASSADAS PELO SGT EVANGELISTA. SOLICITANTE: PAULO DE LIMA. TEWL: 92 993474069. SERVIÇO SAEM ALTERAÇAO. CONTROLADOR: TEN QOABM JAMERSON COMTE SOCORRO: TEN QOAB MARCELO | K47: Jamerson Marques de Castro
A48: Outras ocorrências | B48: Controle de Insetos | C48: 2023 | D48: Jan | E48: 44930 | G48: 44930 | I48: CONTROLE DE INSETOS, NA RUA: RECIFE ADRIANÓPOLIS BBE; PB RODOVIÁRIA; VTR ABT-29 À COMANDO DA SGT BM LAURA. DESLOCA ATÉ O NOVO PRÉDIO DO DETRAN, REALIZAR CONTROLE DE INSETOS. CONTROLE REALIZADO COM SUCESSO, A VTR ABT-29 RETRAI AO PB DE ORIGEM. SERVIÇO DO DIA 04.01.2024 / 1º TURNO CMT DE SOCORRO: 2º TEN BM VALÉRIO CONTROLADOR COBOM: 1º TEN BM R. LIRA | K48: Rozivaldo de Souza Lira
A49: Outras ocorrências | B49: Atendimento pré-hospitalar transporte de paciente | C49: 2023 | D49: Jan | E49: 44930 | G49: 44930 | I49: GREM, PONTA NEGRA, UR-19, UR-23. AO COMANDO DA TEN BM JANETE, REALIZARAM TRANSPORTE DE PACIENTE. TIPO DA OCORRÊNCIA: VÍTIMA DE FRATURA EM MID. SITUAÇÃO DA OCORRÊNCIA: UR 23 ACIONADA PELO CMT DE SOCORRO, TEN VALÉRIO, PARA FAZER O TRANSPORTE DA GENITORA DO MILITAR ST R. RODRIGUES, A MESMA ENCONTRAVA-SE NO HPS JOAO LÚCIO AGUARDANDO TRANSPORTE PARA SUA RESIDÊNCIA APOS ATENDIMENTO MÉDICO (ORTOPEDISTA), A MESMA SOFREU QUEDA E TEVE FRATURA EM PÉ DIREITO. NO MOMENTO PACIENTE ESTÁVEL: SITUAÇÃO DA OCORRÊNCIA: UR 23 ACIONADA PELO CMT DE SOCORRO, TEN VALÉRIO, PARA FAZER O TRANSPORTE DA GENITORA DO MILITAR ST BM R. RODRIGUES, A MESMA ENCONTRAVA-SE NO HPS JOAO LÚCIO AGUARDANDO TRANSPORTE PARA SUA RESIDÊNCIA APOS ATENDIMENTO MÉDICO (ORTOPEDISTA), A MESMA SOFREU QUEDA E TEVE FRATURA EM PÉ DIREITO, NO MOMENTO PACIENTE ESTÁVEL. DADOS DA VÍTIMA: FRANCILENE RODRIGUES DE OLIVEIRA, RG: 2429456-0, 64 ANOS, DN: 01/01/1959, ENDEREÇO: RUA CAIAPÓ, 24 - NOVO ALEIXO, FONE 98404-5269. APÓS DEIXAR A PACIENTE EM SUA RESIDÊNCIA, VIATURA RETORNOU AO POSTO DE ORIGEM SEM ALTERAÇÃO. COMANDO DE SOCORRO: TEN BM VALÉRIO COORDENADOR: TEN BM GUERREIRO | K49: Ezequias Guerreiro Marques
A50: Outras ocorrências | B50: Tentativa de suicídio | C50: 2023 | D50: Jan | E50: 44930 | G50: 44930 | I50: SCI, ALFA-03. AO COMANDO DO ST BM VIVALDO. ATENDIMENTO PRÉ-HOSPITALAR/ TENTATIVA DE SUICÍDIO. TENTANTE FOI ENCONTRADO POR FUNCIONÁRIOS NO ESTACIONAMENTO DO AEROPORTO DENTRO DO SEU AUTOMÓVEL APÓS INGERIR 43 COMPRIMIDOS DE MORFINA 10MG. ENCONTRA-SE, LÚCIDO, ORIENTADO, LETÁRGICO, HIPOCORADO, NORMOTENSO, OBESO, PA: 106X84, FC:81, SAT: 96% T: 36.5C DEXTRO: 90 GLASGOW: 14. ACIONADO SERVIÇO DE PRONTO ATENDIMENTO SAMU. ENTREGUE AOS CUIDADOS DA TÉCNICA ENFERMAGEM ROSANA E CONDUTOR JOAREZ. PACIENTE: SÉRGIO DUARTE DA SILVEIRA JÚNIOR, IDADE: 36 ANOS, CPF: 83312110220, ESPOSA: ADA LIMA DA SILVEIRA, TEL: 9298431-4504. APÓS ENTREGA DO PACIENTE AO SAMU, VIATURA RETORNOU AO POSTO DE ORIGEM SEM ALTERAÇÃO. COMANDO DE SOCORRO: TEN BM VALÉRIO COORDENADOR: TEN BM GUERREIRO | K50: Ezequias Guerreiro Marques
A51: Outras ocorrências | B51: Atendimento pré-hospitalar | C51: 2023 | D51: Jan | E51: 44930 | G51: 44930 | I51: SCI, ALFA-03. AO COMANDO DO ST BM VIVALDO. ATENDIMENTO PRÉ-HOSPITALAR/ TENTATIVA DE SUICÍDIO. TENTANTE FOI ENCONTRADO POR FUNCIONÁRIOS NO ESTACIONAMENTO DO AEROPORTO DENTRO DO SEU AUTOMÓVEL APÓS INGERIR 43 COMPRIMIDOS DE MORFINA 10MG. ENCONTRA-SE, LÚCIDO, ORIENTADO, LETÁRGICO, HIPOCORADO, NORMOTENSO, OBESO, PA: 106X84, FC:81, SAT: 96% T: 36.5C DEXTRO: 90 GLASGOW: 14. ACIONADO SERVIÇO DE PRONTO ATENDIMENTO SAMU. ENTREGUE AOS CUIDADOS DA TÉCNICA ENFERMAGEM ROSANA E CONDUTOR JOAREZ. PACIENTE: SÉRGIO DUARTE DA SILVEIRA JÚNIOR, IDADE: 36 ANOS, CPF: 83312110220, ESPOSA: ADA LIMA DA SILVEIRA, TEL: 9298431-4504. APÓS ENTREGA DO PACIENTE AO SAMU, VIATURA RETORNOU AO POSTO DE ORIGEM SEM ALTERAÇÃO. COMANDO DE SOCORRO: TEN BM VALÉRIO COORDENADOR: TEN BM GUERREIRO | K51: Ezequias Guerreiro Marques
A52: Outras ocorrências | B52: Salvamento ou captura de animal doméstico | C52: 2023 | D52: Jan | E52: 44930 | G52: 44930 | I52: BIFMA, POSTO SUMAÚMA, ABT-32. AO COMANDO DO SGT BM EVANGELISTA, DESLOCARAM-SE PARA REALIZAR RESGATE DE ANIMAL DOMÉSTICO EM BUEIRO, CONFORME INFORMADO PELA SOLICITANTE. AÇÃO DO BOMBEIROS: BUSCA E RESGATE DE ANIMAL DOMÉSTICO (CACHORRO). O ANIMAL NÃO FOI LOCALIZADO NO SUMIDOURO, CONFORME INFORMADO, POIS, ADENTROU AS TUBULAÇÕES DE ESGOTO QUE PERCORREM TODO O BAIRRO. NOME: LANE NERY DE SOUZA, 52 ANOS, CPF: 30985498234, TEL: 991335333. APÓS AS ORIENTAÇÕES A SOLICITANTE (LIGAR NOVAMENTE AO 193 CASO O ANIMAL VENHA A APARECER), VIATURA RETORNOU AO POSTO DE ORIGEM SEM ALTERAÇÃO. COMANDO DE SOCORRO: TEN BM VALÉRIO COORDENADOR: TEN BM GUERREIRO | K52: Ezequias Guerreiro Marques
A53: Outras ocorrências | B53: Corte de algema / anel / outros | C53: 2023 | D53: Jan | E53: 44931 | G53: 44931 | I53: BIFMA, POSTO SUMAÚMA, ABT-32. AO COMANDO DO SGT BM EVANGELISTA, REALIZARAM CORTE DE ANEL DA PACIENTE: JAIME RAFAEL CRESPO LIMA, 11 ANOS, RG:33366225, TEL: 991699286, LOCAL: RUA GUARATINGA Nº 24, CONJ. ÁGUAS CLARAS; ACOMPANHANTE: JANIELLY DA SILVA CRESPO (GENITORA). OCORRÊNCIA FINALIZADA SEM ALTERAÇÃO. COMANDO DE SOCORRO: TEN BM VALÉRIO COORDENADOR: TEN BM GUERREIRO | K53: Ezequias Guerreiro Marques
A54: Outras ocorrências | B54: Treinamento / instrução | C54: 2023 | D54: Jan | E54: 44931 | G54: 44931 | H54: 44931 | I54: SERVIÇO DO DIA 05 DE JANEIRO DE 2024. 1º TURNO. GREM, PONTA NEGRA, UR-23. AO COMANDO DO TEN BM WASHINGTON BORGES, CUMPRIRAM A ORDEM DE SERVIÇO Nº 005/GREM/CBC/2024. EVENTO: TFM NO QCG, DETERMINAÇÃO: CMT DO GREM, MISSÃO: PREVENÇÃO E ATENDIMENTO EM URGÊNCIA/EMERGÊNCIA. FOI REALIZADO A PREVENÇÃO NO LOCAL E CUMPRIDO TODOS OS HORÁRIOS, SEM ALTERAÇÃO. SOLICITANTE: CBC/COBOM. TEL: 36123130. SERVIÇO SEM ALTERAÇÃO CONTROLADOR: TEN QOABM JAMERSON COMTE SOCORRO: TEN QOAB MARCELO | K54: Jamerson Marques de Castro
A55: Outras ocorrências | B55: Prevenção - outros | C55: 2023 | D55: Jan | E55: 44931 | G55: 44931 | H55: 44931 | I55: SERVIÇO DO DIA 05 DE JANEIRO DE 202. 1º TURNO. CUMPRIRAM ESCALA EXTRA NO SERVIÇO DE S. E. G. OS MILITARES DE ACORDO COM SUAS O.S NOS REFERIDOS POSTOS OU BATALHÕES DO CBMAM. SEG 1º TURNO, S/A. SGT JOSEANE COSTA 1608 07:00 19:00 12:00 COBOM 004/COBOM/2024 ATENDIMENTO 193 2024010507173670707 CB DAVIDSON 1043 08:00 20:00 12:00 BIFMA 003/BIFMA/2024 VOLANTE ABT- 32 2024010507173670707 CB ZWANG 1249 07:30 19:30 12:00 PB ZUMBI 009/1°BI/2024 REFORÇO DE GU 2024010507173670707 CB J. NUNES 1063 07:00 17:00 10:00 QCG 007/CBC/2024 ACORTE DE ÁRVORE 2024010507173670707 ST ALEX 625 07:30 19:30 12:00 CIS G. CIRCULAR 009/1°BI/2024 REFORÇO DE GU 2024010507173670707 TEN BIANOR GARCIA 560 07:30 19:30 12:00 SCI-EG 010/SCI-EG/2024 REFORÇO DE EQUIPAGEM 2024010507173670707 CB CLEYTON 1242 07:30 19:30 12:0 0 SCI-EG 010/SCI-EG/2024 REFORÇO DE EQUIPAGEM 2024010507173670707 CB F. LEITE 1262 07:30 19:30 12:00 SCI-EG 010/SCI-EG/2024 REFORÇO DE EQUIPAGEM 2024010507173670707 SGT CELINA 1532 13:00 18:00 05:00 QCG 004/AJAI/2024 ASSESSORIA JURÍDICA 2024010507173670707 TEN GOMES 604 13:00 18:00 05:00 QCG 005/BIFMA/2024 INSTRUÇÃO DE LEGISLAÇÃO TÉCNICA 2024010507173670707 CB RENATA 1126 13:00 18:00 05:00 QCG 005/BIFMA/2024 INSTRUÇÃO DE LEGISLAÇÃO TÉCNICA 2024010507173670707 SGT SILLAS JUNIOR 715 13:00 17:00 04:00 QCG 001/CSM/2024 MANUTENÇÃO DE VTR 2024010507173670707 SGT EVERTON FARIAS 1849 13:00 17:00 04:00 QCG 001/CSM/2024 MANUTENÇÃO DE VTR 2024010507173670707 CB MAQUINÉ 1156 13:00 17:00 04:00 QCG 001/CSM/2024 MANUTENÇÃO DE VTR 2024010507173670707 TEN GOMES 604 07:00 14:00 07:00 BIFMA 004/BIFMA/2024 REFORÇO DE GU 2024010507173670707 SGT EVANGELISTA 699 07:00 14:00 07:00 BIFMA 004/BIFMA/2024 REFORÇO DE GU 2024010507173670707 SGT S. ROCHA 771 07:00 14:00 07:00 BIFMA 004/BIFMA/2024 REFORÇO DE GU 2024010507173670707 CB MARCUS 1017 07:00 14:00 07:00 BIFMA 004/BIFMA/2024 REFORÇO DE GU 2024010507173670707 CB DANILO 1046 07:00 14:00 07:00 BIFMA 004/BIFMA/2024 REFORÇO DE GU 2024010507173670707 CB A. SILVEIRA 1235 07:00 14:00 07:00 BIFMA 004/BIFMA/2024 REFORÇO DE GU 2024010507173670707 CB NELSON 1834 13:00 16:00 03:00 QCG 002/BM-3/EMG/2024 APOIO ADMINISTRATIVO 2024010507173670707 TEN EWERTON 581 13:00 16:00 03:00 QCG 011/1°BI/2024 INSTRUÇÃO ATIVIDADES TÉCNICAS 2024010507173670707 ST JEAN 669 13:00 17:30 04:30 QCG 002/BBE/2024 INSTRUÇÃO DE LEGISLAÇÃO TÉCNICA 2024010507173670707 CB NATALI 1237 13:00 17:30 04:30 QCG 002/BBE/20223 INSTRUÇÃO DE LEGISLAÇÃO TÉCNICA 2024010507173670707 CONTROLADOR: TEN QOABM JAMERSON COMTE SOCORRO: TEN QOAB MARCELO CB TOBIAS 1241 19:00 07:00 12:00 COBOM 003/COBOM/2024 REFORÇO DE GUARNIÇÃO ST COSTA E SILVA 378 19:30 07:30 12:00 SCI-EG 011/SCI-EG/2024 REFORÇO DE GUARNIÇÃO ST HARLEY 509 19:30 07:30 12:00 SCI-EG 011/SCI-EG/2024 REFORÇO DE GUARNIÇÃO ST LEANDRO 634 19:30 07:30 12:00 SCI-EG 011/SCI-EG/2024 REFORÇO DE GUARNIÇÃO SGT RONILDES 757 19:30 07:30 12:00 CIS G. CIRCULAR 010/1BI/2024 REFORÇO DE GUARNIÇÃO CB J. BRITO 1113 20:00 08:00 12:00 DAT 182/DAT/2024 PERMANÊNCIA CB RAFAEL LIMA 1040 19:30 07:00 12:00 ZUMBI 010/1ºBI/2024 REFORÇO DE GUARNIÇÃO CB JOEL 1087 20:00 08:00 12:00 BIFMA 003/BIFMA/2024 VOLANTE ABT- 32 CB FABIANO 1044 20:00 08:00 12:0 0 FLUVIAL 003/BBE/2024 PERMANÊNCIA CONTROLADOR: TEN QOABM GUERREIRO COMTE SOCORRO: TEN QOAB MARCELO | K55: Ezequias Guerreiro Marques
A56: Outras ocorrências | B56: Transporte de pessoal ou equipamento | C56: 2023 | D56: Jan | E56: 44931 | G56: 44931 | H56: 44931 | I56: SERVIÇO DO DIA 05 DE JANEIRO DE 2024. 1º TURNO. CSM AR-53 A COMANDO DO TENENTE ANTONIO JUNIOR DESLOCOU-SE PARA O LOCAL. DESLOCAMENTO AO PB DE MANACAPURU PARA MANUTENÇÃO NAS VIATURAS DO REFERIDO BATALHÃO.EFETIVO: TEN ANTONIO JUNIOR; CB MAQUINÉ, FUNCIONÁRIO CIVIL ISAÍAS.VTR AR-53. A GUARNIÇÃO RETORNOU A MANAUS, AO CSM CBMAM POR VOLTA DAS 12;30. SOLICITANTE: CSM/CBMAM. TEL: 36123130. SERVIÇO SEM ALTERAÇÃO. CONTROLADOR: TEN QOABM JAMERSON COMTE SOCORRO: TEN QOAB MARCELO | K56: Jamerson Marques de Castro
A57: Incêndio em edificação | B57: INCÊNDIO EM COMÉRCIO DE PEQUENO OU MÉDIO PORTE | C57: 2023 | D57: Jan | E57: 44931 | G57: 44931 | H57: 44931 | I57: SERVIÇO DO DIA 05 DE JANEIRO DE 2024. 1º TURNO. "BBE POSTO CENTRAL ABT-31 A COMANDO DO CB ROBSON DESLOCOU-SE PARA O LOCAL. POSTO CENTAL: INCÊNDIO EM ESTABELECIMENTO COMERCIAL - CHURRASCARIA & RESTAURANTE FAMA. RUA JOAQUIM SARMENTO, 231 CENTRO SOLICITANTE: WERLESON BRITO DE OLIVEIRA (PROPRIETÁRIO) 32ANOS, CPF: 95207872240, TEL: 92984889509. SITUAÇÃO: INCÊNDIO NA CHURRASQUEIRA CONTROLADO PELOS FUNCIONÁRIOS COM EXTINTOR PQ. AÇÃO BM: EXAUSTÃO DA FUMAÇA COM VENTILADOR MECÂNICO. SOLICITANTE: JORGE LUCAS. TEL: 92 995103564. SERVIÇO SEM ALTERAÇÃO." CONTROLADOR: TEN QOABM JAMERSON COMTE SOCORRO: TEN QOAB MARCELO | K57: Jamerson Marques de Castro
A58: Outras ocorrências | B58: Lavagem de pátio ou pista | C58: 2023 | D58: Jan | E58: 44931 | G58: 44931 | H58: 44931 | I58: SERVIÇO DO DIA 05 DE JANEIRO DE 2024. 1º TURNO. ORDEM DE SERVIÇO Nº 008-CBC/2024. EVENTO: APOIO A FVS-AM. MISSÃO: REALIZAR LAVAGEM DE PISTA. HORÁRIO: 13H. EFETIVO: ATA COM CONDUTOR CB GREICE LIMA E CB WALLAX.ORDEM DE SERVIÇO Nº 008-CBC/2024. EVENTO: APOIO A FVS-AM. MISSÃO: REALIZAR LAVAGEM DE PISTA. HORÁRIO: 13H. EFETIVO: ATA COM CONDUTOR CB GREICE LIMA E CB WALLAX. AO CHEGAR À FVS O CB WALLAX PROCUROU O RESPONSÁVEL, SENHOR WANDERLEY MAIA BRASIL, RG 9543538, CPF 47471140259, CELULAR 992083932, QUE INFORMOU QUE A MISSÃO DE LAVAGEM DE PATIO ERA APENAS PARA AMANHÃ. SEGUNDO O MESMO, O PATIO ESTÁ CHEIO DE AREIA E FAZ OS CARROS DERRAPAREM NO LOCAL. A O.S 008/CBC/2024 INFORMAVA QUE A MISSÃO ERA PARA O DIA DE HOJE, MOTIVO PELO QUAL A GUARNIÇÃO FOI DESLOCADA PARA O LOCAL. APÓS, A ATA-03 RETORNOU AO POSTO CENTRAL. SOLICITANTE: CBC. TEL: 36123130. SERVIÇO SEM ALTERAÇÃO. CONTROLADOR: TEN QOABM JAMERSON COMTE SOCORRO: TEN QOAB MARCELO | K58: Jamerson Marques de Castro
A59: Outras ocorrências | B59: Corte de árvore | C59: 2023 | D59: Jan | E59: 44931 | G59: 44931 | H59: 44931 | I59: SERVIÇO DO DIA 05 DE JANEIRO DE 2024. 1º TURNO. CBC AR-42 A COMANDO DO CB J.NUNES DESLOCOU-SE PARA O LOCAL. FOI REALIZADO UMA PODA DE UMA ARVORE DA ESPECIE MANGUEIRA DE PORTE MEDIO DE PROPRIEDADE DA SENHORA BERENICE, TELEFONE 992696283. APENAS ESSAS INFORMAÇÕES FORAM REPASSADAS PELO CB CARLOS LOPES. SOLICITANTE: CBC/COBOM. TEL: 36123130. SERVIÇO SEM ALTERAÇÃO. CONTROLADOR: TEN QOABM JAMERSON COMTE SOCORRO: TEN QOAB MARCELO | K59: Jamerson Marques de Castro
A60: Outras ocorrências | B60: Captura de insetos / abelhas / similares | C60: 2023 | D60: Jan | E60: 44931 | G60: 44931 | H60: 44931 | I60: SERVIÇO DO DIA 05 DE JANEIRO DE 2024. 1º TURNO. 1º BI POSTO DO ZUMBI ABT-30 A COMANDO DO SGT GENTIL DESLOCOU-SE PARA O LOCAL. FOI INFORMADO PELO SGT GENTIL QUE AS ABELHAS ENCONTRAVAM-SE EM UM BARRANCO DE DIFICIL ACESSO A APROXIMADAMENTE 08 METROS DE ALTURA. FOI DADO AS DEVIDAS ORIENTAÇÕES DE SEGURANÇA A SENHORA SUELEN D SOUZA, RG 26905078, TELEFONE 92 994866457. O LOCAL FOI ENTREGUE EM SEGURANÇA A PROPRIETARIA. SOLICITANTE: FABIO DE SOUZA. TEL: 92 993436528. SERVIÇO SEM ALTERAÇÃO. CONTROLADOR: TEN QOABM JAMERSON COMTE SOCORRO: TEN QOAB MARCELO | K60: Jamerson Marques de Castro
A61: Incêndio em edificação | B61: Incêndio em residência | C61: 2023 | D61: Jan | E61: 44931 | G61: 44931 | I61: SERVIÇO DO DIA 05 DE JANEIRO DE 2024. 1º TURNO. BBE POSTO DA RODOVIÁRIA ABT-29 A COMANDO DO SGT VITAL DESLOCOU-SE PARA O LOCAL. INCENDIO EM RESIDENCIA. AÇAO DOS BOMBEIROS: CHEGANDO NO LOCAL FOMOS INFORMADOS QUE NAO HAVIA MAIS O SINISTRO E QUE SE TRATAVA DE UM FOGO QUE CRIANÇAS ATEARAM NUMA GELADEIRA VELHA NUM TERRENO ABANDONADO. O SENHOR ELINALDO MASCARENHAS 45 ANOS. CPF 613 430.562.68. RESIDENTE A RUA 15 DE OUTUBRO N.125 BAIRRO DE REDENÇAO, CONSEGUIU JUNTO COM VIZINHOS APAGAR O SINISTRO., FICANDO O MESMO RESPONSAVEL PELO LOCAL. LOCAL EM SEGURANCA SEM ALTERAÇAO. SOLICITANTE: ROSANA SILVA. TEL: 92 984858565. SERVIÇO SEM ALTERAÇÃO. CONTROLADOR: TEN QOABM JAMERSON COMTE SOCORRO: TEN QOAB MARCELO | K61: Jamerson Marques de Castro
A62: Outras ocorrências | B62: Corte de árvore | C62: 2023 | D62: Jan | E62: 44931 | G62: 44931 | H62: 44931 | I62: SERVIÇO DO DIA 05 DE JANEIRO DE 2024. 1º TURNO. 'CBC AR-42 A COMANDO DO CB J.NUNES DESLOCOU-SE PARA O LOCAL. FOI REALIZADO O CORTE TOTAL DE UM COQUEIRO NA RESIDENCIA DO SGT BM WILKMAN. SOLICITANTE: CBC/COBOM. TEL: 36123130. SERVIÇO SEM ALTERAÇÃO. CONTROLADOR: TEN QOABM JAMERSON COMTE SOCORRO: TEN QOAB MARCELO | K62: Jamerson Marques de Castro
A63: Outras ocorrências | B63: Incêndio em veículo | C63: 2023 | D63: Jan | E63: 44931 | G63: 44931 | H63: 44931 | I63: SERVIÇO DO DIA 05 DE JANEIRO DE 2024. 1º TURNO. 'CBC AR-42 A COMANDO DO CB J.NUNES DESLOCOU-SE PARA O LOCAL. A GUARNIÇÃO ESTAVA EM DESLOCAMENTO PARA O MUNICIPIO DEC IRANDUBA QUANDO DEPAROU-SE COM UM VEICULO SIENA DE PLACA JXF 0573 DE COR PRATA DE PROPRIEDADE DO SENHOR EDUARDO MONTEIRO DOS SANTOS DE 32 ANOS, RG 24018082, RESIDENTE A RUA FRANCISCO ORELLANA Nº 34 DOM PEDRO, EM CHAMAS NO MOTOR. FOI FEITO A EXTINÇÃO DAS CHAMAS COM O USO DE EXTINTORES. O VEICULO FOI ENTREGUE EM SEGURANÇA AO PROPRIETÁRIO. APENAS ESSAS INFORMAÇÕES FORAM REPASSADAS PELO CB CARLOS LOPES. SOLICITANTE: CB CARLOS LOPES. TEL: VIA 193. SERVIÇO SEM ALTERAÇÃO. CONTROLADOR: TEN QOABM JAMERSON COMTE SOCORRO: TEN QOAB MARCELO | K63: Jamerson Marques de Castro
A64: Incêndio em edificação | B64: Vazamento de glp com fogo | C64: 2023 | D64: Jan | E64: 44931 | G64: 44931 | H64: 44931 | I64: BIFMA, POSTO SUMAÚMA, ABT-32. AO COMANDO DO ST BM PABLO. DESLOCARAM-SE AO LOCAL PARA ATENDER OCORRÊNCIA DE VAZAMENTO DE GLP COM FOGO, SEGUIDO DE EXPLOSÃO. RELATO DOS MORADORES: APÓS UM PRINCÍPIO DE INCÊNDIO INICIADO NO FOGÃO, A VÁLVULA DA BOTIJA DE GÁS ROMPEU-SE, CAUSANDO ALGUMAS EXPLOSÕES, A FIM DE AJUDAR, A VÍTIMA QUEBROU UM CANO DE ÁGUA PARA SANAR O PRINCÍPIO DE INCÊNDIO, NO MESMO MOMENTO OCORREU OUTRA EXPLOSÃO, CAUSANDO AS QUEIMADURAS DE 2° GRAU, ATO CONTÍNUO, O SR RENATO CORREU ATÉ O BANHEIRO E ACABOU DESMAIANDO NO LOCAL, SENDO RESGATADO POSTERIORMENTE PELOS POPULARES DA RUA. VÍTIMA: RENATO PEREIRA DE CASTRO, IDADE: 34 ANOS, FONE: 991591615. ATUAÇÃO DA GUARNIÇÃO: APH, ISOLAMENTO DO LOCAL, RETIRADA DA BOTIJA DE GÁS EM VAZAMENTO PARA A ÁREA EXTERNA DA RESIDÊNCIA. VÍTIMA FOI CONDUZIDA PARA O PRONTO-SOCORRO MAIS PRÓXIMO PELO SAMU NA VIATURA: UBS 30 - RESP. TEC ENF. GILVANDRER. O LOCAL FOI ENTREGUE EM SEGURANÇA AOS PROPRIETÁRIOS DA RESIDÊNCIA E EM SEGUIDA VIATURA RETORNOU AO POSTO DE ORIGEM SEM ALTERAÇÃO. COMANDO DE SOCORRO: TEN BM MARCELO COORDENADOR: TEN BM GUERREIRO | K64: Ezequias Guerreiro Marques
A65: Incêndio em edificação | B65: Incêndio em residência | C65: 2023 | D65: Jan | E65: 44931 | G65: 44931 | H65: 44931 | I65: BIFMA, POSTO SUMAÚMA, ABT-32. AO COMANDO DO ST BM PABLO. DESLOCARAM-SE AO LOCAL PARA ATENDER OCORRÊNCIA DE VAZAMENTO DE GLP COM FOGO, SEGUIDO DE EXPLOSÃO. RELATO DOS MORADORES: APÓS UM PRINCÍPIO DE INCÊNDIO INICIADO NO FOGÃO, A VÁLVULA DA BOTIJA DE GÁS ROMPEU-SE, CAUSANDO ALGUMAS EXPLOSÕES, A FIM DE AJUDAR, A VÍTIMA QUEBROU UM CANO DE ÁGUA PARA SANAR O PRINCÍPIO DE INCÊNDIO, NO MESMO MOMENTO OCORREU OUTRA EXPLOSÃO, CAUSANDO AS QUEIMADURAS DE 2° GRAU, ATO CONTÍNUO, O SR RENATO CORREU ATÉ O BANHEIRO E ACABOU DESMAIANDO NO LOCAL, SENDO RESGATADO POSTERIORMENTE PELOS POPULARES DA RUA. VÍTIMA: RENATO PEREIRA DE CASTRO, IDADE: 34 ANOS, FONE: 991591615. ATUAÇÃO DA GUARNIÇÃO: APH, ISOLAMENTO DO LOCAL, RETIRADA DA BOTIJA DE GÁS EM VAZAMENTO PARA A ÁREA EXTERNA DA RESIDÊNCIA. VÍTIMA FOI CONDUZIDA PARA O PRONTO-SOCORRO MAIS PRÓXIMO PELO SAMU NA VIATURA: UBS 30 - RESP. TEC ENF. GILVANDRER. O LOCAL FOI ENTREGUE EM SEGURANÇA AOS PROPRIETÁRIOS DA RESIDÊNCIA E EM SEGUIDA VIATURA RETORNOU AO POSTO DE ORIGEM SEM ALTERAÇÃO. COMANDO DE SOCORRO: TEN BM MARCELO COORDENADOR: TEN BM GUERREIRO | K65: Ezequias Guerreiro Marques
A66: Outras ocorrências | B66: Corte de algema / anel / outros | C66: 2023 | D66: Jan | E66: 44931 | G66: 44931 | I66: 1º BI, POSTO ZUMBI, ABT-30. AO COMANDO DO SGT BM GENTIL, RELIZARAM CORTE DE ANEL DO DEDO INDICADOR DIREITO DO PACIENTE: DALMIR CARDOSO FLORES, IDADE: 22 ANOS, FONE: 993384355. OCORRÊNCIA REALIZADA SEM ALTERAÇÃO. COMANDO DE SOCORRO: TEN BM MARCELO COORDENADOR: TEN BM GUERREIRO | K66: Ezequias Guerreiro Marques
A67: Outras ocorrências | B67: Resgate de pessoa | C67: 2023 | D67: Jan | E67: 44932 | G67: 44932 | I67: 1º BI, GRANDE CIRCULAR, ABT-25. AO COMANDO DO ST BM AURÉLIO, DESLOCARAM-SE AO LOCAL PARA REALIZAR RESGATE DE 4 (QUATRO) PESSOAS, O QUAL O MOTORISTA PERDEU O CONTROLE DO VEÍCULO E VIERAM A FICAR TOMBADOS EM UMA ÁREA DE RIBANCEIRA. AÇÃO DO CORPO DE BOMBEIROS: RETIRADA DAS VÍTIMAS DO INTERIOR DO VEÍCULO E DEIXADOS EM LOCAL SEGURO. NÃO FOI NECESSÁRIO CONDUÇÃO DAS VÍTIMAS AO PRONTO SOCORRO. VÍTIMAS: (CONDUTOR) RONILSON DA SILVA SOARES, 38 ANOS, RG: 18267416, FONE: 999325-2207; ESPOSA: LUCIANE PESQUEIRA SANTOS, 36 ANOS, RG: 19453795; LUCIELE NASCIMENTO LABORDA, 19 ANOS; RYANN GABRIEL SANTOS SOARES. IDADE: 10 ANOS. VEÍCULO DO ACIDENTE: CARRO VOYAGE NPB-2063. OBS. VIATURA ABT-30 TAMBÉM DESLOCOU PARA O LOCAL PARA DAR APOIO NA OCORRÊNCIA. OBS2. COMANDO DE SOCORRO DESLOCOU-SE ATÉ O LOCAL PARA COORDENAR A OCORRÊNCIA. APÓS ORIENTAÇÕES VIATURAS RETORNARAM AOS SEUS POSTOS DE ORIGEM SEM ALTERAÇÃO. COMANDO DE SOCORRO: TEN BM MARCELO COORDENADOR: TEN BM GUERREIRO | K67: Ezequias Guerreiro Marques
A68: Outras ocorrências | B68: Prevenção - outros | C68: 2023 | D68: Jan | E68: 44932 | G68: 44932 | H68: 44932 | I68: SEG DOS POSTOS. CB MORAIS 1139 08:00 20:00 12:00 FLUVIAL 003/BBE-FLUVIAL PERMANÊNCIA CB C. NASCIMENTO 1181 08:00 20:00 12:00 CSM 002/CSM CARDÃN SGT SHIRLEY 1604 07:30 19:30 12:00 SCI - EG 012/SCI-EG REFORÇO - APH TEN MATOS 570 07:30 19:30 12:00 SCI - EG 013/SCI-EG REFORÇO DE GU ST J. SOUZA 512 07:30 19:30 12:00 SCI - EG 013/SCI-EG REFORÇO DE GU ST CARVALHO 592 07:30 19:30 12:00 SCI - EG 013/SCI-EG REFORÇO DE GU SGT WALTER 723 07:30 19:30 12:00 SCI - EG 013/SCI-EG REFORÇO DE GU TEN PRISCILA FREITAS 1838 13:00 01:00 12:00 F CECON 001/EMG/CBMAM B5/COMUNICA ÇÕES .......................... ...................................................................................... SERVIÇO DO DIA 06 DE JANEIRO DE 2024. 2º TURNO. CUMPRIRAM ESCALA EXTRA NO SERVIÇO DE S. E. G. OS MILITARES DE ACORDO COM SUAS O.S NOS REFERIDOS POSTOS OU BATALHÕES DO CBMAM. SEG 2º TURNO, S/A. SGT FIGUEIREDO 745 18:00 06:00 12:00 QCG/CBMAM 235/CIACG ATALAIA 2024010607122781371 CB MAQUINE 1156 20:00 08:00 12:00 QCG/CBMAM 002/CSM/2024 GARAGEIRO 2024010607122781371 CB SARMENTO 1105 20:00 08:00 12:00 BBE RODOVIARIA 004/BBE/2024 REFORÇO DE GU 2024010607122781371 SGT F. PAULO 735 20:00 08:00 12:00 DAT 182/2024/DAT PERMANÊCIA 2024010607122781371 SGT LUCIANE MOTA 1544 19:30 07:30 12:00 SCI - EG 012/SCI-EG REFORÇO - APH 2024010607122781371 CB WALTER FILHO 1227 19:30 07:30 12:00 SCI - EG 014/SCI-EG/2024 REFORÇO DE GU 2024010607122781371 CB KRISNA 1264 19:30 07:30 12:00 SCI - EG 014/SCI-EG/2024 REFORÇO DE GU 2024010607122781371 CB DIEGO FALCÃO 1266 19:30 07:30 12:00 SCI - EG 014/SCI-EG/2024 REFORÇO DE GU 2024010607122781371 CB ANDRÉ LUIZ 1269 19:30 07:30 12:00 SCI - EG 014/SCI-EG/2024 REFORÇO DE GU 2024010607122781371 CB VIDAL 1031 20:00 08:00 12:00 FLUVIAL-JORDÃO 003/BBE/FLUVIAL/2024 REFORÇO DE GU 2024010607122781371 TEN R.LIRA 352 19:00 07:00 12:00 COBOM 005/COBOM/CBC/2024 REFORÇO DE GU 2024010607122781371 SGT KERLI CRISTINA 1626 19:00 07:00 12:00 COBOM 006/COBOM/CBC/2024 REFORÇO DE GU 2024010607122781371 CONTROLADOR: TEN QOABM JAMERSON COMTE SOCORRO: TEN QOAB BARRETO | K68: Jamerson Marques de Castro
A69: Outras ocorrências | B69: Corte de algema / anel / outros | C69: 2023 | D69: Jan | E69: 44932 | G69: 44932 | H69: 44932 | I69: BBE, POSTO CENTRAL, VIATURA ABT-31, SOB O COMANDO DO SARGENTO BM ONOFRE, REALIZARAM CORTE DE ANEL DO DEDO ANELAR DA MÃO ESQUERDA DE: ODNEY DA SILVA PINHEIRO, ENDEREÇO, RUA ELDORADO, Nº 99, BAIRRO MONTE SINAI, 20100 RG MILITAR, CONTATO: 99391-1869. | K69: LUIZ RICARDO DE OLIVEIRA ALBUQUERQUE
A70: Outras ocorrências | B70: Lavagem de pátio ou pista | C70: 2023 | D70: Jan | E70: 44932 | G70: 44932 | H70: 44932 | I70: LAVAGEM DE PÁTIO, LOCAL: Fundação de Vigilância em Saúde - Avenida Torquato Tapajós - Colônia Santo Antônio, Manaus - Amazonas, Brasil CSM, POSTO CENTRAL, VIATURA ATA-03, SOB O COMANDO DO CB BM N. SOUSA, REALIZARAM LAVAGEM DE PÁTIO NA FUNDAÇÃO DE VIGILÂNCIA EM SAÚDE, NO LOCAL FORAM USADOS 15,000 LITROS DE ÁGUA. | K70: LUIZ RICARDO DE OLIVEIRA ALBUQUERQUE
A71: Outras ocorrências | B71: Vistoria em árvore - situação de risco | C71: 2023 | D71: Jan | E71: 44932 | G71: 44932 | H71: 44932 | I71: BBE, POSTO CENTRAL, VIATURA ABT-31, SOB O COMANDO DO SARGENTO BM ONOFRE, REALIZARAM A VISTORIA E CORTE TOTAL DE ÁRVORE TIPO ABACATEIRO, USANDO MÉTODOS DE ANCORAGEM E CORTE AMARRAÇÃO DE GALHOS E TRONCO, QUE HAVIA CAÍDO SOBRE DUAS CASAS, SOLICITANTE CASA 1: CARLOS ALBERTO DE OLIVEIRA NEVES, IDADE 56, RG 769891, RUA BENJAMIN BECHIMOL Nº 34 CONJ. PETROS, FONE 998440-1874. SOLICITANTE CASA 2, KLYNTHIA DE LIMA CAVALCANTE, IDADE 46, CPF 61351865234, RUA ALAIDE ROCHA Nº 33, FONE 9798406-2522. VISTORIA EM ÁRVORE / RISCO, ÁRVORE (ABACATEIRO) CAIU SOBRE A RESIDÊNCIA RUA BENJAMIN BENCHIMOL, 34 - CONJ. PETRO - ALEIXO PRÓXIMO A PRAÇA E A QUADRA ESPORTIVA DO PETROS CARLOS ALBERTO - 98440 1874 | K71: LUIZ RICARDO DE OLIVEIRA ALBUQUERQUE
A72: Outras ocorrências | B72: Controle de Insetos | C72: 2023 | D72: Jan | E72: 44932 | G72: 44932 | H72: 44932 | I72: COMANDANTE DE SOCORRO, VIATURA AR-55, BBE, POSTO RODOVIÁRIA, VIATURA ABT-29, SOB O COMANDO DO TENENTE BMJ BARRETO, REALIZARAM VISTORIA DE TAQUE DE ABELHA, NO LOCAL SE TRATAVA DE MIGRAÇÃO E AS ABELHAS ESTAVAM EM BARRACÃO ABANDONADO (ANTIGA MERENDA ESCOLAR), EM FRENTE AO SESI / CAFÉ DA MARI / CENTRO SOCIO-EDUCATIVO DAGMAR FEITOZA, A EQUIPE INFORMOU QUE RETORNARÁ PARA CONTROLAR AS ABELHAS AO ESCURECER, SOLICITANTE SENHORA JOSIANE SIMÕES 99529-2502. FOI INFORMADO PELO CB RENAN SANTOS QUE AO RETORNAREM AO LOCAL AS ABELHAS HAVIA MIGRADO NOVAMENTE. FIZERAM UMA VISTORIA NAS PROXIMIDADES, PORE, NÃO ENCONTRARAM MAIS OS REFERIDOS INSETOS. O LOCAL FOI ENTREGUE EM SEGURANÇA A PROPRIETARIA A SENHORA REMILDA SOUZA DOS SANTOS, 43 ANOS, RG 1979677, TEL 92 995292502. SOLICITANTE: JOSIANE SIMÕES. TEL: 92 995292502. SERVIÇO SEM ALTERAÇÃO. CONTROLADOR: TEN RICARDO COMTE SOCORRO: TEN BARRETO | K72: Jamerson Marques de Castro
A73: Outras ocorrências | B73: Corte de algema / anel / outros | C73: 2023 | D73: Jan | E73: 44933 | G73: 44933 | H73: 44933 | I73: SERVIÇO DO DIA 06 DE JANEIRO DE 2024. 2º TURNO. BBE POSTO CENTRAL ABT-31 A COMANDO DO SGT ONOFRE REALIZOU CORTE DE ANEL NO POSTO. CORTE ANEL DE OURO DO DEDO ANELAR ESQUERDO DO SENHOR EMANUEL JORGE AKEL THOMAZ DE LIMA, CPF : 122 595 432 00, TEL 92999811133, IDADE 62 ANOS, ENDEREÇO: AV EFIGÊNIO SALES RUA ANORI CASA 195 CONDOMÍNIO EFIGÊNIO SALES. SOLICITANTE: SGT ONOFRE. TEL: VIA 193. SERVIÇO SEM ALTERAÇÃO. CONTROLADOR: TEN QOABM JAMERSON COMTE SOCORRO: TEN QOAB BARRETO | K73: Jamerson Marques de Castro
A74: Outras ocorrências | B74: Vítima presa em elevador | C74: 2023 | D74: Jan | E74: 44933 | G74: 44933 | I74: VITIMA PRESA NO 7º ANDAR DO CONDOMÍNIO LONDOM. | K74: Jamerson Marques de Castro
A75: Outras ocorrências | B75: Prevenção - outros | C75: 2023 | D75: Jan | E75: 44933 | G75: 44933 | H75: 44933 | I75: SEG DO DIA 07/01/2024 1° TURNO. CB FERRAZ 1080 08:00 18:00 10:00 PONTA NEGRA 006/BIFMA/2024 PREVENÇÃO AQUÁTICA CB JORGE COELHO 1106 08:00 18:00 10:00 PONTA NEGRA 015/1°BI/2024 PREVENÇÃO AQUÁTICA CB GETTLYN 1225 08:00 20:00 12:00 DAT 181/DAT/2022 PERMANÊNCIA CB NUNES 1151 08:00 18:00 10:00 PONTA NEGRA 011/BBE/2024 PREVENÇÃO AQUÁTICA SGT DE CASTRO 719 07:30 19:30 12:00 SCI-EG 015/SCI-EG/2024 REFORÇO DE EQUIPAGEM CB NOGUEIRA 1091 07:30 19:30 12: 00 SCI-EG 015/SCI-EG/2024 REFORÇO DE EQUIPAGEM CB ASSUNÇÃO 1147 07:30 19:30 12: 00 SCI-EG 015/SCI-EG/2024 REFORÇO DE EQUIPAGEM CB RANIERE 1108 08:00 20:00 12:00 QCG 013/1°BI/2024 VOLANTE AR-55 CB VANZILER 1125 08:00 20:00 12:00 QCG 005/BBE/2024 REFORÇO DE GU SGT SILVA GUERREIRO 1676 08:00 18:00 10:00 PONTA NEGRA 001/PGGM/2024 PREVENÇÃO AQUÁTICA CB W. BATISTA 1793 08:00 18:00 10:00 PONTA NEGRA 001/PGGM/2024 PREVENÇÃO AQUÁTICA CB WANDER 1255 08:00 18:00 10:00 PONTA NEGRA 001/CIACG/2024 PREVENÇÃO AQUÁTICA ST BIANCA 629 16:00 19:00 03:00 BANDA DO DJ EVANDRO JR 189/DAT/2024 FISCALIZAÇÃO EM EVENTOS CB EDLA 1205 18:00 06:00 12:00 QCG 235/CIA CG/2024 GUARDA DO QUARTEL ST WILSON 759 19:00 21:30 02:30 QCG 004/CBC/2024 CONDUTOR SGT CHRISTIE SOUSA 1540 19:00 21:30 02:30 QCG 004/CBC/2024 REFORÇO DE GUARNIÇÃO SGT ADEILSON 1844 19:00 21:30 02:30 QCG 004/CBC/2024 REFORÇO DE GUARNIÇÃO CB EMERSON FREITAS 1052 20:00 08:00 12:00 PB FLUVIAL 004/BBE/2024 REFORÇO DE GUARNIÇÃO ST VIEIRA OAIVA 375 19:30 07:30 12:00 SCI-EG 016/SCI-EG/2024 REFORÇO DE GUARNIÇÃO CB CLEBER 1190 19:30 07:30 12:00 SCI-EG 016/SCI-EG/2024 REFORÇO DE GUARNIÇÃO CB PAULO RICARDO 1232 19:30 07:30 12:00 SCI-EG 016/SCI-EG/2024 REFORÇO DE GUARNIÇÃO CB ALAN OLIVEIRA 1128 20:00 08:00 12:00 PB CENTRAL 006/BBE/2024 REFORÇO DE GUARNIÇÃO CB PETILO 1130 20:00 08:00 12:00 QCG 014/1° BI/2024 CONDUTOR SERVIÇO DO DIA 07.01.2024 / 1º TURNO CMT DE SOCORRO: 2º TEN BM R. ARAÚJO CONTROLADOR COBOM: 1º TEN BM R. LIRA | K75: LUIZ RICARDO DE OLIVEIRA ALBUQUERQUE
A76: Outras ocorrências | B76: Prevenção aquática | C76: 2023 | D76: Jan | E76: 44933 | G76: 44933 | I76: PLANO DE OPERAÇÕES Nº 001-CBC/2024 PREVENÇÃO AQUÁTICA NA PONTA NEGRA. MISSÃO I. Prevenção Aquática e prontidão com guarda-vidas; II. Buscas, Resgates e Salvamentos; III. Socorro de emergência; DATA, EFETIVO, HORÁRIO: 07/01/2024 (Sábado), Das 08h às 18h. PLANO DE OPERAÇÕES Nº 001-CBC/2024. EVENTO: PREVENÇÃO AQUÁTICA. LOCAL: BALNEÁRIO PRAIA DA PONTA NEGRA. TÉRMINO DE PREVENÇÃO, SEM ALTERAÇÃO. SERVIÇO DO DIA 07.01.2024 / 1º TURNO CMT DE SOCORRO: 2º TEN BM R. ARAÚJO CONTROLADOR COBOM: 1º TEN BM R. LIRA - 01 BM a cargo do BBE - 01 BM a cargo do 1º BI - 01 BM a cargo da CIA CG - 01 BM a cargo do BIFMA - 02 BM a cargo da PGGM (APH) . | K76: Rozivaldo de Souza Lira
A77: Outras ocorrências | B77: Encontro de cadáver | C77: 2023 | D77: Jan | E77: 44933 | G77: 44933 | I77: Foi repassado pela PC que uma senhora está no DEHS que o filho dela estava desaparecido e ontem à noite mandaram fotos do corpo dele e informando o local. Segundo ela o corpo tá na rua Perimetral Thales Loureiro, fica por trás do café Priscilla, na av do turismo. ROCORRÊNCIA DE RESGATE/REMOÇÃO DE CADÁVER. CORPO SEM IDENTIFICAÇÃO. AÇÃO DO BOMBEIRO: REMOÇÃO DO CADÁVER EM LOCAL DE DIFÍCIL ACESSO, POR SER AMBIENTE DE SELVA E ENTREGUE À EQUIPE DO IML, VTR 667 TÉCNICO LEGISTA: SADRAQUE. EM SEGUIDA A VTR ABT-29 RETRAIU AO PB DE ORIGEM. SERVIÇO DO DIA 07.01.2024 / 1º TURNO CMT DE SOCORRO: 2º TEN BM R. ARAÚJO CONTROLADOR COBOM: 1º TEN BM R. LIRA | J77: vtr 7414/19 | K77: Rozivaldo de Souza Lira
A78: Incêndio em edificação | B78: Incêndio em apartamento | C78: 2023 | D78: Jan | E78: 44933 | G78: 44933 | I78: INCENDIO EM APARTAMENTO, PREDIO DE 3 ANDARES, SEM VITIMAS NO LOCAL. CBC; PB CENTRAL; VTR ABT-31, ATA-01, AR-55, PB RODOVIÁRIA; ABT-29. FIAT ARGO, À COMANDO DO FIEL, TC BM ANDREY. DESLOCAM AO LOCAL SOLICITADO, ATENDER OCORRÊNCIA DE INCÊNDIO EM APARTAMENTO. NARRATIVA: AS CHAMAS ATINGIRAM DOIS COMODOS DO APARTAMENTO MEDINDO 3X4. DANOS: AR CONDICIONADO, CAMA BOX, GELADEIRA, 2 ARMÁRIOS, 01 FOGÃO, ROUPAS DIVERSAS. LOCATÁRIOS: PABLO AMBRÓSIO RODRIGUES PASTRANO. 45 ANOS. NACIONALIZADE: VENEZUELANA. TEL: 98428-8851 / FRANCY DEL CARMEM. 40 ANOS. CPF: 708.834.132-80. TEL: 98483-1477 NACIONALIDADE: VENEZUELANA. AÇÃO DOS BOMBEIROS: FORAM UTILIZADOS 3.000 L DE ÁGUA NO COMBATE AO FOGO, RESCALDO, RESFRIAMENTO DO LOCAL E COLETA DE DADOS. LOCAL EM SEGURANÇA, AS VIATURAS RETREM AOS SEUS POSTOS DE ORIGEM. SERVIÇO DO DIA 07.01.2024 / 1º TURNO CMT DE SOCORRO: 2º TEN BM R. ARAÚJO CONTROLADOR COBOM: 1º TEN BM R. LIRA | K78: Rozivaldo de Souza Lira
A79: Outras ocorrências | B79: Acidente de trânsito com vítima lesionada | C79: 2023 | D79: Jan | E79: 44933 | G79: 44933 | I79: VITIMA DE ACIDENTE DE TRANSITO NA AV CEL TEIXEIRA, POPULARES ACIONARAM A UR 23 GREM; PB JAGUAR; VTR UR-23 À COMANDO DO TEN BM TOMMAZO. DESLOCA PARA ATENDER OCORRÊNCIA DE ACIDENTE DE TRÂNSITO, CARRO VS MOTO. O VÉICULO DE 4 RODAS BETEU NA MOTO E EVADIU-SE DO LOCAL. NA MOTO, VÍTIMAS, PAI E FILHO: 1ª VÍTIMA: JARDSON DA SILVA NASCIMENTO. 14 ANOS. SO2: 99 F: 76 PA: 140/100 ENDEREÇO: RUA SIMÕES LOPES NETO. Nº 8A, VILA MARINHO. COMPENSA III. 2ª VÍTIMA: JAIR CARMO NASCIMENTO. CPF: 900.371.702-97 IDADE: 40 ANOS. PA: 100/70 SPO 2: 99% 1ª VÍTIMA: DOR EM REGIÃO LOMBO SACRA E MMSS. 2ª VITMA: CORTE CONTUSO EM MÃO DIREITA. AS DUAS VÍTIMAS FORAM ENCAMINHADAS PELA VTR UR-23 AO HPS JOÃO LÚCIO, NO LOCAL, O PROFISSIONAL DE SAÚDE RESPONSÁVEL PELOS PACIENTES. MÉDOCO: BARROS NETO. CRM 2604. EM SEGUIDA A VTR UR-23 RETRAIU AO PB DE ORIGEM. SERVIÇO DO DIA 07.01.2024 / 1º TURNO CMT DE SOCORRO: 2º TEN BM R. ARAÚJO CONTROLADOR COBOM: 1º TEN BM R. LIRA | K79: Rozivaldo de Souza Lira
A80: Outras ocorrências | B80: Incêndio em veículo | C80: 2023 | D80: Jan | E80: 44933 | G80: 44933 | I80: PMAM PEDE APOIO PARA INCENDIO EM VEICULO EMBAIXO DA PASSARELA DO T4. 1º BI; PB CIS GC; VTR ABT-25 À COMANDO DOCB BM TIAGO SILVA. DESLOCA AO LOCAL SALICITADO, ATENDE ROCORRÊNCIA DE INCÊNDIO EM VEÍCULO. CARRO MODELO CITROEN, COR CINZA PLACA: NPA-8157. DANOS: PERCA TOTAL. PROPRIETÁRIO: EDGAR MENEZES. RG. 82675-5. AÇÃO DO BOMBEIRO: FORAM UTILIZADOS 2 MIL LITROS DE ÁGUA NO COMBATE ÀS CHAMAS NO VEÍCULO QUA JÁ ESTAVA TOMA DO PELO FOGO. LOCAL EM SEGURANÇA, A VTR ABT-25 RETRAI AO PB DE ORIGEM. SERVIÇO DO DIA 07.01.2024 / 1º TURNO CMT DE SOCORRO: 2º TEN BM R. ARAÚJO CONTROLADOR COBOM: 1º TEN BM R. LIRA | K80: Rozivaldo de Souza Lira
A81: Outras ocorrências | B81: Captura de insetos / abelhas / similares | C81: 2023 | D81: Jan | E81: 44933 | G81: 44933 | H81: 44933 | I81: CONTROLE DE INSETO TIPO ABELHA - RUA VIVALDO LIMA, N° 41, ALVORADA 1 PRÓXIMO A DISTRIBUIDORA BRITO. SOLICITANTE: CRISTIANE GARCIA 99529 - 2502. | K81: LUIZ RICARDO DE OLIVEIRA ALBUQUERQUE
A82: Outras ocorrências | B82: Captura de insetos / abelhas / similares | C82: 2023 | D82: Jan | E82: 44933 | G82: 44933 | I82: CONTROLE DE INSETO TIPO CABA EM ÁRVORE TIPO ABACATEIRO - RUA CAMBUCI, N° 16, NC - 09, CIDADAE NOVA 2, PRÓXIMO AO HOSPITAL FRANCISCA MENDES. SOLICITANTE: SONGELA DE ARAÚJO 98274 - 3941. BIFMA; PB SUMAÚMA; VTR ABT-32 À COMANDO DO SGT BM S. ROCHA. DESLOCA AO LOCAL SOLICITADO, ATENDER OCORRÊNCIA DE CONTROLE DE INSETOS TIPO CABA. CONTROLE REALIZADO COM SUCESSO, A VTR ABT-32 RETRAI AO PB DE ORIGEM. SERVIÇO DO DIA 07.01.2024 / 1º TURNO CMT DE SOCORRO: 2º TEN BM R. ARAÚJO CONTROLADOR COBOM: 1º TEN BM R. LIRA | K82: Rozivaldo de Souza Lira
A83: Outras ocorrências | B83: Corte de algema / anel / outros | C83: 2023 | D83: Jan | E83: 44933 | G83: 44933 | I83: CORTE DE ANEL DO PB ZUMBI. 1º BI; PB ZUMBI; A GUARNIÇÃO DA VTR ABT-30 REALIZOU CORTE DE ANEL NO DEDO ANELAR ESQUERDO. TIPO ANEL: ROMANEL. NOME: JOSEANE T. DE SOUZA. 40 ANOS. ENDEREÇO: RUA GARAPÉ DO 40 N°183 DISTRITO INDUSTRIAL TEL: 98203-0160 RG:1614447-3 SERVIÇO DO DIA 07.01.2024 / 1º TURNO CMT DE SOCORRO: 2º TEN BM R. ARAÚJO CONTROLADOR COBOM: 1º TEN BM R. LIRA | K83: Rozivaldo de Souza Lira
A84: Incêndio em vegetação | B84: Incêndio em vegetação | C84: 2023 | D84: Jan | E84: 44933 | G84: 44933 | I84: INCÊNDIO EM VEGETAÇÃO NA AV. CAMPOS SALES - SANTA ETELVINA AO LADO DO SHOPING VIA NORTE. SOLICITANTE: SACHA LOPES 99402 - 2257. BIFMA; PB SUMAÚMA; VTR ABT-32 À COMANDO DO SGT BM S. ROCHA. DESLOCA AO LOCAL SOLICITADO, ATENDER OCORRÊNCIA DE INCÊNDIO EM VEGETAÇÃO. AÇÃO DO BOMBEIRO: FORA UTILIZADOS APROXIMADAMENTE HUM MIL LITROS DE ÁGUA EM UMA ÁREA DE APROXIMADAMENTE 300m². LOCAL EM SERGURANÇA, A VTR ABT-32 RETRAI AO PB DE ORIGEM. SERVIÇO DO DIA 07.01.2024 / 1º TURNO CMT DE SOCORRO: 2º TEN BM R. ARAÚJO CONTROLADOR COBOM: 1º TEN BM R. LIRA | K84: Rozivaldo de Souza Lira
A85: Outras ocorrências | B85: Encontro de cadáver | C85: 2023 | D85: Jan | E85: 44933 | G85: 44933 | H85: 44933 | I85: 37 em frente graja yano am 010 sentido rio preto 92991227814 Solicitante informa que acharam um corpo. BBE, POSTO RODOVIÁRIA, VIATURA ABT-29, SOB O COMANDO DO ST BM ESMERALDO, BBE, POSTO RODOVIÁRIA, VIATURA ABT-29, SOB O COMANDO DO ST BM ESMERALDO, EM APOIO A POLICIA MILITAR REALIZARA O RESGATE DE CADAVER JÁ EM ESTADO AVANÇADO DE PUTREFAÇÃO, APROXIMADAMENTE 3M DA MARGEM DA AM 010. O MESMO ESTAVA EM UMA PEQUENA RIBANCEIRA, FEITO A REMOÇÃO DO LOCAL DE DIFÍCIL ACESSO E COLOCADO NA MARGEM, CORPO FICOU SOBRE CUIDADOS DA POLICIA MILITAR. | K85: LUIZ RICARDO DE OLIVEIRA ALBUQUERQUE
A86: Outras ocorrências | B86: Prevenção em festas / eventos diversos | C86: 2023 | D86: Jan | E86: 44933 | G86: 44933 | H86: 44933 | I86: ORDEM DE SERVIÇO Nº 003/BBE/CBC-2024. 1. EVENTO: Presença em evento de aniversário. - 07/01/2024 - sábado - 19H 2. MISSÃO: realizar a presença no aniversário de uma criança, fã dos bombeiros; Avenida Igarapé de Manaus, QD 1A, BL 08, Apt0 06 - Centro procurar a Sra Leciane Santos (92) 993290579. BBE, POSTO CENTRA, VIATURA ABT-31, CUNMPRIU ORDEM DE SERVIÇO Nº 003/BBE/CBC-2024, EVENTO: PRESENÇA EM EVENTO DE ANIVERSÁRIO. - 07/01/2024 - SÁBADO - 19H, MISSÃO: REALIZAR A PRESENÇA NO ANIVERSÁRIO DE UMA CRIANÇA, FÃ DOS BOMBEIROS; AVENIDA IGARAPÉ DE MANAUS, QD 1A, BL 08, APT0 06 ¿ CENTRO, SOLICITANTE A SRA LECIANE SANTOS (92) 993290579. | K86: LUIZ RICARDO DE OLIVEIRA ALBUQUERQUE
A87: Outras ocorrências | B87: Prevenção em festas / eventos diversos | C87: 2023 | D87: Jan | E87: 44933 | G87: 44933 | H87: 44933 | I87: ORDEM DE SERVIÇO Nº 004-CBC/2024. 1. EVENTO: Chegada da Kamélia. 2. MISSÃO: Apoiar o evento com viatura para o transporte da boneca da Kamélia; 3. CRONOGRAMA: 07/01/2024 - Sábado 19h00min - QCG/CBMAM - Apresentação da equipe 19h50min - Aeroporto Internacional Eduardo Gomes - Início da carretada 21h30min - QCG/CBMAM - Previsão de término da operação ST BM WILSON (0759) - Condutor 3º SGT BM CHRISTIE SOUZA (1540) 3º SGT BM ADEILSON (1844) -AR-47 a cargo do CSM/CBMAM POSTO CENTRAL, CBC, VIATUIRA AR-47, SOB O COMANDO DO ST BM WILSON, CUMPRIRAM, ORDEM DE SERVIÇO Nº 004-CBC/2024. EVENTO: CHEGADA DA KAMÉLIA. MISSÃO: APOIAR O EVENTO COM VIATURA PARA O TRANSPORTE DA BONECA DA KAMÉLIA;. CRONOGRAMA: 07/01/2024 ¿ SÁBADO, 19H00MIN - QCG/CBMAM - APRESENTAÇÃO DA EQUIPE, 19H50MIN - AEROPORTO INTERNACIONAL EDUARDO GOMES - INÍCIO DA CARRETADA, 21H30MIN - QCG/CBMAM - PREVISÃO DE TÉRMINO DA OPERAÇÃO, ST BM WILSON (0759) ¿ CONDUTOR, 3º SGT BM CHRISTIE SOUZA (1540), 3º SGT BM ADEILSON (1844), -AR-47 A CARGO DO CSM/CBMAM | K87: LUIZ RICARDO DE OLIVEIRA ALBUQUERQUE
A88: Incêndio em edificação | B88: Incêndio em comércio de pequeno ou médio porte em depósito | C88: 2023 | D88: Jan | E88: 44933 | G88: 44933 | I88: 1 BI, POSTO CIS GRANDE CIRCULAR, VIATURA ABT-25, SOB O CONMANDO DO CB BM TIAGO SILVA, DESLOCARAM PARA PRINCÍPIO DE INCÊNDIO EM COMERCIO NO LOCAL SE TRATAVA DE CURTO CIRCUITO E FOI CONTROLADO POR POPULARES, NO LOCALE STAVA A PROPRIETÁRIA A SENHORA PATRICIA - 99355 6047, AÇÃO DA EQUIPE FOI VISTORIA. PRÓXIMO AO IML, LOCAL É NO COMERCIAL PATRICIA. RUA CURRAIS NOVOS, ANTIGA RUA 248, NUCLEO 23 - CIDADE NOVA | K88: LUIZ RICARDO DE OLIVEIRA ALBUQUERQUE
A89: Outras ocorrências | B89: Acidente de trânsito com vítima | C89: 2023 | D89: Jan | E89: 44933 | G89: 44933 | H89: 44934 | I89: COMANDANTE DE SOCORRO, VIATURA AR-55, BIFMA, PARQUE SUMAUMA, VIATURA ABT-32, 1º BI, POSTO CIS GRANDE CIRCULAR, VIATURA ABT-35, SOB O COMANDO DO TENENTE BM R. ARAÚJO, DESLOCARAM PARA ACIDENTE DE TRÂNSITO COM VÍTIMA TRAVESSA BUSIOS, FRAC MENSDE4S, PX A IGREJA MARANTA, SOLICITANTE CB PM SOUZA - CIOPS BIFMA, PARQUE SUMAUMA, VIATURA ABT-32, SOB O COMAN DO ST BM S. ROCHA, CHEGANDO NA CENA JÁ SE ENCONTRAVA IML. PM. SIC, UMA SENHORA CONDUZINDO SEU VEÍCULO FRONTIER AUTOMÁTICO DE COR PRETA PLACA NON-8129, QUE NÃO SE ENCONTRAVA MAIS NO LOCAL ATROPELOU E VITIMOU UMA SENHORA POR NOME MEIRIVAN SOARES DE OLIVEIRA 32 ANOS E UMA CRIANÇA DE 2 ANOS.NA ABORDAGEM A CRIANÇA JÁ HAVIA SIDO CONDUZIDO AO HOSPITAL PLATÃO ARAÚJO E A SENHORA SE ENCONTRAVA EM BAIXO DO VEÍCULO PRESA NA FERRAGEM FEITO AVALIAÇÃO NO LOCAL, AÇÃO DO BOMBEIRO FOI RETIRAR A VÍTIMA DEBAIXO DO VEÍCULO ENTREGUE AO IML. FOI UTILIZADO DESENCARCERADOR PARA IÇAR O VEICULO QUE FOI ENTREGUE AOS CUIDADOS DA PM: CB J. BRAGA, CB VIDAL, VTR 1702, EQUIPE IML, CONDUTOR MARTINS SADRAC, VTR 667, EQUIPE PERICIA, PERITO SERUDO, PERITO MAIKE, FAROL DARLAN, VTR 2005, DELEGADO 6 DIP SR MÁRIO. INVESTIGADOR CHARLIES | K89: LUIZ RICARDO DE OLIVEIRA ALBUQUERQUE
A90: Outras ocorrências | B90: Corte de algema / anel / outros | C90: 2023 | D90: Jan | E90: 44933 | G90: 44933 | H90: 44933 | I90: CORTE DE ANEL REALIZADO PELA EQUIPE DO POSTO ZUMBI. | K90: LUIZ RICARDO DE OLIVEIRA ALBUQUERQUE
A91: Outras ocorrências | B91: Suicídio | C91: 2023 | D91: Jan | E91: 44933 | G91: 44933 | H91: 44934 | I91: O VIGILANTE DA PONTE VIU GUANDO UM HOMEM SE APROXIMOU DO VÃO PRINCIPAL DA PONTE E SE JOGOU DA MESMA, TENDO AINDA AVISTADO O CORPO BOIANDO NO RIO, DEIXANDO UMA MOCHILA NO LOCAL. SUICIDIO (SEXO MASCULINO) NA PONTE RIO NEGRO SENTIDO IRANDUBA X MANAUS RODRIGO ARAUJO VIGILANTE DA PONTE 99387 8285 BBE, PELOTÃO FLUVIAL, LANCHA RIO MADEIRA, SOB O COMANDO DO CB BM MORAIS, EM APOIO A POLICA MILITAR DESLOCARAM PARA A PONTE SOBFRE O RIO NEGRO ONDE O VIGILANTE DA PONTE O SENHOR RODRIGO ARAUJO, CONTATO 99387 8285, VIU GUANDO UM HOMEM SE APROXIMOU DO VÃO PRINCIPAL DA PONTE E SE JOGOU DA MESMA, TENDO AINDA AVISTADO O CORPO BOIANDO NO RIO, DEIXANDO UMA MOCHILA NO LOCAL, NA MOCHILA ESTAVA OS DOCUMENTOS PESSOAIS DE: DANIEL SAN ABREU DO CARMO, 25 ANOS, ENDEREÇO: RUA AJURICABA, Nº 866, BAIRRO SÃO JORGE, A EQUIPE DO PELOTÃO FLUVIAL RELIZOU BUSCAS DE SUPERFICIE SEM EXITO. COMANDO DE SOCORRO: TEN BM R. ARAÚJO COORDENADOR: TEN BM RICARDO. .............................................................. SERVIÇO DO DIA 10 DE JANEIRO DE 2024. 1º TURNO. NO SERVIÇO DE HOJE O CB MORAIS NA LANCHA RIO MADEIRA DEU INICIO AS BUSCAS AS 08:30 AS 17:00, POREM SEM EXITO.EM ANDAMENTO... CONTROLADOR: TEN QOABM JAMERSON COMTE SOCORRO: TEN QOAB R. PEREIRA NO DIA 08/01/2022, ÀS 08H00MIN, A EQUIPE DO PELOTÃO FLUVIAL: CB BM PICANÇO E CB BM JOILDO, RETORNARAM AO LOCAL PARA PROSSEGUIMENTO NAS BUSCAS. EM ANDAMENTO. COMANDO DE SOCORRO: TEN BM MARCELO COORDENADOR: TEN BM GUERREIRO --------------------------------------------------------------------------------------------------------------------------------------------------------------------- BBE, PELOTÃO FLUVIAL, LANCHA RIO MADEIRA, SOB O COMANDO DO CB BM MORAIS, EM APOIO A POLÍCIA MILITAR, DESLOCARAM-SE À PONTE SOBRE O RIO NEGRO, ONDE O VIGILANTE DA PONTE O SENHOR RODRIGO ARAUJO, CONTATO 99387 8285, VIU QUANDO UM HOMEM SE APROXIMOU DO VÃO PRINCIPAL DA PONTE E SE JOGOU DA MESMA, TENDO AINDA AVISTADO O CORPO BOIANDO NO RIO, DEIXANDO UMA MOCHILA NO LOCAL, NA MOCHILA ESTAVA OS DOCUMENTOS PESSOAIS DE: DANIEL SAN ABREU DO CARMO, 25 ANOS, ENDEREÇO: RUA AJURICABA, Nº 866, BAIRRO: SÃO JORGE, A EQUIPE DO PELOTÃO FLUVIAL RELIZOU BUSCAS DE SUPERFICIE SEM ÊXITO. NO DIA 08/01/2022, ÀS 08H00MIN, A EQUIPE DO PELOTÃO FLUVIAL: CB BM PICANÇO E CB BM JOILDO, RETORNARAM AO LOCAL PARA PROSSEGUIMENTO NAS BUSCAS. 09/01/2024 ÀS 09h30 A LANCHA RIO MADEIRA, COMPOSTA PELOS MILITARES, CB BM EMERSON FREITAS E CB BM FABIANO, DESLOCA PARA A ÁREA DA PONTE RIO NEGRO, DAR CONTINUIDADE AS BUSCAS PELA PASSOA DESAPARECIDA EM MEIO LÍQUIDO, NA PARTE DA TARDE, A LANCHA RIO MADEIRA DEU CONTINUIDADE JUNTO COM FAMILIARES DO DESAPARECIDO ATÉ ÀS 17h00. SEM ÊXITO. EM ANDAMENTO... SERVIÇO DO DIA 09.01.2024 / 1º TURNO CMT DE SOCORRO: 1º TEN BM TOMÁS CONTROLADOR COBOM: 1º TEN BM R. LIRA ................................................. SERVIÇO DO DIA 15 DE JANEIRO DE 2024. 1º TURNO. NÃO FOI REALIZADO BUSCAS NO DIA DE HOJE. SEM ATUALIZAÇÕES. CONTROLADOR: TEN QOABM JAMERSON COMTE SOCORRO: TEN QOAB TOMÁS .......................... ................................ ........................ SERVIÇO DO DIA 16 DE JANEIRO DE 2024. 2º TURNO. NÃO FOI REALIZADO BUSCAS NO DIA DE HOJE. SEM ATUALIZAÇÕES. CONTROLADOR: TEN QOABM JAMERSON COMTE SOCORRO: TEN QOAB JONATAS ................................................................................................... SERVIÇO DO DIA 25 DE JANEIRO DE 2024. 1º TURNO. NÃO FOI REALIZADO BUSCAS NO DIA DE HOJE. SEM ATUALIZAÇÕES. CONTROLADOR: TEN QOABM JAMERSON COMTE SOCORRO: TEN QOAB R. ARAUJO ---------------------------------------------------- INFORMO-VOS QUE DURANTE O SERVIÇO DO DIA 29.01.-1º TURNO, NENHUMA INFORMAÇÃO FOI REPASSADA A ESTE CENTRO. EM ANDAMENTO COMANDO DE SOCORRO: TEN BM ALTACI CONTROLADORA COBOM/CICC: ST BM CONCEIÇÃO --------------------- ------------------------------------------------------------------------------------
A92: Outras ocorrências | B92: Corte de algema / anel / outros | C92: 2023 | D92: Jan | E92: 44934 | G92: 44934 | H92: 44934 | I92: CORTE ANEL Nome: Camilla Alselma dos Santos Idade 28 Anos RG 25712098 Fone. 981955774 Ind. Rua Dos Palmeiras N°26 Bairro Zumbi III DEDO ANELAR DA MÃO ESQUERDA TIPO DE AÇO CIRÚRGICO. | K92: LUIZ RICARDO DE OLIVEIRA ALBUQUERQUE
A93: Outras ocorrências | B93: Atendimento pré-hospitalar transporte de paciente | C93: 2023 | D93: Jan | E93: 44934 | G93: 44934 | I93: ALFA 03-SCI AEREOPORTO DESLOCOU SE NO HORARIO DAS 03:35 DO AEREOPORTO ATÉ A UPA CAMPOS SALES PARA REALIZAR TRANSPORTE DE PACIENTE. EM ANDAMEBNTO... SCI, POSTO AEROPORTO, VIATURA ALFA-01, SOB O COMANDO DO DA SARGENTO BM SARA DIANNEREALIZARAM TRANSPORTE DE PACIENTE: GLAUCO ARAÚJO DA CRUZ, 06 ANOS, PACIENTE ONCOLÓGICO, TRATAMENTO EM SÃO PAULO, ORIUNDO DE AMAZONAS CIDADE DE BARCELOS, 3 RETINOBLASTOMA COM LADO ESQUERDO COMPROMETIDO. SINAIS: 5 EPISÓDIOS EMÉTICOS, DOR ABDOMINAL, FOI DEIXADO NA UPA CAMPOS SALES, ENTREGUE AOS CUIDADOS DO MEDICO WILIAN SILVA, CRM 11422. | K93: LUIZ RICARDO DE OLIVEIRA ALBUQUERQUE
A94: Outras ocorrências | B94: Prevenção - outros | C94: 2023 | D94: Jan | E94: 44934 | G94: 44934 | H94: 44934 | I94: S.E.G NOS POSTOS DO CBMAM NA DATA DE 08 DE JAN DE 2024. CB DE PAULA 1084 07:30 19:30 12:00 1º BI 017/1º B.I/2024 PERMANÊNCIA CB GOUVÉIA 1117 08:00 18:00 10:00 PRAIA DA PONTA NEGRA 006/BIFMA/2024 GUARDA-VIDAS CB JONAS 1089 08:00 18:00 10:00 PRAIA DA PONTA NEGRA 016/1º B.I/2024 GUARDA-VIDAS CB OTÁVIO JOSÉ 1081 08:00 18:00 10:00 PRAIA DA PONTA NEGRA 012/BBE/2024 GUARDA-VIDAS SGT DAMIANE 1651 08:00 18:00 10:00 PRAIA DA PONTA NEGRA 001/DG/PGGM/2024 GUARDA-VIDAS CB MARGALHO 1785 08:00 18:00 10:00 PRAIA DA PONTA NEGRA 001/DG/PGGM/2024 GUARDA-VIDAS SGT FIGUEIREDO 745 08:00 18:00 10:00 PRAIA DA PONTA NEGRA 001/CIA CG/2024 GUARDA-VIDAS ST ARILSON 572 07:30 19:30 12:00 SCI AEROPORTO 017/SCI/2024 REFORÇO DE GUARNIÇÃO ST VIVALDO 619 07:30 19:30 12:00 SCI AEROPORTO 017/SCI/2024 REFORÇO DE GUARNIÇÃO ST HELDER 738 07:30 19:30 12:00 SCI AEROPORTO 017/SCI/2024 REFORÇO DE GUARNIÇÃO CB MORAIS 1139 08:00 20:00 12:00 PB FLUVIAL 004/BBE/2024 PERMANÊNCIA CB PIMENTEL 1188 08:00 20:00 12:00 PB RODOVIÁRIA 009/BBE/2024 CONDUTOR ABT-29 CB MAIK 1244 08:00 20:00 12:00 PB CENTRAL 007/BBE/2024 CONDUTOR ABT-31 COMANDO DE SOCORRO: TEN BM MARCELO COORDENADOR: TEN BM GUERREIRO --------------------------------------------------------------------------------------------------------------------------------------------------------------- SGT WENDEL 706 19:30 07:30 12:00 SCI-EG 018/SCI-EG/2024 REFORÇO DE EQUIPAGEM CB GENIVALDO 1193 19:30 07:30 12:00 SCI-EG 018/SCI-EG/2024 REFORÇO DE EQUIPAGEM CB GERÔNIMO 1202 19:30 07:30 12: 00 SCI-EG 018/SCI-EG/2024 REFORÇO DE EQUIPAGEM CB SARNEY 1223 19:30 07:30 12:00 PB DRAGÃO 018/1°BI/2024 PERMANÊNCIA CB AZEVEDO 1208 20:00 08:00 12:00 PB FLUVIAL 004/BBE/2024 REFORÇO DE GUARNIÇÃO SGT GUTEMBERGUE 741 20:00 08:00 12:00 DAT 182/DAT/2022 PERMANÊNCIA SGT JEFERSON 1533 18:00 06:00 12:00 QCG 235/CIACG/2022 SENTINELA ARMADA CB ED SOUZA 1192 20:00 08:00 12:00 QCG 008/BBE/2024 VOLANTE ABT - 31 SERVIÇO DO DIA 08.01.2024 / 2º TURNO CMT DE SOCORRO: 2º TEN BM MARCELO CONTROLADOR COBOM: 1º TEN BM R. LIRA | K94: Rozivaldo de Souza Lira
A95: Outras ocorrências | B95: Prevenção aquática | C95: 2023 | D95: Jan | E95: 44934 | G95: 44934 | H95: 44934 | I95: PLANO DE OPERAÇÕES Nº 001-CBC/2024. AO COMANDO DO SGT BM LEANDRO NUNES, CUMPRIRAM A PREVENÇÃO AQUÁTICA NA PRAIA DA PONTA NEGRA. HORÁRIO: DAS 08h00 ÀS 18h00MIN. OBS. FOI LOCALIZADA UMA CRIANÇA PERDIDA: MARIA CLARA BARBOSA BATISTA, E ENTREGUE A SUA MÃE: PATRÍCIA CALDAS BARBOSA, FONE: 995287326. PREVENÇÃO FINALIZADA ÀS 18H00MIN, SEM ALTERAÇÃO. COMANDO DE SOCORRO: TEN BM MARCELO COORDENADOR: TEN BM GUERREIRO | K95: Ezequias Guerreiro Marques
A96: Outras ocorrências | B96: Controle de Insetos | C96: 2023 | D96: Jan | E96: 44934 | G96: 44934 | I96: 1º BI, POSTO ZUMBI, ABT-30. AO COMANDO DO CB BM JORGE COELHO, DESLOCARAM-SE AO LOCAL PARA REALIZAR CONTROLE DE INSETOS. CHEGANDO AO LOCAL FOI CONSTATADO UMA CASA DE INSETOS DA ESPÉCIE CABAS. SOLICITANTE: SRA. FRANCIMARA FONE: 985879085. FOI REALIZADO O CONTROLE TOTAL DOS INSETOS. OCORRÊNCIA FINALIZADA SEM ALTERAÇÃO. COMANDO DE SOCORRO: TEN BM MARCELO COORDENADOR: TEN BM GUERREIRO | K96: Ezequias Guerreiro Marques
A97: Outras ocorrências | B97: Atendimento pré-hospitalar | C97: 2023 | D97: Jan | E97: 44934 | G97: 44934 | H97: 44934 | I97: GREM, PONTA NEGRA, UR-23. AO COMANDO DO TEN BM ANDRÉ JESUS, REALIZARAM ATENDIMENTO PRÉ-HOSPITALAR DA PACIENTE: JOSIANA ALBUQUERQUE NOGUEIRA, 39, RUA ÁGUA BRANCA S/N, SÃO JOSÉ, CPF: 73825069249, FONE: 92994997808, DN 20/01/83. PACIENTE TRABALHA NA COZINHA DO ACAMPAMENTO, OBESA, QUEIXADO DE TONTURA, NEGA COMORBIDADES, APRESENTANDO QUADRO HIPERTENSIVO, RECUSA SER REMOVIDA PARA ATENDIMENTO MÉDICO. OCORRÊNCIA FINALIZADA S/A. COMANDO DE SOCORRO: TEN BM MARCELO COORDENADOR: TEN BM GUERREIRO | K97: Ezequias Guerreiro Marques
A98: Outras ocorrências | B98: Suicídio | C98: 2023 | D98: Jan | E98: 44934 | G98: 44934 | H98: 44934 | I98: Comunicante informa que seu cunhado cometeu suicídio Rua Faveiro, Monte das Oliveiras. Obs: casa s/n, porém familiares estariam na frente da residência, que aparentemente estaria trancada. NÃO HOUVE NECESSIDADE DE ATUAÇÃO DO CORPO DE BOMBEIROS. | J98: Equipes Policia Civil acionadas às 15h30 DEHS/IPC LEONEL IC/Ana Telma IML/Natalia Equipes Policia Civil em deslocamento: As 15h45 - DEHS na vtr 311 com os investigadores Leonel e Elinaldo, delegado Gustavo Cerqueira. As /16h10 - IC na VTR 2001 com o motorista Marcelo, e peritos Amanda e Cleber. As /16h13 - IML na VTR 670, com o motorista Tony, e auxiliar Felipe. PM SGT FRANCISCO JUNIOR E G. MORENO 7210 26 CICOM. | K98: Ezequias Guerreiro Marques
A99: Outras ocorrências | B99: Controle de Insetos | C99: 2023 | D99: Jan | E99: 44934 | G99: 44934 | I99: SR. EDUARDO FONE: 991435656, PEDE APOIO PARA CONTROLE DE INSETO TIPO CABA ALOJADA NO TETO DA AREA EXTERNA DA SUA CASA. NA RUA 47, N. 1042, JAPIIM 1, MORRO DA PREGUIÇA PROXIMO AO SUPERMERCADO ATACADAO. 'BBE, POSTO CENTRAL, ABT-31. AO COMANDO DO SGT BM PARDO, DESLOCARAM-SE AO LOCAL PARA REALIZAR CONTROLE DE INSETO. EM ANDAMENTO. COMANDO DE SOCORRO: TEN BM MARCELO COORDENADOR: TEN BM GUERREIRO ---------------------------------------------------------------------------------------------------------------------------------------------------------------------------- BBE; PB CENTRAL; VTR ABT-31 À COMANDO DO SGT BM PARDO. DESLOCA AO LOCAL SOLICITADO, ATENDER OCORRÊNCIA DE CONTROLE DE INSETOS TIPO CABA. SOLICITANTE: EDUARDO BALDIVEZO SILVA. 73 ANOS. CPF: 022.606.112-49 CONTROLE DREALIZADO COM SUCESSO, A VTR ABT-31 RETRAI AO PB DE ORIGEM. SERVIÇO DO DIA 08.01.2024 / 2º TURNO CMT DE SOCORRO: 2º TEN BM MARCELO CONTROLADOR COBOM: 1º TEN BM R. LIRA | K99: Rozivaldo de Souza Lira
A100: Incêndio em edificação | B100: Vazamento de glp com fogo | C100: 2023 | D100: Jan | E100: 44935 | G100: 44935 | I100: PROPRIETARIA INFORMA QIE SUA BOTIJA DE GAS ESTA VAZANDO COM FOGO. 1º BI; PB CIS GC; VTR ABT-25 À COAMNDO DO SGT BM ARILDO. DESLOCA AO LOCAL SOLICITADO, ATENDER OCORRÊNCIA DE VAZAMENTO DE GLP COM FOGO. AO CHEGAR NO LOCAL, O FOGO JÁ HAVIA SIDO CONTROLADO. SOLICITANTE: IVANETE ALVES LEÃO. CPF: 000.826.822-32 FONE: 92 99267-8488 ENDEREÇO: RUA CAREIRO CASTANHA 988. BAIRRO: VAL PARAÍSO II. AÇÃO DO CORPO DE BOMBEIROS: REALIZOU A VENTILAÇÃO NO LOCAL E FEZ A INSPEÇÃO NOS COMPARTIMENTOS E NOS EQUIPAMENTOS, E ORIENTOU A PROPRIETÁRIA A MUDAR O SISTEMA DE VÁLVULA DE CONEXÃO DO FOGÃO PARA O BOTIJÃO GLP, POIS O MESMO ENCONTRAVA -SE DANIFICADO. LOCAL EM SEGURANÇA, A VTR ABT-25 RETRAIU AO PB DE ORIGEM. SERVIÇO DO DIA 08.01.2024 / 2º TURNO CMT DE SOCORRO: 2º TEN BM MARCELO CONTROLADOR COBOM: 1º TEN BM R. LIRA | K100: Rozivaldo de Souza Lira
...

Sheet RELATORIO.
A1: CORPO DE BOMBEIROS MILITAR DO AMAZONAS
A2: RELATÓRIO DE OCORRÊNCIAS DE INCÊNDIOS FLORESTAIS 2024
A3: 1 | B3: Comandante do Incidente: | G3: CEL QOBM MENEZES
A4: 2 | B4: Chefe de Operações Capital: | G4: TC QOBM RICARDO
A5: 3 | B5: Chefe de Operações Interior: | G5: TC QOBM MONTEIRO
A6: 4 | B6: Coordenador da Sala de Situação: | G6: TC QOBM ANDREY
A7: 5 | B7: Período Operacional: | G7: 02/JUL/2024- 08h00 às 20h
A8: 6 | B8: Próximo Período Operacional: | G8: 03/JUL/2024-8h00
A9: 7 | B9: Reunião de Planejamento: | G9: 02/JUL/2024-8h15
A10: 8 | B10: Reunião de Briefing: | G10: 02/JUL/2024-8h30
A12: EFETIVO | W12: EFETIVO
A13: Nº | B13: MUNICÍPIO | C13: ADMINISTRAÇÃO | D13: SERV. ORDINÁRIO | E13: SEG | F13: BM CÉU LIMPO | G13: BM ACEIRO | H13: FORÇA NACIONAL | I13: BDA FLORESTAL | J13: BDA CIVIL | K13: DC MUNICIPAL | L13: TRIP. AVIÃO | M13: OUTROS | N13: TOTAL | O13: OPERAÇÃO | W13: MISSÃO | X13: CAPITAL | Y13: INTERIOR | Z13: TOTAL
A14: 1 | B14: Manaus | C14: 52 | D14: 100 | E14: 10 | F14: 4 | N14: 166 | O14: CÉU LIMPO | W14: ADMINISTRAÇÃO | X14: 52 | Y14: 24 | Z14: 76
A15: 2 | B15: Iranduba | C15: 2 | D15: 3 | E15: 1 | N15: 6 | W15: SERVIÇO ORDINÁRIO | X15: 100 | Y15: 43 | Z15: 143
A16: 3 | B16: Manacapuru | C16: 1 | D16: 6 | N16: 7 | W16: SEG | X16: 10 | Y16: 2 | Z16: 12
A17: 4 | B17: Novo Airão | C17: 2 | D17: 2 | J17: 3 | N17: 7 | W17: BM CÉU LIMPO | X17: 4 | Y17: 0 | Z17: 4
A18: 5 | B18: Pres. Figueiredo | C18: 2 | D18: 6 | N18: 8 | W18: BM ACEIRO | X18: 0 | Y18: 98 | Z18: 98
A19: 6 | B19: Rio Preto da Eva | C19: 4 | D19: 3 | E19: 1 | N19: 8 | W19: FORÇA NACIONAL | X19: 0 | Y19: 18 | Z19: 18
B20: TOTAL CÉU LIMPO | C20: 63 | D20: 120 | E20: 12 | F20: 4 | G20: 0 | H20: 0 | I20: 0 | J20: 3 | K20: 0 | L20: 0 | M20: 0 | N20: 202 | W20: BDA FLORESTAL | X20: 0 | Y20: 2 | Z20: 2
A21: 1 | B21: Itacoatiara | C21: 2 | D21: 3 | N21: 5 | O21: CBI | W21: BDA CIVIL | X21: 0 | Y21: 33 | Z21: 33
A22: 2 | B22: Parintins | C22: 4 | D22: 5 | N22: 9 | W22: DC MUNICIPAL | X22: 0 | Y22: 0 | Z22: 0
A23: 3 | B23: Tabatinga | C23: 4 | D23: 4 | I23: 2 | N23: 10 | W23: TRIP. AVIÃO | X23: 0 | Y23: 0 | Z23: 0
A24: 4 | B24: Tefé | C24: 1 | D24: 2 | J24: 3 | N24: 6 | W24: OUTROS | X24: 0 | Y24: 0 | Z24: 0
B25: TOTAL CBI | C25: 11 | D25: 14 | E25: 0 | F25: 0 | G25: 0 | H25: 0 | I25: 2 | J25: 3 | K25: 0 | L25: 0 | M25: 0 | N25: 30 | W25: Total | X25: 166 | Y25: 220 | Z25: 386
A26: 1 | B26: Apuí | G26: 8 | H26: 8 | N26: 16 | O26: ACEIRO
A27: 2 | B27: Autazes | D27: 3 | G27: 8 | N27: 11
A28: 3 | B28: Boca do Acre | G28: 8 | H28: 4 | N28: 12
A29: 4 | B29: Canutama | G29: 5 | N29: 5
A30: 5 | B30: Careiro Castanho | D30: 3 | G30: 8 | J30: 13 | N30: 24
A31: 6 | B31: Humaitá | C31: 2 | G31: 20 | H31: 2 | N31: 24
A32: 7 | B32: Lábrea | G32: 8 | H32: 4 | N32: 12
A33: 8 | B33: Manaquiri | D33: 3 | G33: 8 | N33: 11
A34: 9 | B34: Manicoré | G34: 7 | J34: 8 | N34: 15
A35: 10 | B35: Maués | G35: 7 | J35: 6 | N35: 13
A36: 11 | B36: Novo Aripuanã | G36: 6 | N36: 6
A37: 12 | B37: Tapauá | G37: 5 | N37: 5
B38: TOTAL ACEIRO | C38: 2 | D38: 9 | E38: 0 | F38: 0 | G38: 98 | H38: 18 | I38: 0 | J38: 27 | K38: 0 | L38: 0 | M38: 0 | N38: 154
B39: TOTAL GERAL | C39: 76 | D39: 143 | E39: 12 | F39: 4 | G39: 98 | H39: 18 | I39: 2 | J39: 33 | K39: 0 | L39: 0 | M39: 0 | N39: 386
A41: RECURSOS | AC41: RESUMO RECURSOS
A42: Nº | B42: MUNICÍPIO | C42: ABT | D42: AT | E42: ATP | F42: ATA | G42: ABF | H42: ABS | I42: PIPA | J42: DOSA | K42: CRS | L42: AR | M42: ATM | N42: UR | O42: MT | P42: TA | Q42: EMBARCAÇÃO | R42: PICAPE FN | S42: PICAPE MUNI | T42: PICAPE SSP | U42: HELICÓPTERO | V42: AVIÃO | W42: JET SKI | X42: QUADRICICLO | Y42: AEM | Z42: TOTAL | AA42: OPERAÇÃO | AC42: RECURSOS | AD42: QTD
A43: 1 | B43: Manaus | C43: 7 | D43: 1 | F43: 1 | J43: 3 | K43: 1 | L43: 4 | N43: 4 | Q43: 2 | T43: 1 | Y43: 1 | Z43: 25 | AA43: CÉU LIMPO | AC43: ABT | AD43: 13
A44: 2 | B44: Iranduba | C44: 1 | O44: 1 | Z44: 2 | AC44: AT | AD44: 3
A45: 3 | B45: Manacapuru | C45: 1 | N45: 1 | O45: 1 | Q45: 1 | Z45: 4 | AC45: ATP | AD45: 1
A46: 4 | B46: Novo Airão | C46: 1 | F46: 1 | L46: 1 | Q46: 1 | Z46: 4 | AC46: ATA | AD46: 2
A47: 5 | B47: Pres. Figueiredo | C47: 1 | N47: 1 | O47: 1 | Q47: 1 | Z47: 4 | AC47: ABF | AD47: 2
A48: 6 | B48: Rio Preto da Eva | C48: 1 | L48: 1 | N48: 1 | O48: 2 | Q48: 1 | Z48: 6 | AC48: ABS | AD48: 3
B49: TOTAL CÉU LIMPO | C49: 12 | D49: 1 | E49: 0 | F49: 2 | G49: 0 | H49: 0 | I49: 0 | J49: 3 | K49: 1 | L49: 6 | M49: 0 | N49: 7 | O49: 5 | P49: 0 | Q49: 6 | R49: 0 | S49: 0 | T49: 1 | U49: 0 | V49: 0 | W49: 0 | X49: 0 | Y49: 1 | Z49: 45 | AC49: PIPA | AD49: 0
A50: 1 | B50: Itacoatiara | H50: 1 | L50: 1 | O50: 1 | Q50: 1 | Z50: 4 | AA50: CBI | AC50: CCI/DOSA | AD50: 3
A51: 2 | B51: Parintins | D51: 1 | H51: 1 | N51: 1 | O51: 2 | Q51: 1 | Z51: 6 | AC51: CRS | AD51: 1
A52: 3 | B52: Tabatinga | D52: 1 | L52: 1 | O52: 2 | P52: 1 | Z52: 5 | AC52: AR | AD52: 19
A53: 4 | B53: Tefé | C53: 1 | H53: 1 | L53: 1 | N53: 1 | O53: 2 | Q53: 1 | Z53: 7 | AC53: ATM | AD53: 0
B54: TOTAL CBI | C54: 1 | D54: 2 | E54: 0 | F54: 0 | G54: 0 | H54: 3 | I54: 0 | J54: 0 | K54: 0 | L54: 3 | M54: 0 | N54: 2 | O54: 7 | P54: 1 | Q54: 3 | R54: 0 | S54: 0 | T54: 0 | U54: 0 | V54: 0 | W54: 0 | X54: 0 | Y54: 0 | Z54: 22 | AC54: UR | AD54: 9
A55: 1 | B55: Apuí | L55: 1 | R55: 1 | Z55: 2 | AA55: ACEIRO | AC55: MT | AD55: 14
A56: 2 | B56: Autazes | S56: 1 | Z56: 1 | AC56: TA | AD56: 1
A57: 3 | B57: Boca do Acre | L57: 1 | R57: 1 | Z57: 2 | AC57: EMBARCAÇÃO | AD57: 10
A58: 4 | B58: Canutama | S58: 1 | Z58: 1 | AC58: PICAPES | AD58: 6
A59: 5 | B59: Careiro Castanho | L59: 1 | Z59: 1 | AC59: HELICÓPTERO | AD59: 0
A60: 6 | B60: Humaitá | E60: 1 | G60: 2 | L60: 1 | O60: 2 | Q60: 1 | Z60: 7 | AC60: AVIÃO | AD60: 0
A61: 7 | B61: Lábrea | L61: 1 | R61: 1 | Z61: 2 | AC61: JET SKI | AD61: 0
A62: 8 | B62: Manaquiri | L62: 1 | Z62: 1 | AC62: QUADRICICLO | AD62: 0
A63: 9 | B63: Manicoré | L63: 1 | Z63: 1 | AC63: AEM | AD63: 1
A64: 10 | B64: Maués | L64: 1 | Z64: 1 | AC64: TOTAL | AD64: 88
A65: 11 | B65: Novo Aripuanã | L65: 1 | Z65: 1
A66: 12 | B66: Tapauá | L66: 1 | Z66: 1
B67: TOTAL ACEIRO | C67: 0 | D67: 0 | E67: 1 | F67: 0 | G67: 2 | H67: 0 | I67: 0 | J67: 0 | K67: 0 | L67: 10 | M67: 0 | N67: 0 | O67: 2 | P67: 0 | Q67: 1 | R67: 3 | S67: 2 | T67: 0 | U67: 0 | V67: 0 | W67: 0 | X67: 0 | Y67: 0 | Z67: 21
B68: TOTAL GERAL | C68: 13 | D68: 3 | E68: 1 | F68: 2 | G68: 2 | H68: 3 | I68: 0 | J68: 3 | K68: 1 | L68: 19 | M68: 0 | N68: 9 | O68: 14 | P68: 1 | Q68: 10 | R68: 3 | S68: 2 | T68: 1 | U68: 0 | V68: 0 | W68: 0 | X68: 0 | Y68: 1 | Z68: 88
A70: OCORRÊNCIAS DIÁRIAS EM | D70: 45468 | V70: OCORRÊNCIAS 03/06/2024 A | Y70: 45477
A71: Nº | B71: MUNICÍPIO | C71: INCÊNDIO EDIFICAÇÃO | D71: INCÊNDIO FLORESTAL | E71: FOCOS | F71: TOTAL DE OCORRÊNCIAS DE INCÊNDIO (S/ FOCOS) | V71: Nº | W71: MUNICÍPIO | X71: OCORRÊNCIAS INCÊNDIO EDIFICAÇÃO | Y71: OCORRÊNCIAS INCÊNDIO FLORESTAL | Z71: FOCOS | AA71: TOTAL DE OCORRÊNCIAS (S/ FOCOS)
A72: 1 | B72: Manaus | C72: =COUNTIFS(DADOS!$C:$C,$B72,DADOS!$D:$D, $D$70, DADOS!$F:$F, "INCÊNDIO EM EDIFICAÇÃO") -> 0 | D72: =COUNTIFS(DADOS!$C:$C,$B72,DADOS!$D:$D, $D$70, DADOS!$F:$F, "INCÊNDIO FLORESTAL") -> 0 | E72: =SUMIFS(DADOS!$G:$G, DADOS!$C:$C, $B72, DADOS!$D:$D, $D$70) -> 0 | F72: =SUM(C72:D72) -> 0 | V72: 1 | W72: Manaus | X72: 47 | Y72: =COUNTIFS(DADOS!$C:$C,$W72,DADOS!$D:$D, "<=" & $Y$70, DADOS!$F:$F, "INCÊNDIO FLORESTAL") -> 27 | Z72: =SUMIFS(DADOS!$G:$G, DADOS!$C:$C, $W72, DADOS!$D:$D, "<=" & $Y$70) -> 26 | AA72: 56
A73: 2 | B73: Iranduba | C73: =COUNTIFS(DADOS!$C:$C,$B73,DADOS!$D:$D, $D$70, DADOS!$F:$F, "INCÊNDIO EM EDIFICAÇÃO") -> 0 | D73: =COUNTIFS(DADOS!$C:$C,$B73,DADOS!$D:$D, $D$70, DADOS!$F:$F, "INCÊNDIO FLORESTAL") -> 1 | E73: =SUMIFS(DADOS!$G:$G, DADOS!$C:$C, $B73, DADOS!$D:$D, $D$70) -> 1 | F73: =SUM(C73:D73) -> 1 | V73: 2 | W73: Iranduba | X73: =COUNTIFS(DADOS!$C:$C,$W73,DADOS!$D:$D, "<=" & $Y$70, DADOS!$F:$F, "INCÊNDIO EM EDIFICAÇÃO") -> 0 | Y73: =COUNTIFS(DADOS!$C:$C,$W73,DADOS!$D:$D, "<=" & $Y$70, DADOS!$F:$F, "INCÊNDIO FLORESTAL") -> 4 | Z73: =SUMIFS(DADOS!$G:$G, DADOS!$C:$C, $W73, DADOS!$D:$D, "<=" & $Y$70) -> 12 | AA73: 0
A74: 3 | B74: Manacapuru | C74: =COUNTIFS(DADOS!$C:$C,$B74,DADOS!$D:$D, $D$70, DADOS!$F:$F, "INCÊNDIO EM EDIFICAÇÃO") -> 0 | D74: =COUNTIFS(DADOS!$C:$C,$B74,DADOS!$D:$D, $D$70, DADOS!$F:$F, "INCÊNDIO FLORESTAL") -> 0 | E74: =SUMIFS(DADOS!$G:$G, DADOS!$C:$C, $B74, DADOS!$D:$D, $D$70) -> 0 | F74: =SUM(C74:D74) -> 0 | V74: 3 | W74: Manacapuru | X74: =COUNTIFS(DADOS!$C:$C,$W74,DADOS!$D:$D, "<=" & $Y$70, DADOS!$F:$F, "INCÊNDIO EM EDIFICAÇÃO") -> 0 | Y74: =COUNTIFS(DADOS!$C:$C,$W74,DADOS!$D:$D, "<=" & $Y$70, DADOS!$F:$F, "INCÊNDIO FLORESTAL") -> 2 | Z74: =SUMIFS(DADOS!$G:$G, DADOS!$C:$C, $W74, DADOS!$D:$D, "<=" & $Y$70) -> 1 | AA74: 0
A75: 4 | B75: Novo Airão | C75: =COUNTIFS(DADOS!$C:$C,$B75,DADOS!$D:$D, $D$70, DADOS!$F:$F, "INCÊNDIO EM EDIFICAÇÃO") -> 0 | D75: =COUNTIFS(DADOS!$C:$C,$B75,DADOS!$D:$D, $D$70, DADOS!$F:$F, "INCÊNDIO FLORESTAL") -> 0 | E75: =SUMIFS(DADOS!$G:$G, DADOS!$C:$C, $B75, DADOS!$D:$D, $D$70) -> 0 | F75: =SUM(C75:D75) -> 0 | V75: 4 | W75: Novo Airão | X75: =COUNTIFS(DADOS!$C:$C,$W75,DADOS!$D:$D, "<=" & $Y$70, DADOS!$F:$F, "INCÊNDIO EM EDIFICAÇÃO") -> 0 | Y75: =COUNTIFS(DADOS!$C:$C,$W75,DADOS!$D:$D, "<=" & $Y$70, DADOS!$F:$F, "INCÊNDIO FLORESTAL") -> 2 | Z75: =SUMIFS(DADOS!$G:$G, DADOS!$C:$C, $W75, DADOS!$D:$D, "<=" & $Y$70) -> 6 | AA75: 0
A76: 5 | B76: Pres. Figueiredo | C76: =COUNTIFS(DADOS!$C:$C,$B76,DADOS!$D:$D, $D$70, DADOS!$F:$F, "INCÊNDIO EM EDIFICAÇÃO") -> 0 | D76: =COUNTIFS(DADOS!$C:$C,$B76,DADOS!$D:$D, $D$70, DADOS!$F:$F, "INCÊNDIO FLORESTAL") -> 0 | E76: =SUMIFS(DADOS!$G:$G, DADOS!$C:$C, $B76, DADOS!$D:$D, $D$70) -> 0 | F76: =SUM(C76:D76) -> 0 | V76: 5 | W76: Pres. Figueiredo | X76: =COUNTIFS(DADOS!$C:$C,$W76,DADOS!$D:$D, "<=" & $Y$70, DADOS!$F:$F, "INCÊNDIO EM EDIFICAÇÃO") -> 0 | Y76: =COUNTIFS(DADOS!$C:$C,$W76,DADOS!$D:$D, "<=" & $Y$70, DADOS!$F:$F, "INCÊNDIO FLORESTAL") -> 0 | Z76: =SUMIFS(DADOS!$G:$G, DADOS!$C:$C, $W76, DADOS!$D:$D, "<=" & $Y$70) -> 0 | AA76: 0
A77: 6 | B77: Rio Preto da Eva | C77: =COUNTIFS(DADOS!$C:$C,$B77,DADOS!$D:$D, $D$70, DADOS!$F:$F, "INCÊNDIO EM EDIFICAÇÃO") -> 0 | D77: =COUNTIFS(DADOS!$C:$C,$B77,DADOS!$D:$D, $D$70, DADOS!$F:$F, "INCÊNDIO FLORESTAL") -> 0 | E77: =SUMIFS(DADOS!$G:$G, DADOS!$C:$C, $B77, DADOS!$D:$D, $D$70) -> 0 | F77: =SUM(C77:D77) -> 0 | V77: 6 | W77: Rio Preto da Eva | X77: =COUNTIFS(DADOS!$C:$C,$W77,DADOS!$D:$D, "<=" & $Y$70, DADOS!$F:$F, "INCÊNDIO EM EDIFICAÇÃO") -> 0 | Y77: =COUNTIFS(DADOS!$C:$C,$W77,DADOS!$D:$D, "<=" & $Y$70, DADOS!$F:$F, "INCÊNDIO FLORESTAL") -> 1 | Z77: =SUMIFS(DADOS!$G:$G, DADOS!$C:$C, $W77, DADOS!$D:$D, "<=" & $Y$70) -> 4 | AA77: 0
A78: 7 | B78: Itacoatiara | C78: =COUNTIFS(DADOS!$C:$C,$B78,DADOS!$D:$D, $D$70, DADOS!$F:$F, "INCÊNDIO EM EDIFICAÇÃO") -> 0 | D78: =COUNTIFS(DADOS!$C:$C,$B78,DADOS!$D:$D, $D$70, DADOS!$F:$F, "INCÊNDIO FLORESTAL") -> 0 | E78: =SUMIFS(DADOS!$G:$G, DADOS!$C:$C, $B78, DADOS!$D:$D, $D$70) -> 0 | F78: =SUM(C78:D78) -> 0 | V78: 7 | W78: Itacoatiara | X78: =COUNTIFS(DADOS!$C:$C,$W78,DADOS!$D:$D, "<=" & $Y$70, DADOS!$F:$F, "INCÊNDIO EM EDIFICAÇÃO") -> 0 | Y78: =COUNTIFS(DADOS!$C:$C,$W78,DADOS!$D:$D, "<=" & $Y$70, DADOS!$F:$F, "INCÊNDIO FLORESTAL") -> 0 | Z78: =SUMIFS(DADOS!$G:$G, DADOS!$C:$C, $W78, DADOS!$D:$D, "<=" & $Y$70) -> 0 | AA78: 0
A79: 7 | B79: Nova Olinda do Norte | C79: =COUNTIFS(DADOS!$C:$C,$B79,DADOS!$D:$D, $D$70, DADOS!$F:$F, "INCÊNDIO EM EDIFICAÇÃO") -> 0 | D79: =COUNTIFS(DADOS!$C:$C,$B79,DADOS!$D:$D, $D$70, DADOS!$F:$F, "INCÊNDIO FLORESTAL") -> 0 | E79: =SUMIFS(DADOS!$G:$G, DADOS!$C:$C, $B79, DADOS!$D:$D, $D$70) -> 0 | F79: =SUM(C79:D79) -> 0 | V79: 7 | W79: Nova Olinda do Norte | X79: =COUNTIFS(DADOS!$C:$C,$W79,DADOS!$D:$D, "<=" & $Y$70, DADOS!$F:$F, "INCÊNDIO EM EDIFICAÇÃO") -> 0 | Y79: =COUNTIFS(DADOS!$C:$C,$W79,DADOS!$D:$D, "<=" & $Y$70, DADOS!$F:$F, "INCÊNDIO FLORESTAL") -> 0 | Z79: =SUMIFS(DADOS!$G:$G, DADOS!$C:$C, $W79, DADOS!$D:$D, "<=" & $Y$70) -> 0 | AA79: 0
A80: 8 | B80: Parintins | C80: =COUNTIFS(DADOS!$C:$C,$B80,DADOS!$D:$D, $D$70, DADOS!$F:$F, "INCÊNDIO EM EDIFICAÇÃO") -> 0 | D80: =COUNTIFS(DADOS!$C:$C,$B80,DADOS!$D:$D, $D$70, DADOS!$F:$F, "INCÊNDIO FLORESTAL") -> 0 | E80: =SUMIFS(DADOS!$G:$G, DADOS!$C:$C, $B80, DADOS!$D:$D, $D$70) -> 0 | F80: =SUM(C80:D80) -> 0 | V80: 8 | W80: Parintins | X80: =COUNTIFS(DADOS!$C:$C,$W80,DADOS!$D:$D, "<=" & $Y$70, DADOS!$F:$F, "INCÊNDIO EM EDIFICAÇÃO") -> 0 | Y80: =COUNTIFS(DADOS!$C:$C,$W80,DADOS!$D:$D, "<=" & $Y$70, DADOS!$F:$F, "INCÊNDIO FLORESTAL") -> 1 | Z80: =SUMIFS(DADOS!$G:$G, DADOS!$C:$C, $W80, DADOS!$D:$D, "<=" & $Y$70) -> 1 | AA80: 2
A81: 9 | B81: Tabatinga | C81: =COUNTIFS(DADOS!$C:$C,$B81,DADOS!$D:$D, $D$70, DADOS!$F:$F, "INCÊNDIO EM EDIFICAÇÃO") -> 0 | D81: =COUNTIFS(DADOS!$C:$C,$B81,DADOS!$D:$D, $D$70, DADOS!$F:$F, "INCÊNDIO FLORESTAL") -> 0 | E81: =SUMIFS(DADOS!$G:$G, DADOS!$C:$C, $B81, DADOS!$D:$D, $D$70) -> 0 | F81: =SUM(C81:D81) -> 0 | V81: 9 | W81: Tabatinga | X81: =COUNTIFS(DADOS!$C:$C,$W81,DADOS!$D:$D, "<=" & $Y$70, DADOS!$F:$F, "INCÊNDIO EM EDIFICAÇÃO") -> 0 | Y81: =COUNTIFS(DADOS!$C:$C,$W81,DADOS!$D:$D, "<=" & $Y$70, DADOS!$F:$F, "INCÊNDIO FLORESTAL") -> 1 | Z81: =SUMIFS(DADOS!$G:$G, DADOS!$C:$C, $W81, DADOS!$D:$D, "<=" & $Y$70) -> 8 | AA81: 0
A82: 10 | B82: Tefé | C82: =COUNTIFS(DADOS!$C:$C,$B82,DADOS!$D:$D, $D$70, DADOS!$F:$F, "INCÊNDIO EM EDIFICAÇÃO") -> 0 | D82: =COUNTIFS(DADOS!$C:$C,$B82,DADOS!$D:$D, $D$70, DADOS!$F:$F, "INCÊNDIO FLORESTAL") -> 0 | E82: =SUMIFS(DADOS!$G:$G, DADOS!$C:$C, $B82, DADOS!$D:$D, $D$70) -> 0 | F82: =SUM(C82:D82) -> 0 | V82: 10 | W82: Tefé | X82: =COUNTIFS(DADOS!$C:$C,$W82,DADOS!$D:$D, "<=" & $Y$70, DADOS!$F:$F, "INCÊNDIO EM EDIFICAÇÃO") -> 0 | Y82: =COUNTIFS(DADOS!$C:$C,$W82,DADOS!$D:$D, "<=" & $Y$70, DADOS!$F:$F, "INCÊNDIO FLORESTAL") -> 2 | Z82: =SUMIFS(DADOS!$G:$G, DADOS!$C:$C, $W82, DADOS!$D:$D, "<=" & $Y$70) -> 2 | AA82: 1
A83: 11 | B83: Apuí | C83: =COUNTIFS(DADOS!$C:$C,$B83,DADOS!$D:$D, $D$70, DADOS!$F:$F, "INCÊNDIO EM EDIFICAÇÃO") -> 0 | D83: =COUNTIFS(DADOS!$C:$C,$B83,DADOS!$D:$D, $D$70, DADOS!$F:$F, "INCÊNDIO FLORESTAL") -> 0 | E83: =SUMIFS(DADOS!$G:$G, DADOS!$C:$C, $B83, DADOS!$D:$D, $D$70) -> 0 | F83: =SUM(C83:D83) -> 0 | V83: 11 | W83: Apuí | X83: =COUNTIFS(DADOS!$C:$C,$W83,DADOS!$D:$D, "<=" & $Y$70, DADOS!$F:$F, "INCÊNDIO EM EDIFICAÇÃO") -> 0 | Y83: =COUNTIFS(DADOS!$C:$C,$W83,DADOS!$D:$D, "<=" & $Y$70, DADOS!$F:$F, "INCÊNDIO FLORESTAL") -> 6 | Z83: =SUMIFS(DADOS!$G:$G, DADOS!$C:$C, $W83, DADOS!$D:$D, "<=" & $Y$70) -> 54 | AA83: =SUM(X83:Y83) -> 6
A84: 12 | B84: Autazes | C84: =COUNTIFS(DADOS!$C:$C,$B84,DADOS!$D:$D, $D$70, DADOS!$F:$F, "INCÊNDIO EM EDIFICAÇÃO") -> 0 | D84: =COUNTIFS(DADOS!$C:$C,$B84,DADOS!$D:$D, $D$70, DADOS!$F:$F, "INCÊNDIO FLORESTAL") -> 0 | E84: =SUMIFS(DADOS!$G:$G, DADOS!$C:$C, $B84, DADOS!$D:$D, $D$70) -> 0 | F84: =SUM(C84:D84) -> 0 | V84: 12 | W84: Autazes | X84: =COUNTIFS(DADOS!$C:$C,$W84,DADOS!$D:$D, "<=" & $Y$70, DADOS!$F:$F, "INCÊNDIO EM EDIFICAÇÃO") -> 0 | Y84: =COUNTIFS(DADOS!$C:$C,$W84,DADOS!$D:$D, "<=" & $Y$70, DADOS!$F:$F, "INCÊNDIO FLORESTAL") -> 3 | Z84: =SUMIFS(DADOS!$G:$G, DADOS!$C:$C, $W84, DADOS!$D:$D, "<=" & $Y$70) -> 32 | AA84: 4
A85: 13 | B85: Boca do Acre | C85: =COUNTIFS(DADOS!$C:$C,$B85,DADOS!$D:$D, $D$70, DADOS!$F:$F, "INCÊNDIO EM EDIFICAÇÃO") -> 0 | D85: =COUNTIFS(DADOS!$C:$C,$B85,DADOS!$D:$D, $D$70, DADOS!$F:$F, "INCÊNDIO FLORESTAL") -> 1 | E85: =SUMIFS(DADOS!$G:$G, DADOS!$C:$C, $B85, DADOS!$D:$D, $D$70) -> 13 | F85: =SUM(C85:D85) -> 1 | V85: 13 | W85: Boca do Acre | X85: =COUNTIFS(DADOS!$C:$C,$W85,DADOS!$D:$D, "<=" & $Y$70, DADOS!$F:$F, "INCÊNDIO EM EDIFICAÇÃO") -> 0 | Y85: =COUNTIFS(DADOS!$C:$C,$W85,DADOS!$D:$D, "<=" & $Y$70, DADOS!$F:$F, "INCÊNDIO FLORESTAL") -> 12 | Z85: =SUMIFS(DADOS!$G:$G, DADOS!$C:$C, $W85, DADOS!$D:$D, "<=" & $Y$70) -> 59 | AA85: 7
A86: 14 | B86: Canutama | C86: =COUNTIFS(DADOS!$C:$C,$B86,DADOS!$D:$D, $D$70, DADOS!$F:$F, "INCÊNDIO EM EDIFICAÇÃO") -> 0 | D86: =COUNTIFS(DADOS!$C:$C,$B86,DADOS!$D:$D, $D$70, DADOS!$F:$F, "INCÊNDIO FLORESTAL") -> 0 | E86: =SUMIFS(DADOS!$G:$G, DADOS!$C:$C, $B86, DADOS!$D:$D, $D$70) -> 0 | F86: =SUM(C86:D86) -> 0 | V86: 14 | W86: Canutama | X86: =COUNTIFS(DADOS!$C:$C,$W86,DADOS!$D:$D, "<=" & $Y$70, DADOS!$F:$F, "INCÊNDIO EM EDIFICAÇÃO") -> 0 | Y86: =COUNTIFS(DADOS!$C:$C,$W86,DADOS!$D:$D, "<=" & $Y$70, DADOS!$F:$F, "INCÊNDIO FLORESTAL") -> 2 | Z86: =SUMIFS(DADOS!$G:$G, DADOS!$C:$C, $W86, DADOS!$D:$D, "<=" & $Y$70) -> 18 | AA86: 0
A87: 15 | B87: Careiro Castanho | C87: =COUNTIFS(DADOS!$C:$C,$B87,DADOS!$D:$D, $D$70, DADOS!$F:$F, "INCÊNDIO EM EDIFICAÇÃO") -> 0 | D87: =COUNTIFS(DADOS!$C:$C,$B87,DADOS!$D:$D, $D$70, DADOS!$F:$F, "INCÊNDIO FLORESTAL") -> 0 | E87: =SUMIFS(DADOS!$G:$G, DADOS!$C:$C, $B87, DADOS!$D:$D, $D$70) -> 0 | F87: =SUM(C87:D87) -> 0 | V87: 15 | W87: Careiro Castanho | X87: =COUNTIFS(DADOS!$C:$C,$W87,DADOS!$D:$D, "<=" & $Y$70, DADOS!$F:$F, "INCÊNDIO EM EDIFICAÇÃO") -> 0 | Y87: =COUNTIFS(DADOS!$C:$C,$W87,DADOS!$D:$D, "<=" & $Y$70, DADOS!$F:$F, "INCÊNDIO FLORESTAL") -> 5 | Z87: =SUMIFS(DADOS!$G:$G, DADOS!$C:$C, $W87, DADOS!$D:$D, "<=" & $Y$70) -> 11 | AA87: 2
A88: 16 | B88: Humaitá | C88: =COUNTIFS(DADOS!$C:$C,$B88,DADOS!$D:$D, $D$70, DADOS!$F:$F, "INCÊNDIO EM EDIFICAÇÃO") -> 0 | D88: =COUNTIFS(DADOS!$C:$C,$B88,DADOS!$D:$D, $D$70, DADOS!$F:$F, "INCÊNDIO FLORESTAL") -> 3 | E88: =SUMIFS(DADOS!$G:$G, DADOS!$C:$C, $B88, DADOS!$D:$D, $D$70) -> 18 | F88: =SUM(C88:D88) -> 3 | V88: 16 | W88: Humaitá | X88: =COUNTIFS(DADOS!$C:$C,$W88,DADOS!$D:$D, "<=" & $Y$70, DADOS!$F:$F, "INCÊNDIO EM EDIFICAÇÃO") -> 0 | Y88: =COUNTIFS(DADOS!$C:$C,$W88,DADOS!$D:$D, "<=" & $Y$70, DADOS!$F:$F, "INCÊNDIO FLORESTAL") -> 33 | Z88: =SUMIFS(DADOS!$G:$G, DADOS!$C:$C, $W88, DADOS!$D:$D, "<=" & $Y$70) -> 246 | AA88: 34
A89: 17 | B89: Lábrea | C89: =COUNTIFS(DADOS!$C:$C,$B89,DADOS!$D:$D, $D$70, DADOS!$F:$F, "INCÊNDIO EM EDIFICAÇÃO") -> 0 | D89: =COUNTIFS(DADOS!$C:$C,$B89,DADOS!$D:$D, $D$70, DADOS!$F:$F, "INCÊNDIO FLORESTAL") -> 0 | E89: =SUMIFS(DADOS!$G:$G, DADOS!$C:$C, $B89, DADOS!$D:$D, $D$70) -> 0 | F89: =SUM(C89:D89) -> 0 | V89: 17 | W89: Lábrea | X89: =COUNTIFS(DADOS!$C:$C,$W89,DADOS!$D:$D, "<=" & $Y$70, DADOS!$F:$F, "INCÊNDIO EM EDIFICAÇÃO") -> 0 | Y89: =COUNTIFS(DADOS!$C:$C,$W89,DADOS!$D:$D, "<=" & $Y$70, DADOS!$F:$F, "INCÊNDIO FLORESTAL") -> 6 | Z89: =SUMIFS(DADOS!$G:$G, DADOS!$C:$C, $W89, DADOS!$D:$D, "<=" & $Y$70) -> 30 | AA89: 5
A90: 18 | B90: Manaquiri | C90: =COUNTIFS(DADOS!$C:$C,$B90,DADOS!$D:$D, $D$70, DADOS!$F:$F, "INCÊNDIO EM EDIFICAÇÃO") -> 0 | D90: =COUNTIFS(DADOS!$C:$C,$B90,DADOS!$D:$D, $D$70, DADOS!$F:$F, "INCÊNDIO FLORESTAL") -> 1 | E90: =SUMIFS(DADOS!$G:$G, DADOS!$C:$C, $B90, DADOS!$D:$D, $D$70) -> 1 | F90: =SUM(C90:D90) -> 1 | V90: 18 | W90: Manaquiri | X90: =COUNTIFS(DADOS!$C:$C,$W90,DADOS!$D:$D, "<=" & $Y$70, DADOS!$F:$F, "INCÊNDIO EM EDIFICAÇÃO") -> 0 | Y90: =COUNTIFS(DADOS!$C:$C,$W90,DADOS!$D:$D, "<=" & $Y$70, DADOS!$F:$F, "INCÊNDIO FLORESTAL") -> 8 | Z90: =SUMIFS(DADOS!$G:$G, DADOS!$C:$C, $W90, DADOS!$D:$D, "<=" & $Y$70) -> 22 | AA90: 9
A91: 19 | B91: Manicoré | C91: =COUNTIFS(DADOS!$C:$C,$B91,DADOS!$D:$D, $D$70, DADOS!$F:$F, "INCÊNDIO EM EDIFICAÇÃO") -> 0 | D91: =COUNTIFS(DADOS!$C:$C,$B91,DADOS!$D:$D, $D$70, DADOS!$F:$F, "INCÊNDIO FLORESTAL") -> 0 | E91: =SUMIFS(DADOS!$G:$G, DADOS!$C:$C, $B91, DADOS!$D:$D, $D$70) -> 0 | F91: =SUM(C91:D91) -> 0 | V91: 19 | W91: Manicoré | X91: =COUNTIFS(DADOS!$C:$C,$W91,DADOS!$D:$D, "<=" & $Y$70, DADOS!$F:$F, "INCÊNDIO EM EDIFICAÇÃO") -> 0 | Y91: =COUNTIFS(DADOS!$C:$C,$W91,DADOS!$D:$D, "<=" & $Y$70, DADOS!$F:$F, "INCÊNDIO FLORESTAL") -> 7 | Z91: =SUMIFS(DADOS!$G:$G, DADOS!$C:$C, $W91, DADOS!$D:$D, "<=" & $Y$70) -> 43 | AA91: 8
A92: 20 | B92: Maués | C92: =COUNTIFS(DADOS!$C:$C,$B92,DADOS!$D:$D, $D$70, DADOS!$F:$F, "INCÊNDIO EM EDIFICAÇÃO") -> 0 | D92: =COUNTIFS(DADOS!$C:$C,$B92,DADOS!$D:$D, $D$70, DADOS!$F:$F, "INCÊNDIO FLORESTAL") -> 0 | E92: =SUMIFS(DADOS!$G:$G, DADOS!$C:$C, $B92, DADOS!$D:$D, $D$70) -> 0 | F92: =SUM(C92:D92) -> 0 | V92: 20 | W92: Maués | X92: =COUNTIFS(DADOS!$C:$C,$W92,DADOS!$D:$D, "<=" & $Y$70, DADOS!$F:$F, "INCÊNDIO EM EDIFICAÇÃO") -> 0 | Y92: =COUNTIFS(DADOS!$C:$C,$W92,DADOS!$D:$D, "<=" & $Y$70, DADOS!$F:$F, "INCÊNDIO FLORESTAL") -> 2 | Z92: =SUMIFS(DADOS!$G:$G, DADOS!$C:$C, $W92, DADOS!$D:$D, "<=" & $Y$70) -> 6 | AA92: 1
A93: 21 | B93: Novo Aripuanã | C93: =COUNTIFS(DADOS!$C:$C,$B93,DADOS!$D:$D, $D$70, DADOS!$F:$F, "INCÊNDIO EM EDIFICAÇÃO") -> 0 | D93: =COUNTIFS(DADOS!$C:$C,$B93,DADOS!$D:$D, $D$70, DADOS!$F:$F, "INCÊNDIO FLORESTAL") -> 1 | E93: =SUMIFS(DADOS!$G:$G, DADOS!$C:$C, $B93, DADOS!$D:$D, $D$70) -> 2 | F93: =SUM(C93:D93) -> 1 | V93: 21 | W93: Novo Aripuanã | X93: =COUNTIFS(DADOS!$C:$C,$W93,DADOS!$D:$D, "<=" & $Y$70, DADOS!$F:$F, "INCÊNDIO EM EDIFICAÇÃO") -> 0 | Y93: =COUNTIFS(DADOS!$C:$C,$W93,DADOS!$D:$D, "<=" & $Y$70, DADOS!$F:$F, "INCÊNDIO FLORESTAL") -> 5 | Z93: =SUMIFS(DADOS!$G:$G, DADOS!$C:$C, $W93, DADOS!$D:$D, "<=" & $Y$70) -> 13 | AA93: 5
A94: 22 | B94: Tapauá | C94: =COUNTIFS(DADOS!$C:$C,$B94,DADOS!$D:$D, $D$70, DADOS!$F:$F, "INCÊNDIO EM EDIFICAÇÃO") -> 0 | D94: =COUNTIFS(DADOS!$C:$C,$B94,DADOS!$D:$D, $D$70, DADOS!$F:$F, "INCÊNDIO FLORESTAL") -> 0 | E94: =SUMIFS(DADOS!$G:$G, DADOS!$C:$C, $B94, DADOS!$D:$D, $D$70) -> 0 | F94: =SUM(C94:D94) -> 0 | V94: 22 | W94: Tapauá | X94: =COUNTIFS(DADOS!$C:$C,$W94,DADOS!$D:$D, "<=" & $Y$70, DADOS!$F:$F, "INCÊNDIO EM EDIFICAÇÃO") -> 0 | Y94: =COUNTIFS(DADOS!$C:$C,$W94,DADOS!$D:$D, "<=" & $Y$70, DADOS!$F:$F, "INCÊNDIO FLORESTAL") -> 0 | Z94: =SUMIFS(DADOS!$G:$G, DADOS!$C:$C, $W94, DADOS!$D:$D, "<=" & $Y$70) -> 0 | AA94: 0
B95: TOTAL | C95: =SUM(C72:C94) -> 0 | D95: =SUM(D72:D94) -> 7 | E95: =SUM(E72:E94) -> 35 | F95: =SUM(F72:F94) -> 7 | W95: TOTAL | X95: =SUM(X72:X94) -> 47 | Y95: =SUM(Y72:Y94) -> 129 | Z95: =SUM(Z72:Z94) -> 594 | AA95: 142
A97: HOJE | V97: DE 03/06/2024 ATÉ | Y97: =Y70 -> 45477
A98: REGIÃO | C98: INC. EDIF | D98: INC. FLORESTAL | E98: FOCOS | F98: TOTAL DE OCORRÊNCIAS (S/ FOCOS) | V98: REGIÃO | X98: INC. EDIF | Y98: INC. FLORESTAL | Z98: FOCOS | AA98: TOTAL DE OCORRÊNCIAS (S/ FOCOS)
A99: CAPITAL | C99: =C72 -> 0 | D99: =D72 -> 0 | E99: =E72 -> 0 | F99: =SUM(D99) -> 0 | V99: CAPITAL | X99: =X72 -> 47 | Y99: =Y72 -> 27 | Z99: =Z72 -> 26 | AA99: =SUM(X99:Y99) -> 74
A100: INTERIOR | C100: =SUM(C73:C94) -> 0 | D100: =SUM(D73:D94) -> 7 | E100: =SUM(E73:E94) -> 35 | F100: =SUM(D100) -> 7 | V100: INTERIOR | X100: =SUM(X73:X94) -> 0 | Y100: =SUM(Y73:Y94) -> 102 | Z100: =SUM(Z73:Z94) -> 568 | AA100: =SUM(X100:Y100) -> 102
A101: TOTAL | C101: =SUM(C99:C100) -> 0 | D101: =SUM(D99:D100) -> 7 | E101: =SUM(E99:E100) -> 35 | F101: =SUM(D101) -> 7 | V101: TOTAL | X101: =SUM(X99:X100) -> 47 | Y101: =SUM(Y99:Y100) -> 129 | Z101: =SUM(Z99:Z100) -> 594 | AA101: =SUM(AA99:AA100) -> 176
A128: OBSERVAÇÕES
